Workbook
Name AprStart: WEEKDAY(DATE(_xleta.Year,4,1))
Name AprStart: WEEKDAY(DATE(_xleta.Year,4,1))
Name AprStart: WEEKDAY(DATE(_xleta.Year,4,1))
Name AprStart: WEEKDAY(DATE(_xleta.Year,4,1))
Name AprStart: WEEKDAY(DATE(_xleta.Year,4,1))
Name AprStart: WEEKDAY(DATE(_xleta.Year,4,1))
Name AprStart: WEEKDAY(DATE(_xleta.Year,4,1))
Name AprStart: WEEKDAY(DATE(_xleta.Year,4,1))
Name AprStart: WEEKDAY(DATE(_xleta.Year,4,1))
Name AprStart: WEEKDAY(DATE(_xleta.Year,4,1))
Name AugStart: WEEKDAY(DATE(_xleta.Year,8,1))
Name AugStart: WEEKDAY(DATE(_xleta.Year,8,1))
Name AugStart: WEEKDAY(DATE(_xleta.Year,8,1))
Name AugStart: WEEKDAY(DATE(_xleta.Year,8,1))
Name AugStart: WEEKDAY(DATE(_xleta.Year,8,1))
Name AugStart: WEEKDAY(DATE(_xleta.Year,8,1))
Name AugStart: WEEKDAY(DATE(_xleta.Year,8,1))
Name AugStart: WEEKDAY(DATE(_xleta.Year,8,1))
Name AugStart: WEEKDAY(DATE(_xleta.Year,8,1))
Name AugStart: WEEKDAY(DATE(_xleta.Year,8,1))
Name BUDGET_Title: #REF!
Name ColumnTitle1: #REF!
Name COMPANY_NAME: #REF!
Name DecStart: WEEKDAY(DATE(_xleta.Year,12,1))
Name DecStart: WEEKDAY(DATE(_xleta.Year,12,1))
Name DecStart: WEEKDAY(DATE(_xleta.Year,12,1))
Name DecStart: WEEKDAY(DATE(_xleta.Year,12,1))
Name DecStart: WEEKDAY(DATE(_xleta.Year,12,1))
Name DecStart: WEEKDAY(DATE(_xleta.Year,12,1))
Name DecStart: WEEKDAY(DATE(_xleta.Year,12,1))
Name DecStart: WEEKDAY(DATE(_xleta.Year,12,1))
Name DecStart: WEEKDAY(DATE(_xleta.Year,12,1))
Name DecStart: WEEKDAY(DATE(_xleta.Year,12,1))
Name FebStart: WEEKDAY(DATE(_xleta.Year,2,1))
Name FebStart: WEEKDAY(DATE(_xleta.Year,2,1))
Name FebStart: WEEKDAY(DATE(_xleta.Year,2,1))
Name FebStart: WEEKDAY(DATE(_xleta.Year,2,1))
Name FebStart: WEEKDAY(DATE(_xleta.Year,2,1))
Name FebStart: WEEKDAY(DATE(_xleta.Year,2,1))
Name FebStart: WEEKDAY(DATE(_xleta.Year,2,1))
Name FebStart: WEEKDAY(DATE(_xleta.Year,2,1))
Name FebStart: WEEKDAY(DATE(_xleta.Year,2,1))
Name FebStart: WEEKDAY(DATE(_xleta.Year,2,1))
Name IsLeapYear: OR(MOD(_xleta.Year,400)=0,AND(MOD(_xleta.Year,4)=0,MOD(_xleta.Year,100)<>0))
Name IsLeapYear: OR(MOD(_xleta.Year,400)=0,AND(MOD(_xleta.Year,4)=0,MOD(_xleta.Year,100)<>0))
Name IsLeapYear: OR(MOD(_xleta.Year,400)=0,AND(MOD(_xleta.Year,4)=0,MOD(_xleta.Year,100)<>0))
Name IsLeapYear: OR(MOD(_xleta.Year,400)=0,AND(MOD(_xleta.Year,4)=0,MOD(_xleta.Year,100)<>0))
Name IsLeapYear: OR(MOD(_xleta.Year,400)=0,AND(MOD(_xleta.Year,4)=0,MOD(_xleta.Year,100)<>0))
Name IsLeapYear: OR(MOD(_xleta.Year,400)=0,AND(MOD(_xleta.Year,4)=0,MOD(_xleta.Year,100)<>0))
Name IsLeapYear: OR(MOD(_xleta.Year,400)=0,AND(MOD(_xleta.Year,4)=0,MOD(_xleta.Year,100)<>0))
Name IsLeapYear: OR(MOD(_xleta.Year,400)=0,AND(MOD(_xleta.Year,4)=0,MOD(_xleta.Year,100)<>0))
Name IsLeapYear: OR(MOD(_xleta.Year,400)=0,AND(MOD(_xleta.Year,4)=0,MOD(_xleta.Year,100)<>0))
Name IsLeapYear: OR(MOD(_xleta.Year,400)=0,AND(MOD(_xleta.Year,4)=0,MOD(_xleta.Year,100)<>0))
Name JanStart: WEEKDAY(DATE(_xleta.Year,1,1))
Name JanStart: WEEKDAY(DATE(_xleta.Year,1,1))
Name JanStart: WEEKDAY(DATE(_xleta.Year,1,1))
Name JanStart: WEEKDAY(DATE(_xleta.Year,1,1))
Name JanStart: WEEKDAY(DATE(_xleta.Year,1,1))
Name JanStart: WEEKDAY(DATE(_xleta.Year,1,1))
Name JanStart: WEEKDAY(DATE(_xleta.Year,1,1))

Sheet Manu

Sheet All Exp  (3)
A1: Month | B1: Salaries | C1: Utilities | D1: Fuel | E1: Petty | F1: Rent | G1: Tax & P | H1: Purchase | I1: Incentive | J1: Comm | K1: Repair | M1: Non | N1: Other | O1: Adjust | P1: RTGS | AH1: RTGS | AN1: Credit | AO1: Cr Paid | AP1: Cr Payable | AQ1: Loan | AR1: Loan Paid | AS1: L Payable | AT1: T Liabelity | AU1: Whl Pur | AV1: DC | AW1: Adjust | AX1: RTGS | AY1: Outflow (sum of Debit) | BD1: Month | BE1: Inflows (Credit) | BF1: Outflows (Debit) | BG1: Closing Balance
A2: 2018-11 | B2: =SUMIFS(Trans!$D:$D,Trans!$F:$F,$B$1,Trans!$I:$I,$A2,Trans!$C:$C,"Debit") -> 0 | C2: =SUMIFS(Trans!$D:$D,Trans!$F:$F,C$1,Trans!$I:$I,$A2,Trans!$C:$C,"Debit") -> 0 | D2: =SUMIFS(Trans!$D:$D,Trans!$F:$F,D$1,Trans!$I:$I,$A2,Trans!$C:$C,"Debit") -> 30000 | E2: =SUMIFS(Trans!$D:$D,Trans!$F:$F,E$1,Trans!$I:$I,$A2,Trans!$C:$C,"Debit") -> 0 | F2: =SUMIFS(Trans!$D:$D,Trans!$F:$F,F$1,Trans!$I:$I,$A2,Trans!$C:$C,"Debit") -> 0 | G2: =SUMIFS(Trans!$D:$D,Trans!$H:$H,G$1,Trans!$I:$I,$A2,Trans!$C:$C,"Debit") -> 0 | H2: =SUMIFS(Trans!$D:$D,Trans!$G:$G,H$1,Trans!$I:$I,$A2,Trans!$C:$C,"Debit") -> 0 | I2: =SUMIFS(Trans!$D:$D,Trans!$G:$G,I$1,Trans!$I:$I,$A2,Trans!$C:$C,"Debit") -> 0 | J2: =SUMIFS(Trans!$D:$D,Trans!$G:$G,J$1,Trans!$I:$I,$A2,Trans!$C:$C,"Debit") -> 0 | K2: =SUMIFS(Trans!$D:$D,Trans!$G:$G,K$1,Trans!$I:$I,$A2,Trans!$C:$C,"Debit") -> 0 | M2: =SUMIFS(Trans!$D:$D,Trans!$G:$G,M$1,Trans!$I:$I,$A2,Trans!$C:$C,"Debit") -> 0 | N2: =SUMIFS(Trans!$D:$D,Trans!$G:$G,N$1,Trans!$I:$I,$A2,Trans!$C:$C,"Debit") -> 0 | O2: =SUMIFS(Trans!$D:$D,Trans!$G:$G,E$1,Trans!$I:$I,$A17,Trans!$C:$C,"Debit") -> 0 | P2: =SUMIFS(Trans!$D:$D,Trans!$G:$G,M$1,Trans!$I:$I,$A17,Trans!$C:$C,"Debit")-SUMIFS(Trans!$D:$D,Trans!$G:$G,AX$1,Trans!$I:$I,$A17,Trans!$C:$C,"Credit") -> 0 | AH2: =SUMIFS(Trans!$D:$D,Trans!$G:$G,AH$1,Trans!$I:$I,$A2,Trans!$C:$C,"Credit") -> 0 | AN2: =SUMIFS(Trans!$D:$D,Trans!$G:$G,AN$1,Trans!$I:$I,$A2,Trans!$C:$C,"Debit") -> 0 | AO2: =SUMIFS(Trans!$D:$D,Trans!$G:$G,AO$1,Trans!$I:$I,$A2,Trans!$C:$C,"Credit") -> 0 | AP2: =AO2-AN2 -> 0 | AQ2: =SUMIFS(Trans!$D:$D,Trans!$G:$G,AQ$1,Trans!$I:$I,$A2,Trans!$C:$C,"Debit") -> 0 | AR2: =SUMIFS(Trans!$D:$D,Trans!$G:$G,AR$1,Trans!$I:$I,$A2,Trans!$C:$C,"Credit") -> 0 | AU2: =SUMIFS(Trans!$D:$D,Trans!$G:$G,AU$1,Trans!$I:$I,$A2,Trans!$C:$C,"Debit") -> 0 | AV2: {=SUM(SUMIFS(Trans!$D:$D,Trans!$H:$H,{"LC","DC","Customs duty","Freight ","Insurance","Related"},Trans!$I:$I,$A2,Trans!$C:$C,"Debit"))} -> 0 | AW2: =SUMIFS(Trans!$D:$D,Trans!$G:$G,AQ$1,Trans!$I:$I,$A2,Trans!$C:$C,"Debit") -> 0 | AX2: =SUMIFS(Trans!$D:$D,Trans!$G:$G,AX$1,Trans!$I:$I,$A2,Trans!$C:$C,"Debit")-SUMIFS(Trans!$D:$D,Trans!$G:$G,#REF!,Trans!$I:$I,$A2,Trans!$C:$C,"Credit") -> 0 | BD2: 2017-11 | BE2: =SUMIFS(Trans!$D:$D,Trans!$A:$A,">="&DATE(2017,11,1),Trans!$A:$A,"<"&EDATE(DATE(2017,11,1),1),Trans!$C:$C,"Credit") -> 0 | BF2: =SUMIFS(Trans!$D:$D,Trans!$A:$A,">="&DATE(2017,11,1),Trans!$A:$A,"<"&EDATE(DATE(2017,11,1),1),Trans!$C:$C,"Debit") -> 0 | BG2: 451625
A3: 2018-12 | B3: =SUMIFS(Trans!$D:$D,Trans!$F:$F,$B$1,Trans!$I:$I,$A3,Trans!$C:$C,"Debit") -> 0 | C3: =SUMIFS(Trans!$D:$D,Trans!$F:$F,C$1,Trans!$I:$I,$A3,Trans!$C:$C,"Debit") -> 0 | D3: =SUMIFS(Trans!$D:$D,Trans!$F:$F,D$1,Trans!$I:$I,$A3,Trans!$C:$C,"Debit") -> 0 | E3: =SUMIFS(Trans!$D:$D,Trans!$F:$F,E$1,Trans!$I:$I,$A3,Trans!$C:$C,"Debit") -> 0 | F3: =SUMIFS(Trans!$D:$D,Trans!$F:$F,F$1,Trans!$I:$I,$A3,Trans!$C:$C,"Debit") -> 0 | G3: =SUMIFS(Trans!$D:$D,Trans!$H:$H,G$1,Trans!$I:$I,$A3,Trans!$C:$C,"Debit") -> 0 | H3: =SUMIFS(Trans!$D:$D,Trans!$G:$G,H$1,Trans!$I:$I,$A3,Trans!$C:$C,"Debit") -> 0 | I3: =SUMIFS(Trans!$D:$D,Trans!$G:$G,I$1,Trans!$I:$I,$A3,Trans!$C:$C,"Debit") -> 0 | J3: =SUMIFS(Trans!$D:$D,Trans!$G:$G,J$1,Trans!$I:$I,$A3,Trans!$C:$C,"Debit") -> 0 | K3: =SUMIFS(Trans!$D:$D,Trans!$G:$G,K$1,Trans!$I:$I,$A3,Trans!$C:$C,"Debit") -> 0 | M3: =SUMIFS(Trans!$D:$D,Trans!$G:$G,M$1,Trans!$I:$I,$A3,Trans!$C:$C,"Debit") -> 0 | N3: =SUMIFS(Trans!$D:$D,Trans!$G:$G,N$1,Trans!$I:$I,$A3,Trans!$C:$C,"Debit") -> 0 | O3: =SUMIFS(Trans!$D:$D,Trans!$G:$G,E$1,Trans!$I:$I,$A18,Trans!$C:$C,"Debit") -> 0 | P3: =SUMIFS(Trans!$D:$D,Trans!$G:$G,M$1,Trans!$I:$I,$A18,Trans!$C:$C,"Debit")-SUMIFS(Trans!$D:$D,Trans!$G:$G,AX$1,Trans!$I:$I,$A18,Trans!$C:$C,"Credit") -> 0 | AE3: salary | AF3: 57000 | AH3: =SUMIFS(Trans!$D:$D,Trans!$G:$G,AH$1,Trans!$I:$I,$A3,Trans!$C:$C,"Credit") -> 0 | AN3: =SUMIFS(Trans!$D:$D,Trans!$G:$G,AN$1,Trans!$I:$I,$A3,Trans!$C:$C,"Debit") -> 0 | AO3: =SUMIFS(Trans!$D:$D,Trans!$G:$G,AO$1,Trans!$I:$I,$A3,Trans!$C:$C,"Credit") -> 0 | AP3: =AO3-AN3 -> 0 | AQ3: =SUMIFS(Trans!$D:$D,Trans!$G:$G,AQ$1,Trans!$I:$I,$A3,Trans!$C:$C,"Debit") -> 0 | AR3: =SUMIFS(Trans!$D:$D,Trans!$G:$G,AR$1,Trans!$I:$I,$A3,Trans!$C:$C,"Credit") -> 0 | AU3: =SUMIFS(Trans!$D:$D,Trans!$G:$G,AU$1,Trans!$I:$I,$A3,Trans!$C:$C,"Debit") -> 0 | AV3: =SUM(SUMIFS(Trans!$D:$D,Trans!$H:$H,{"LC","DC","Customs duty","Freight ","Insurance","Related"},Trans!$I:$I,$A3,Trans!$C:$C,"Debit")) -> 0 | AW3: =SUMIFS(Trans!$D:$D,Trans!$G:$G,AQ$1,Trans!$I:$I,$A3,Trans!$C:$C,"Debit") -> 0 | AX3: =SUMIFS(Trans!$D:$D,Trans!$G:$G,AX$1,Trans!$I:$I,$A3,Trans!$C:$C,"Debit")-SUMIFS(Trans!$D:$D,Trans!$G:$G,#REF!,Trans!$I:$I,$A3,Trans!$C:$C,"Credit") -> 0 | AY3: =SUMIFS(Trans!$D:$D,Trans!#REF!,#REF!,Trans!$C:$C,"Debit") -> #REF! | BD3: 2017-12 | BE3: =SUMIFS(Trans!$D:$D,Trans!$A:$A,">="&DATE(2017,12,1),Trans!$A:$A,"<"&EDATE(DATE(2017,12,1),1),Trans!$C:$C,"Credit") -> 0 | BF3: =SUMIFS(Trans!$D:$D,Trans!$A:$A,">="&DATE(2017,12,1),Trans!$A:$A,"<"&EDATE(DATE(2017,12,1),1),Trans!$C:$C,"Debit") -> 0 | BG3: 1175740
A4: 2019-01 | B4: =SUMIFS(Trans!$D:$D,Trans!$F:$F,$B$1,Trans!$I:$I,$A4,Trans!$C:$C,"Debit") -> 0 | C4: =SUMIFS(Trans!$D:$D,Trans!$F:$F,C$1,Trans!$I:$I,$A4,Trans!$C:$C,"Debit") -> 0 | D4: =SUMIFS(Trans!$D:$D,Trans!$F:$F,D$1,Trans!$I:$I,$A4,Trans!$C:$C,"Debit") -> 0 | E4: =SUMIFS(Trans!$D:$D,Trans!$F:$F,E$1,Trans!$I:$I,$A4,Trans!$C:$C,"Debit") -> 0 | F4: =SUMIFS(Trans!$D:$D,Trans!$F:$F,F$1,Trans!$I:$I,$A4,Trans!$C:$C,"Debit") -> 0 | G4: =SUMIFS(Trans!$D:$D,Trans!$H:$H,G$1,Trans!$I:$I,$A4,Trans!$C:$C,"Debit") -> 0 | H4: =SUMIFS(Trans!$D:$D,Trans!$G:$G,H$1,Trans!$I:$I,$A4,Trans!$C:$C,"Debit") -> 0 | I4: =SUMIFS(Trans!$D:$D,Trans!$G:$G,I$1,Trans!$I:$I,$A4,Trans!$C:$C,"Debit") -> 0 | J4: =SUMIFS(Trans!$D:$D,Trans!$G:$G,J$1,Trans!$I:$I,$A4,Trans!$C:$C,"Debit") -> 0 | K4: =SUMIFS(Trans!$D:$D,Trans!$G:$G,K$1,Trans!$I:$I,$A4,Trans!$C:$C,"Debit") -> 0 | M4: =SUMIFS(Trans!$D:$D,Trans!$G:$G,M$1,Trans!$I:$I,$A4,Trans!$C:$C,"Debit") -> 0 | N4: =SUMIFS(Trans!$D:$D,Trans!$G:$G,N$1,Trans!$I:$I,$A4,Trans!$C:$C,"Debit") -> 0 | O4: =SUMIFS(Trans!$D:$D,Trans!$G:$G,E$1,Trans!$I:$I,$A19,Trans!$C:$C,"Debit") -> 0 | P4: =SUMIFS(Trans!$D:$D,Trans!$G:$G,M$1,Trans!$I:$I,$A19,Trans!$C:$C,"Debit")-SUMIFS(Trans!$D:$D,Trans!$G:$G,AX$1,Trans!$I:$I,$A19,Trans!$C:$C,"Credit") -> 0 | AE4: Fuel | AF4: 30000 | AH4: =SUMIFS(Trans!$D:$D,Trans!$G:$G,AH$1,Trans!$I:$I,$A4,Trans!$C:$C,"Credit") -> 0 | AN4: =SUMIFS(Trans!$D:$D,Trans!$G:$G,AN$1,Trans!$I:$I,$A4,Trans!$C:$C,"Debit") -> 0 | AO4: =SUMIFS(Trans!$D:$D,Trans!$G:$G,AO$1,Trans!$I:$I,$A4,Trans!$C:$C,"Credit") -> 0 | AP4: =AO4-AN4 -> 0 | AQ4: =SUMIFS(Trans!$D:$D,Trans!$G:$G,AQ$1,Trans!$I:$I,$A4,Trans!$C:$C,"Debit") -> 0 | AR4: =SUMIFS(Trans!$D:$D,Trans!$G:$G,AR$1,Trans!$I:$I,$A4,Trans!$C:$C,"Credit") -> 0 | AU4: =SUMIFS(Trans!$D:$D,Trans!$G:$G,AU$1,Trans!$I:$I,$A4,Trans!$C:$C,"Debit") -> 0 | AV4: =SUM(SUMIFS(Trans!$D:$D,Trans!$H:$H,{"LC","DC","Customs duty","Freight ","Insurance","Related"},Trans!$I:$I,$A4,Trans!$C:$C,"Debit")) -> 0 | AW4: =SUMIFS(Trans!$D:$D,Trans!$G:$G,AQ$1,Trans!$I:$I,$A4,Trans!$C:$C,"Debit") -> 0 | AX4: =SUMIFS(Trans!$D:$D,Trans!$G:$G,AX$1,Trans!$I:$I,$A4,Trans!$C:$C,"Debit")-SUMIFS(Trans!$D:$D,Trans!$G:$G,#REF!,Trans!$I:$I,$A4,Trans!$C:$C,"Credit") -> 0 | AY4: =SUMIFS(Trans!$D:$D,Trans!#REF!,#REF!,Trans!$C:$C,"Debit") -> #REF! | AZ4: #VALUE! | BD4: 2018-01 | BE4: =SUMIFS(Trans!$D:$D,Trans!$A:$A,">="&DATE(2018,1,1),Trans!$A:$A,"<"&EDATE(DATE(2018,1,1),1),Trans!$C:$C,"Credit") -> 0 | BF4: =SUMIFS(Trans!$D:$D,Trans!$A:$A,">="&DATE(2018,1,1),Trans!$A:$A,"<"&EDATE(DATE(2018,1,1),1),Trans!$C:$C,"Debit") -> 0 | BG4: 1232836
A5: 2019-02 | B5: =SUMIFS(Trans!$D:$D,Trans!$F:$F,$B$1,Trans!$I:$I,$A5,Trans!$C:$C,"Debit") -> 0 | C5: =SUMIFS(Trans!$D:$D,Trans!$F:$F,C$1,Trans!$I:$I,$A5,Trans!$C:$C,"Debit") -> 0 | D5: =SUMIFS(Trans!$D:$D,Trans!$F:$F,D$1,Trans!$I:$I,$A5,Trans!$C:$C,"Debit") -> 0 | E5: =SUMIFS(Trans!$D:$D,Trans!$F:$F,E$1,Trans!$I:$I,$A5,Trans!$C:$C,"Debit") -> 0 | F5: =SUMIFS(Trans!$D:$D,Trans!$F:$F,F$1,Trans!$I:$I,$A5,Trans!$C:$C,"Debit") -> 0 | G5: =SUMIFS(Trans!$D:$D,Trans!$H:$H,G$1,Trans!$I:$I,$A5,Trans!$C:$C,"Debit") -> 0 | H5: =SUMIFS(Trans!$D:$D,Trans!$G:$G,H$1,Trans!$I:$I,$A5,Trans!$C:$C,"Debit") -> 0 | I5: =SUMIFS(Trans!$D:$D,Trans!$G:$G,I$1,Trans!$I:$I,$A5,Trans!$C:$C,"Debit") -> 0 | J5: =SUMIFS(Trans!$D:$D,Trans!$G:$G,J$1,Trans!$I:$I,$A5,Trans!$C:$C,"Debit") -> 0 | K5: =SUMIFS(Trans!$D:$D,Trans!$G:$G,K$1,Trans!$I:$I,$A5,Trans!$C:$C,"Debit") -> 0 | M5: =SUMIFS(Trans!$D:$D,Trans!$G:$G,M$1,Trans!$I:$I,$A5,Trans!$C:$C,"Debit") -> 0 | N5: =SUMIFS(Trans!$D:$D,Trans!$G:$G,N$1,Trans!$I:$I,$A5,Trans!$C:$C,"Debit") -> 0 | O5: =SUMIFS(Trans!$D:$D,Trans!$G:$G,E$1,Trans!$I:$I,$A20,Trans!$C:$C,"Debit") -> 0 | P5: =SUMIFS(Trans!$D:$D,Trans!$G:$G,M$1,Trans!$I:$I,$A20,Trans!$C:$C,"Debit")-SUMIFS(Trans!$D:$D,Trans!$G:$G,AX$1,Trans!$I:$I,$A20,Trans!$C:$C,"Credit") -> 0 | AF5: 70000 | AH5: =SUMIFS(Trans!$D:$D,Trans!$G:$G,AH$1,Trans!$I:$I,$A5,Trans!$C:$C,"Credit") -> 0 | AN5: =SUMIFS(Trans!$D:$D,Trans!$G:$G,AN$1,Trans!$I:$I,$A5,Trans!$C:$C,"Debit") -> 0 | AO5: =SUMIFS(Trans!$D:$D,Trans!$G:$G,AO$1,Trans!$I:$I,$A5,Trans!$C:$C,"Credit") -> 0 | AP5: =AO5-AN5 -> 0 | AQ5: =SUMIFS(Trans!$D:$D,Trans!$G:$G,AQ$1,Trans!$I:$I,$A5,Trans!$C:$C,"Debit") -> 0 | AR5: =SUMIFS(Trans!$D:$D,Trans!$G:$G,AR$1,Trans!$I:$I,$A5,Trans!$C:$C,"Credit") -> 0 | AU5: =SUMIFS(Trans!$D:$D,Trans!$G:$G,AU$1,Trans!$I:$I,$A5,Trans!$C:$C,"Debit") -> 0 | AV5: =SUM(SUMIFS(Trans!$D:$D,Trans!$H:$H,{"LC","DC","Customs duty","Freight ","Insurance","Related"},Trans!$I:$I,$A5,Trans!$C:$C,"Debit")) -> 0 | AW5: =SUMIFS(Trans!$D:$D,Trans!$G:$G,AQ$1,Trans!$I:$I,$A5,Trans!$C:$C,"Debit") -> 0 | AX5: =SUMIFS(Trans!$D:$D,Trans!$G:$G,AX$1,Trans!$I:$I,$A5,Trans!$C:$C,"Debit")-SUMIFS(Trans!$D:$D,Trans!$G:$G,#REF!,Trans!$I:$I,$A5,Trans!$C:$C,"Credit") -> 0 | AY5: =SUMIFS(Trans!$D:$D,Trans!#REF!,#REF!,Trans!$C:$C,"Debit") -> #REF! | BD5: 2018-02 | BE5: =SUMIFS(Trans!$D:$D,Trans!$A:$A,">="&DATE(2018,2,1),Trans!$A:$A,"<"&EDATE(DATE(2018,2,1),1),Trans!$C:$C,"Credit") -> 0 | BF5: =SUMIFS(Trans!$D:$D,Trans!$A:$A,">="&DATE(2018,2,1),Trans!$A:$A,"<"&EDATE(DATE(2018,2,1),1),Trans!$C:$C,"Debit") -> 0 | BG5: 1385458
A6: 2019-03 | B6: =SUMIFS(Trans!$D:$D,Trans!$F:$F,$B$1,Trans!$I:$I,$A6,Trans!$C:$C,"Debit") -> 0 | C6: =SUMIFS(Trans!$D:$D,Trans!$F:$F,C$1,Trans!$I:$I,$A6,Trans!$C:$C,"Debit") -> 0 | D6: =SUMIFS(Trans!$D:$D,Trans!$F:$F,D$1,Trans!$I:$I,$A6,Trans!$C:$C,"Debit") -> 0 | E6: =SUMIFS(Trans!$D:$D,Trans!$F:$F,E$1,Trans!$I:$I,$A6,Trans!$C:$C,"Debit") -> 0 | F6: =SUMIFS(Trans!$D:$D,Trans!$F:$F,F$1,Trans!$I:$I,$A6,Trans!$C:$C,"Debit") -> 0 | G6: =SUMIFS(Trans!$D:$D,Trans!$H:$H,G$1,Trans!$I:$I,$A6,Trans!$C:$C,"Debit") -> 0 | H6: =SUMIFS(Trans!$D:$D,Trans!$G:$G,H$1,Trans!$I:$I,$A6,Trans!$C:$C,"Debit") -> 0 | I6: =SUMIFS(Trans!$D:$D,Trans!$G:$G,I$1,Trans!$I:$I,$A6,Trans!$C:$C,"Debit") -> 0 | J6: =SUMIFS(Trans!$D:$D,Trans!$G:$G,J$1,Trans!$I:$I,$A6,Trans!$C:$C,"Debit") -> 0 | K6: =SUMIFS(Trans!$D:$D,Trans!$G:$G,K$1,Trans!$I:$I,$A6,Trans!$C:$C,"Debit") -> 0 | M6: =SUMIFS(Trans!$D:$D,Trans!$G:$G,M$1,Trans!$I:$I,$A6,Trans!$C:$C,"Debit") -> 0 | N6: =SUMIFS(Trans!$D:$D,Trans!$G:$G,N$1,Trans!$I:$I,$A6,Trans!$C:$C,"Debit") -> 0 | O6: =SUMIFS(Trans!$D:$D,Trans!$G:$G,E$1,Trans!$I:$I,$A21,Trans!$C:$C,"Debit") -> 0 | P6: =SUMIFS(Trans!$D:$D,Trans!$G:$G,M$1,Trans!$I:$I,$A21,Trans!$C:$C,"Debit")-SUMIFS(Trans!$D:$D,Trans!$G:$G,AX$1,Trans!$I:$I,$A21,Trans!$C:$C,"Credit") -> 0 | AF6: 20000 | AH6: =SUMIFS(Trans!$D:$D,Trans!$G:$G,AH$1,Trans!$I:$I,$A6,Trans!$C:$C,"Credit") -> 0 | AN6: =SUMIFS(Trans!$D:$D,Trans!$G:$G,AN$1,Trans!$I:$I,$A6,Trans!$C:$C,"Debit") -> 0 | AO6: =SUMIFS(Trans!$D:$D,Trans!$G:$G,AO$1,Trans!$I:$I,$A6,Trans!$C:$C,"Credit") -> 0 | AP6: =AO6-AN6 -> 0 | AQ6: =SUMIFS(Trans!$D:$D,Trans!$G:$G,AQ$1,Trans!$I:$I,$A6,Trans!$C:$C,"Debit") -> 0 | AR6: =SUMIFS(Trans!$D:$D,Trans!$G:$G,AR$1,Trans!$I:$I,$A6,Trans!$C:$C,"Credit") -> 0 | AU6: =SUMIFS(Trans!$D:$D,Trans!$G:$G,AU$1,Trans!$I:$I,$A6,Trans!$C:$C,"Debit") -> 0 | AV6: =SUM(SUMIFS(Trans!$D:$D,Trans!$H:$H,{"LC","DC","Customs duty","Freight ","Insurance","Related"},Trans!$I:$I,$A6,Trans!$C:$C,"Debit")) -> 0 | AW6: =SUMIFS(Trans!$D:$D,Trans!$G:$G,AQ$1,Trans!$I:$I,$A6,Trans!$C:$C,"Debit") -> 0 | AX6: =SUMIFS(Trans!$D:$D,Trans!$G:$G,AX$1,Trans!$I:$I,$A6,Trans!$C:$C,"Debit")-SUMIFS(Trans!$D:$D,Trans!$G:$G,#REF!,Trans!$I:$I,$A6,Trans!$C:$C,"Credit") -> 0 | AY6: =SUMIFS(Trans!$D:$D,Trans!#REF!,#REF!,Trans!$C:$C,"Debit") -> #REF! | BD6: 2018-03 | BE6: =SUMIFS(Trans!$D:$D,Trans!$A:$A,">="&DATE(2018,3,1),Trans!$A:$A,"<"&EDATE(DATE(2018,3,1),1),Trans!$C:$C,"Credit") -> 0 | BF6: =SUMIFS(Trans!$D:$D,Trans!$A:$A,">="&DATE(2018,3,1),Trans!$A:$A,"<"&EDATE(DATE(2018,3,1),1),Trans!$C:$C,"Debit") -> 0 | BG6: ='A1'!BB13 -> 0
A7: 2019-04 | B7: =SUMIFS(Trans!$D:$D,Trans!$F:$F,$B$1,Trans!$I:$I,$A7,Trans!$C:$C,"Debit") -> 0 | C7: =SUMIFS(Trans!$D:$D,Trans!$F:$F,C$1,Trans!$I:$I,$A7,Trans!$C:$C,"Debit") -> 0 | D7: =SUMIFS(Trans!$D:$D,Trans!$F:$F,D$1,Trans!$I:$I,$A7,Trans!$C:$C,"Debit") -> 0 | E7: =SUMIFS(Trans!$D:$D,Trans!$F:$F,E$1,Trans!$I:$I,$A7,Trans!$C:$C,"Debit") -> 0 | F7: =SUMIFS(Trans!$D:$D,Trans!$F:$F,F$1,Trans!$I:$I,$A7,Trans!$C:$C,"Debit") -> 0 | G7: =SUMIFS(Trans!$D:$D,Trans!$H:$H,G$1,Trans!$I:$I,$A7,Trans!$C:$C,"Debit") -> 0 | H7: =SUMIFS(Trans!$D:$D,Trans!$G:$G,H$1,Trans!$I:$I,$A7,Trans!$C:$C,"Debit") -> 0 | I7: =SUMIFS(Trans!$D:$D,Trans!$G:$G,I$1,Trans!$I:$I,$A7,Trans!$C:$C,"Debit") -> 0 | J7: =SUMIFS(Trans!$D:$D,Trans!$G:$G,J$1,Trans!$I:$I,$A7,Trans!$C:$C,"Debit") -> 0 | K7: =SUMIFS(Trans!$D:$D,Trans!$G:$G,K$1,Trans!$I:$I,$A7,Trans!$C:$C,"Debit") -> 0 | M7: =SUMIFS(Trans!$D:$D,Trans!$G:$G,M$1,Trans!$I:$I,$A7,Trans!$C:$C,"Debit") -> 0 | N7: =SUMIFS(Trans!$D:$D,Trans!$G:$G,N$1,Trans!$I:$I,$A7,Trans!$C:$C,"Debit") -> 0 | O7: =SUMIFS(Trans!$D:$D,Trans!$G:$G,E$1,Trans!$I:$I,$A22,Trans!$C:$C,"Debit") -> 0 | P7: =SUMIFS(Trans!$D:$D,Trans!$G:$G,M$1,Trans!$I:$I,$A22,Trans!$C:$C,"Debit")-SUMIFS(Trans!$D:$D,Trans!$G:$G,AX$1,Trans!$I:$I,$A22,Trans!$C:$C,"Credit") -> 0 | AF7: =AF6+AF5+AF4+AF3 -> 177000 | AH7: =SUMIFS(Trans!$D:$D,Trans!$G:$G,AH$1,Trans!$I:$I,$A7,Trans!$C:$C,"Credit") -> 0 | AN7: =SUMIFS(Trans!$D:$D,Trans!$G:$G,AN$1,Trans!$I:$I,$A7,Trans!$C:$C,"Debit") -> 0 | AO7: =SUMIFS(Trans!$D:$D,Trans!$G:$G,AO$1,Trans!$I:$I,$A7,Trans!$C:$C,"Credit") -> 0 | AP7: =AO7-AN7 -> 0 | AQ7: =SUMIFS(Trans!$D:$D,Trans!$G:$G,AQ$1,Trans!$I:$I,$A7,Trans!$C:$C,"Debit") -> 0 | AR7: =SUMIFS(Trans!$D:$D,Trans!$G:$G,AR$1,Trans!$I:$I,$A7,Trans!$C:$C,"Credit") -> 0 | AU7: =SUMIFS(Trans!$D:$D,Trans!$G:$G,AU$1,Trans!$I:$I,$A7,Trans!$C:$C,"Debit") -> 0 | AV7: =SUM(SUMIFS(Trans!$D:$D,Trans!$H:$H,{"LC","DC","Customs duty","Freight ","Insurance","Related"},Trans!$I:$I,$A7,Trans!$C:$C,"Debit")) -> 0 | AW7: =SUMIFS(Trans!$D:$D,Trans!$G:$G,AQ$1,Trans!$I:$I,$A7,Trans!$C:$C,"Debit") -> 0 | AX7: =SUMIFS(Trans!$D:$D,Trans!$G:$G,AX$1,Trans!$I:$I,$A7,Trans!$C:$C,"Debit")-SUMIFS(Trans!$D:$D,Trans!$G:$G,#REF!,Trans!$I:$I,$A7,Trans!$C:$C,"Credit") -> 0 | AY7: =SUMIFS(Trans!$D:$D,Trans!#REF!,#REF!,Trans!$C:$C,"Debit") -> #REF! | BD7: 2018-04 | BE7: =SUMIFS(Trans!$D:$D,Trans!$A:$A,">="&DATE(2018,4,1),Trans!$A:$A,"<"&EDATE(DATE(2018,4,1),1),Trans!$C:$C,"Credit") -> 0 | BF7: =SUMIFS(Trans!$D:$D,Trans!$A:$A,">="&DATE(2018,4,1),Trans!$A:$A,"<"&EDATE(DATE(2018,4,1),1),Trans!$C:$C,"Debit") -> 0
A8: 2019-05 | B8: =SUMIFS(Trans!$D:$D,Trans!$F:$F,$B$1,Trans!$I:$I,$A8,Trans!$C:$C,"Debit") -> 0 | C8: =SUMIFS(Trans!$D:$D,Trans!$F:$F,C$1,Trans!$I:$I,$A8,Trans!$C:$C,"Debit") -> 0 | D8: =SUMIFS(Trans!$D:$D,Trans!$F:$F,D$1,Trans!$I:$I,$A8,Trans!$C:$C,"Debit") -> 0 | E8: =SUMIFS(Trans!$D:$D,Trans!$F:$F,E$1,Trans!$I:$I,$A8,Trans!$C:$C,"Debit") -> 0 | F8: =SUMIFS(Trans!$D:$D,Trans!$F:$F,F$1,Trans!$I:$I,$A8,Trans!$C:$C,"Debit") -> 0 | G8: =SUMIFS(Trans!$D:$D,Trans!$H:$H,G$1,Trans!$I:$I,$A8,Trans!$C:$C,"Debit") -> 0 | H8: =SUMIFS(Trans!$D:$D,Trans!$G:$G,H$1,Trans!$I:$I,$A8,Trans!$C:$C,"Debit") -> 0 | I8: =SUMIFS(Trans!$D:$D,Trans!$G:$G,I$1,Trans!$I:$I,$A8,Trans!$C:$C,"Debit") -> 0 | J8: =SUMIFS(Trans!$D:$D,Trans!$G:$G,J$1,Trans!$I:$I,$A8,Trans!$C:$C,"Debit") -> 0 | K8: =SUMIFS(Trans!$D:$D,Trans!$G:$G,K$1,Trans!$I:$I,$A8,Trans!$C:$C,"Debit") -> 0 | M8: =SUMIFS(Trans!$D:$D,Trans!$G:$G,M$1,Trans!$I:$I,$A8,Trans!$C:$C,"Debit") -> 0 | N8: =SUMIFS(Trans!$D:$D,Trans!$G:$G,N$1,Trans!$I:$I,$A8,Trans!$C:$C,"Debit") -> 0 | O8: =SUMIFS(Trans!$D:$D,Trans!$G:$G,E$1,Trans!$I:$I,$A23,Trans!$C:$C,"Debit") -> 0 | P8: =SUMIFS(Trans!$D:$D,Trans!$G:$G,M$1,Trans!$I:$I,$A23,Trans!$C:$C,"Debit")-SUMIFS(Trans!$D:$D,Trans!$G:$G,AX$1,Trans!$I:$I,$A23,Trans!$C:$C,"Credit") -> 0 | AH8: =SUMIFS(Trans!$D:$D,Trans!$G:$G,AH$1,Trans!$I:$I,$A8,Trans!$C:$C,"Credit") -> 0 | AN8: =SUMIFS(Trans!$D:$D,Trans!$G:$G,AN$1,Trans!$I:$I,$A8,Trans!$C:$C,"Debit") -> 0 | AO8: =SUMIFS(Trans!$D:$D,Trans!$G:$G,AO$1,Trans!$I:$I,$A8,Trans!$C:$C,"Credit") -> 0 | AP8: =AO8-AN8 -> 0 | AQ8: =SUMIFS(Trans!$D:$D,Trans!$G:$G,AQ$1,Trans!$I:$I,$A8,Trans!$C:$C,"Debit") -> 0 | AR8: =SUMIFS(Trans!$D:$D,Trans!$G:$G,AR$1,Trans!$I:$I,$A8,Trans!$C:$C,"Credit") -> 0 | AU8: =SUMIFS(Trans!$D:$D,Trans!$G:$G,AU$1,Trans!$I:$I,$A8,Trans!$C:$C,"Debit") -> 0 | AV8: =SUM(SUMIFS(Trans!$D:$D,Trans!$H:$H,{"LC","DC","Customs duty","Freight ","Insurance","Related"},Trans!$I:$I,$A8,Trans!$C:$C,"Debit")) -> 0 | AW8: =SUMIFS(Trans!$D:$D,Trans!$G:$G,AQ$1,Trans!$I:$I,$A8,Trans!$C:$C,"Debit") -> 0 | AX8: =SUMIFS(Trans!$D:$D,Trans!$G:$G,AX$1,Trans!$I:$I,$A8,Trans!$C:$C,"Debit")-SUMIFS(Trans!$D:$D,Trans!$G:$G,#REF!,Trans!$I:$I,$A8,Trans!$C:$C,"Credit") -> 0 | AY8: =SUMIFS(Trans!$D:$D,Trans!#REF!,#REF!,Trans!$C:$C,"Debit") -> #REF! | BD8: 2018-05 | BE8: =SUMIFS(Trans!$D:$D,Trans!$A:$A,">="&DATE(2018,5,1),Trans!$A:$A,"<"&EDATE(DATE(2018,5,1),1),Trans!$C:$C,"Credit") -> 0 | BF8: =SUMIFS(Trans!$D:$D,Trans!$A:$A,">="&DATE(2018,5,1),Trans!$A:$A,"<"&EDATE(DATE(2018,5,1),1),Trans!$C:$C,"Debit") -> 0
A9: 2019-06 | B9: =SUMIFS(Trans!$D:$D,Trans!$F:$F,$B$1,Trans!$I:$I,$A9,Trans!$C:$C,"Debit") -> 0 | C9: =SUMIFS(Trans!$D:$D,Trans!$F:$F,C$1,Trans!$I:$I,$A9,Trans!$C:$C,"Debit") -> 0 | D9: =SUMIFS(Trans!$D:$D,Trans!$F:$F,D$1,Trans!$I:$I,$A9,Trans!$C:$C,"Debit") -> 0 | E9: =SUMIFS(Trans!$D:$D,Trans!$F:$F,E$1,Trans!$I:$I,$A9,Trans!$C:$C,"Debit") -> 0 | F9: =SUMIFS(Trans!$D:$D,Trans!$F:$F,F$1,Trans!$I:$I,$A9,Trans!$C:$C,"Debit") -> 0 | G9: =SUMIFS(Trans!$D:$D,Trans!$H:$H,G$1,Trans!$I:$I,$A9,Trans!$C:$C,"Debit") -> 0 | H9: =SUMIFS(Trans!$D:$D,Trans!$G:$G,H$1,Trans!$I:$I,$A9,Trans!$C:$C,"Debit") -> 0 | I9: =SUMIFS(Trans!$D:$D,Trans!$G:$G,I$1,Trans!$I:$I,$A9,Trans!$C:$C,"Debit") -> 0 | J9: =SUMIFS(Trans!$D:$D,Trans!$G:$G,J$1,Trans!$I:$I,$A9,Trans!$C:$C,"Debit") -> 0 | K9: =SUMIFS(Trans!$D:$D,Trans!$G:$G,K$1,Trans!$I:$I,$A9,Trans!$C:$C,"Debit") -> 0 | M9: =SUMIFS(Trans!$D:$D,Trans!$G:$G,M$1,Trans!$I:$I,$A9,Trans!$C:$C,"Debit") -> 0 | N9: =SUMIFS(Trans!$D:$D,Trans!$G:$G,N$1,Trans!$I:$I,$A9,Trans!$C:$C,"Debit") -> 0 | O9: =SUMIFS(Trans!$D:$D,Trans!$G:$G,E$1,Trans!$I:$I,$A24,Trans!$C:$C,"Debit") -> 0 | P9: =SUMIFS(Trans!$D:$D,Trans!$G:$G,M$1,Trans!$I:$I,$A24,Trans!$C:$C,"Debit")-SUMIFS(Trans!$D:$D,Trans!$G:$G,AX$1,Trans!$I:$I,$A24,Trans!$C:$C,"Credit") -> 0 | AH9: =SUMIFS(Trans!$D:$D,Trans!$G:$G,AH$1,Trans!$I:$I,$A9,Trans!$C:$C,"Credit") -> 0 | AN9: =SUMIFS(Trans!$D:$D,Trans!$G:$G,AN$1,Trans!$I:$I,$A9,Trans!$C:$C,"Debit") -> 0 | AO9: =SUMIFS(Trans!$D:$D,Trans!$G:$G,AO$1,Trans!$I:$I,$A9,Trans!$C:$C,"Credit") -> 0 | AP9: =AO9-AN9 -> 0 | AQ9: =SUMIFS(Trans!$D:$D,Trans!$G:$G,AQ$1,Trans!$I:$I,$A9,Trans!$C:$C,"Debit") -> 0 | AR9: =SUMIFS(Trans!$D:$D,Trans!$G:$G,AR$1,Trans!$I:$I,$A9,Trans!$C:$C,"Credit") -> 0 | AU9: =SUMIFS(Trans!$D:$D,Trans!$G:$G,AU$1,Trans!$I:$I,$A9,Trans!$C:$C,"Debit") -> 0 | AV9: =SUM(SUMIFS(Trans!$D:$D,Trans!$H:$H,{"LC","DC","Customs duty","Freight ","Insurance","Related"},Trans!$I:$I,$A9,Trans!$C:$C,"Debit")) -> 0 | AW9: =SUMIFS(Trans!$D:$D,Trans!$G:$G,AQ$1,Trans!$I:$I,$A9,Trans!$C:$C,"Debit") -> 0 | AX9: =SUMIFS(Trans!$D:$D,Trans!$G:$G,AX$1,Trans!$I:$I,$A9,Trans!$C:$C,"Debit")-SUMIFS(Trans!$D:$D,Trans!$G:$G,#REF!,Trans!$I:$I,$A9,Trans!$C:$C,"Credit") -> 0 | AY9: =SUMIFS(Trans!$D:$D,Trans!#REF!,#REF!,Trans!$C:$C,"Debit") -> #REF! | BD9: 2018-06 | BE9: =SUMIFS(Trans!$D:$D,Trans!$A:$A,">="&DATE(2018,6,1),Trans!$A:$A,"<"&EDATE(DATE(2018,6,1),1),Trans!$C:$C,"Credit") -> 0 | BF9: =SUMIFS(Trans!$D:$D,Trans!$A:$A,">="&DATE(2018,6,1),Trans!$A:$A,"<"&EDATE(DATE(2018,6,1),1),Trans!$C:$C,"Debit") -> 0
A10: 2019-07 | B10: =SUMIFS(Trans!$D:$D,Trans!$F:$F,$B$1,Trans!$I:$I,$A10,Trans!$C:$C,"Debit") -> 0 | C10: =SUMIFS(Trans!$D:$D,Trans!$F:$F,C$1,Trans!$I:$I,$A10,Trans!$C:$C,"Debit") -> 0 | D10: =SUMIFS(Trans!$D:$D,Trans!$F:$F,D$1,Trans!$I:$I,$A10,Trans!$C:$C,"Debit") -> 0 | E10: =SUMIFS(Trans!$D:$D,Trans!$F:$F,E$1,Trans!$I:$I,$A10,Trans!$C:$C,"Debit") -> 0 | F10: =SUMIFS(Trans!$D:$D,Trans!$F:$F,F$1,Trans!$I:$I,$A10,Trans!$C:$C,"Debit") -> 0 | G10: =SUMIFS(Trans!$D:$D,Trans!$H:$H,G$1,Trans!$I:$I,$A10,Trans!$C:$C,"Debit") -> 0 | H10: =SUMIFS(Trans!$D:$D,Trans!$G:$G,H$1,Trans!$I:$I,$A10,Trans!$C:$C,"Debit") -> 0 | I10: =SUMIFS(Trans!$D:$D,Trans!$G:$G,I$1,Trans!$I:$I,$A10,Trans!$C:$C,"Debit") -> 0 | J10: =SUMIFS(Trans!$D:$D,Trans!$G:$G,J$1,Trans!$I:$I,$A10,Trans!$C:$C,"Debit") -> 0 | K10: =SUMIFS(Trans!$D:$D,Trans!$G:$G,K$1,Trans!$I:$I,$A10,Trans!$C:$C,"Debit") -> 0 | M10: =SUMIFS(Trans!$D:$D,Trans!$G:$G,M$1,Trans!$I:$I,$A10,Trans!$C:$C,"Debit") -> 0 | N10: =SUMIFS(Trans!$D:$D,Trans!$G:$G,N$1,Trans!$I:$I,$A10,Trans!$C:$C,"Debit") -> 0 | O10: =SUMIFS(Trans!$D:$D,Trans!$G:$G,E$1,Trans!$I:$I,$A25,Trans!$C:$C,"Debit") -> 0 | P10: =SUMIFS(Trans!$D:$D,Trans!$G:$G,M$1,Trans!$I:$I,$A25,Trans!$C:$C,"Debit")-SUMIFS(Trans!$D:$D,Trans!$G:$G,AX$1,Trans!$I:$I,$A25,Trans!$C:$C,"Credit") -> 0 | AH10: =SUMIFS(Trans!$D:$D,Trans!$G:$G,AH$1,Trans!$I:$I,$A10,Trans!$C:$C,"Credit") -> 0 | AN10: =SUMIFS(Trans!$D:$D,Trans!$G:$G,AN$1,Trans!$I:$I,$A10,Trans!$C:$C,"Debit") -> 0 | AO10: =SUMIFS(Trans!$D:$D,Trans!$G:$G,AO$1,Trans!$I:$I,$A10,Trans!$C:$C,"Credit") -> 0 | AP10: =AO10-AN10 -> 0 | AQ10: =SUMIFS(Trans!$D:$D,Trans!$G:$G,AQ$1,Trans!$I:$I,$A10,Trans!$C:$C,"Debit") -> 0 | AR10: =SUMIFS(Trans!$D:$D,Trans!$G:$G,AR$1,Trans!$I:$I,$A10,Trans!$C:$C,"Credit") -> 0 | AU10: =SUMIFS(Trans!$D:$D,Trans!$G:$G,AU$1,Trans!$I:$I,$A10,Trans!$C:$C,"Debit") -> 0 | AV10: =SUM(SUMIFS(Trans!$D:$D,Trans!$H:$H,{"LC","DC","Customs duty","Freight ","Insurance","Related"},Trans!$I:$I,$A10,Trans!$C:$C,"Debit")) -> 0 | AW10: =SUMIFS(Trans!$D:$D,Trans!$G:$G,AQ$1,Trans!$I:$I,$A10,Trans!$C:$C,"Debit") -> 0 | AX10: =SUMIFS(Trans!$D:$D,Trans!$G:$G,AX$1,Trans!$I:$I,$A10,Trans!$C:$C,"Debit")-SUMIFS(Trans!$D:$D,Trans!$G:$G,#REF!,Trans!$I:$I,$A10,Trans!$C:$C,"Credit") -> 0 | AY10: =SUMIFS(Trans!$D:$D,Trans!#REF!,#REF!,Trans!$C:$C,"Debit") -> #REF! | BD10: 2018-07 | BE10: =SUMIFS(Trans!$D:$D,Trans!$A:$A,">="&DATE(2018,7,1),Trans!$A:$A,"<"&EDATE(DATE(2018,7,1),1),Trans!$C:$C,"Credit") -> 0 | BF10: =SUMIFS(Trans!$D:$D,Trans!$A:$A,">="&DATE(2018,7,1),Trans!$A:$A,"<"&EDATE(DATE(2018,7,1),1),Trans!$C:$C,"Debit") -> 0
A11: 2019-08 | B11: =SUMIFS(Trans!$D:$D,Trans!$F:$F,$B$1,Trans!$I:$I,$A11,Trans!$C:$C,"Debit") -> 0 | C11: =SUMIFS(Trans!$D:$D,Trans!$F:$F,C$1,Trans!$I:$I,$A11,Trans!$C:$C,"Debit") -> 0 | D11: =SUMIFS(Trans!$D:$D,Trans!$F:$F,D$1,Trans!$I:$I,$A11,Trans!$C:$C,"Debit") -> 0 | E11: =SUMIFS(Trans!$D:$D,Trans!$F:$F,E$1,Trans!$I:$I,$A11,Trans!$C:$C,"Debit") -> 0 | F11: =SUMIFS(Trans!$D:$D,Trans!$F:$F,F$1,Trans!$I:$I,$A11,Trans!$C:$C,"Debit") -> 0 | G11: =SUMIFS(Trans!$D:$D,Trans!$H:$H,G$1,Trans!$I:$I,$A11,Trans!$C:$C,"Debit") -> 0 | H11: =SUMIFS(Trans!$D:$D,Trans!$G:$G,H$1,Trans!$I:$I,$A11,Trans!$C:$C,"Debit") -> 0 | I11: =SUMIFS(Trans!$D:$D,Trans!$G:$G,I$1,Trans!$I:$I,$A11,Trans!$C:$C,"Debit") -> 0 | J11: =SUMIFS(Trans!$D:$D,Trans!$G:$G,J$1,Trans!$I:$I,$A11,Trans!$C:$C,"Debit") -> 0 | K11: =SUMIFS(Trans!$D:$D,Trans!$G:$G,K$1,Trans!$I:$I,$A11,Trans!$C:$C,"Debit") -> 0 | M11: =SUMIFS(Trans!$D:$D,Trans!$G:$G,M$1,Trans!$I:$I,$A11,Trans!$C:$C,"Debit") -> 0 | N11: =SUMIFS(Trans!$D:$D,Trans!$G:$G,N$1,Trans!$I:$I,$A11,Trans!$C:$C,"Debit") -> 0 | O11: =SUMIFS(Trans!$D:$D,Trans!$G:$G,E$1,Trans!$I:$I,$A26,Trans!$C:$C,"Debit") -> 0 | P11: =SUMIFS(Trans!$D:$D,Trans!$G:$G,M$1,Trans!$I:$I,$A26,Trans!$C:$C,"Debit")-SUMIFS(Trans!$D:$D,Trans!$G:$G,AX$1,Trans!$I:$I,$A26,Trans!$C:$C,"Credit") -> 0 | AH11: =SUMIFS(Trans!$D:$D,Trans!$G:$G,AH$1,Trans!$I:$I,$A11,Trans!$C:$C,"Credit") -> 0 | AN11: =SUMIFS(Trans!$D:$D,Trans!$G:$G,AN$1,Trans!$I:$I,$A11,Trans!$C:$C,"Debit") -> 0 | AO11: =SUMIFS(Trans!$D:$D,Trans!$G:$G,AO$1,Trans!$I:$I,$A11,Trans!$C:$C,"Credit") -> 0 | AP11: =AO11-AN11 -> 0 | AQ11: =SUMIFS(Trans!$D:$D,Trans!$G:$G,AQ$1,Trans!$I:$I,$A11,Trans!$C:$C,"Debit") -> 0 | AR11: =SUMIFS(Trans!$D:$D,Trans!$G:$G,AR$1,Trans!$I:$I,$A11,Trans!$C:$C,"Credit") -> 0 | AU11: =SUMIFS(Trans!$D:$D,Trans!$G:$G,AU$1,Trans!$I:$I,$A11,Trans!$C:$C,"Debit") -> 0 | AV11: =SUM(SUMIFS(Trans!$D:$D,Trans!$H:$H,{"LC","DC","Customs duty","Freight ","Insurance","Related"},Trans!$I:$I,$A11,Trans!$C:$C,"Debit")) -> 0 | AW11: =SUMIFS(Trans!$D:$D,Trans!$G:$G,AQ$1,Trans!$I:$I,$A11,Trans!$C:$C,"Debit") -> 0 | AX11: =SUMIFS(Trans!$D:$D,Trans!$G:$G,AX$1,Trans!$I:$I,$A11,Trans!$C:$C,"Debit")-SUMIFS(Trans!$D:$D,Trans!$G:$G,#REF!,Trans!$I:$I,$A11,Trans!$C:$C,"Credit") -> 0 | AY11: =SUMIFS(Trans!$D:$D,Trans!#REF!,#REF!,Trans!$C:$C,"Debit") -> #REF! | BD11: 2018-08 | BE11: =SUMIFS(Trans!$D:$D,Trans!$A:$A,">="&DATE(2018,8,1),Trans!$A:$A,"<"&EDATE(DATE(2018,8,1),1),Trans!$C:$C,"Credit") -> 0 | BF11: =SUMIFS(Trans!$D:$D,Trans!$A:$A,">="&DATE(2018,8,1),Trans!$A:$A,"<"&EDATE(DATE(2018,8,1),1),Trans!$C:$C,"Debit") -> 0
A12: 2019-09 | B12: =SUMIFS(Trans!$D:$D,Trans!$F:$F,$B$1,Trans!$I:$I,$A12,Trans!$C:$C,"Debit") -> 0 | C12: =SUMIFS(Trans!$D:$D,Trans!$F:$F,C$1,Trans!$I:$I,$A12,Trans!$C:$C,"Debit") -> 0 | D12: =SUMIFS(Trans!$D:$D,Trans!$F:$F,D$1,Trans!$I:$I,$A12,Trans!$C:$C,"Debit") -> 0 | E12: =SUMIFS(Trans!$D:$D,Trans!$F:$F,E$1,Trans!$I:$I,$A12,Trans!$C:$C,"Debit") -> 0 | F12: =SUMIFS(Trans!$D:$D,Trans!$F:$F,F$1,Trans!$I:$I,$A12,Trans!$C:$C,"Debit") -> 0 | G12: =SUMIFS(Trans!$D:$D,Trans!$H:$H,G$1,Trans!$I:$I,$A12,Trans!$C:$C,"Debit") -> 0 | H12: =SUMIFS(Trans!$D:$D,Trans!$G:$G,H$1,Trans!$I:$I,$A12,Trans!$C:$C,"Debit") -> 0 | I12: =SUMIFS(Trans!$D:$D,Trans!$G:$G,I$1,Trans!$I:$I,$A12,Trans!$C:$C,"Debit") -> 0 | J12: =SUMIFS(Trans!$D:$D,Trans!$G:$G,J$1,Trans!$I:$I,$A12,Trans!$C:$C,"Debit") -> 0 | K12: =SUMIFS(Trans!$D:$D,Trans!$G:$G,K$1,Trans!$I:$I,$A12,Trans!$C:$C,"Debit") -> 0 | M12: =SUMIFS(Trans!$D:$D,Trans!$G:$G,M$1,Trans!$I:$I,$A12,Trans!$C:$C,"Debit") -> 0 | N12: =SUMIFS(Trans!$D:$D,Trans!$G:$G,N$1,Trans!$I:$I,$A12,Trans!$C:$C,"Debit") -> 0 | O12: =SUMIFS(Trans!$D:$D,Trans!$G:$G,E$1,Trans!$I:$I,$A27,Trans!$C:$C,"Debit") -> 0 | P12: =SUMIFS(Trans!$D:$D,Trans!$G:$G,M$1,Trans!$I:$I,$A27,Trans!$C:$C,"Debit")-SUMIFS(Trans!$D:$D,Trans!$G:$G,AX$1,Trans!$I:$I,$A27,Trans!$C:$C,"Credit") -> 0 | AH12: =SUMIFS(Trans!$D:$D,Trans!$G:$G,AH$1,Trans!$I:$I,$A12,Trans!$C:$C,"Credit") -> 0 | AN12: =SUMIFS(Trans!$D:$D,Trans!$G:$G,AN$1,Trans!$I:$I,$A12,Trans!$C:$C,"Debit") -> 0 | AO12: =SUMIFS(Trans!$D:$D,Trans!$G:$G,AO$1,Trans!$I:$I,$A12,Trans!$C:$C,"Credit") -> 0 | AP12: =AO12-AN12 -> 0 | AQ12: =SUMIFS(Trans!$D:$D,Trans!$G:$G,AQ$1,Trans!$I:$I,$A12,Trans!$C:$C,"Debit") -> 0 | AR12: =SUMIFS(Trans!$D:$D,Trans!$G:$G,AR$1,Trans!$I:$I,$A12,Trans!$C:$C,"Credit") -> 0 | AU12: =SUMIFS(Trans!$D:$D,Trans!$G:$G,AU$1,Trans!$I:$I,$A12,Trans!$C:$C,"Debit") -> 0 | AV12: =SUM(SUMIFS(Trans!$D:$D,Trans!$H:$H,{"LC","DC","Customs duty","Freight ","Insurance","Related"},Trans!$I:$I,$A12,Trans!$C:$C,"Debit")) -> 0 | AW12: =SUMIFS(Trans!$D:$D,Trans!$G:$G,AQ$1,Trans!$I:$I,$A12,Trans!$C:$C,"Debit") -> 0 | AX12: =SUMIFS(Trans!$D:$D,Trans!$G:$G,AX$1,Trans!$I:$I,$A12,Trans!$C:$C,"Debit")-SUMIFS(Trans!$D:$D,Trans!$G:$G,#REF!,Trans!$I:$I,$A12,Trans!$C:$C,"Credit") -> 0 | AY12: =SUMIFS(Trans!$D:$D,Trans!#REF!,#REF!,Trans!$C:$C,"Debit") -> #REF! | BD12: 2018-09 | BE12: =SUMIFS(Trans!$D:$D,Trans!$A:$A,">="&DATE(2018,9,1),Trans!$A:$A,"<"&EDATE(DATE(2018,9,1),1),Trans!$C:$C,"Credit") -> 0 | BF12: =SUMIFS(Trans!$D:$D,Trans!$A:$A,">="&DATE(2018,9,1),Trans!$A:$A,"<"&EDATE(DATE(2018,9,1),1),Trans!$C:$C,"Debit") -> 0
A13: 2019-10 | B13: =SUMIFS(Trans!$D:$D,Trans!$F:$F,$B$1,Trans!$I:$I,$A13,Trans!$C:$C,"Debit") -> 0 | C13: =SUMIFS(Trans!$D:$D,Trans!$F:$F,C$1,Trans!$I:$I,$A13,Trans!$C:$C,"Debit") -> 0 | D13: =SUMIFS(Trans!$D:$D,Trans!$F:$F,D$1,Trans!$I:$I,$A13,Trans!$C:$C,"Debit") -> 0 | E13: =SUMIFS(Trans!$D:$D,Trans!$F:$F,E$1,Trans!$I:$I,$A13,Trans!$C:$C,"Debit") -> 0 | F13: =SUMIFS(Trans!$D:$D,Trans!$F:$F,F$1,Trans!$I:$I,$A13,Trans!$C:$C,"Debit") -> 0 | G13: =SUMIFS(Trans!$D:$D,Trans!$H:$H,G$1,Trans!$I:$I,$A13,Trans!$C:$C,"Debit") -> 0 | H13: =SUMIFS(Trans!$D:$D,Trans!$G:$G,H$1,Trans!$I:$I,$A13,Trans!$C:$C,"Debit") -> 0 | I13: =SUMIFS(Trans!$D:$D,Trans!$G:$G,I$1,Trans!$I:$I,$A13,Trans!$C:$C,"Debit") -> 0 | J13: =SUMIFS(Trans!$D:$D,Trans!$G:$G,J$1,Trans!$I:$I,$A13,Trans!$C:$C,"Debit") -> 0 | K13: =SUMIFS(Trans!$D:$D,Trans!$G:$G,K$1,Trans!$I:$I,$A13,Trans!$C:$C,"Debit") -> 0 | M13: =SUMIFS(Trans!$D:$D,Trans!$G:$G,M$1,Trans!$I:$I,$A13,Trans!$C:$C,"Debit") -> 0 | N13: =SUMIFS(Trans!$D:$D,Trans!$G:$G,N$1,Trans!$I:$I,$A13,Trans!$C:$C,"Debit") -> 0 | O13: =SUMIFS(Trans!$D:$D,Trans!$G:$G,E$1,Trans!$I:$I,$A28,Trans!$C:$C,"Debit") -> 0 | P13: =SUMIFS(Trans!$D:$D,Trans!$G:$G,M$1,Trans!$I:$I,$A28,Trans!$C:$C,"Debit")-SUMIFS(Trans!$D:$D,Trans!$G:$G,AX$1,Trans!$I:$I,$A28,Trans!$C:$C,"Credit") -> 0 | AH13: =SUMIFS(Trans!$D:$D,Trans!$G:$G,AH$1,Trans!$I:$I,$A13,Trans!$C:$C,"Credit") -> 0 | AN13: =SUMIFS(Trans!$D:$D,Trans!$G:$G,AN$1,Trans!$I:$I,$A13,Trans!$C:$C,"Debit") -> 0 | AO13: =SUMIFS(Trans!$D:$D,Trans!$G:$G,AO$1,Trans!$I:$I,$A13,Trans!$C:$C,"Credit") -> 0 | AP13: =AO13-AN13 -> 0 | AQ13: =SUMIFS(Trans!$D:$D,Trans!$G:$G,AQ$1,Trans!$I:$I,$A13,Trans!$C:$C,"Debit") -> 0 | AR13: =SUMIFS(Trans!$D:$D,Trans!$G:$G,AR$1,Trans!$I:$I,$A13,Trans!$C:$C,"Credit") -> 0 | AU13: =SUMIFS(Trans!$D:$D,Trans!$G:$G,AU$1,Trans!$I:$I,$A13,Trans!$C:$C,"Debit") -> 0 | AV13: =SUM(SUMIFS(Trans!$D:$D,Trans!$H:$H,{"LC","DC","Customs duty","Freight ","Insurance","Related"},Trans!$I:$I,$A13,Trans!$C:$C,"Debit")) -> 0 | AW13: =SUMIFS(Trans!$D:$D,Trans!$G:$G,AQ$1,Trans!$I:$I,$A13,Trans!$C:$C,"Debit") -> 0 | AX13: =SUMIFS(Trans!$D:$D,Trans!$G:$G,AX$1,Trans!$I:$I,$A13,Trans!$C:$C,"Debit")-SUMIFS(Trans!$D:$D,Trans!$G:$G,#REF!,Trans!$I:$I,$A13,Trans!$C:$C,"Credit") -> 0 | AY13: =SUMIFS(Trans!$D:$D,Trans!#REF!,#REF!,Trans!$C:$C,"Debit") -> #REF! | BD13: 2018-10 | BE13: =SUMIFS(Trans!$D:$D,Trans!$A:$A,">="&DATE(2018,10,1),Trans!$A:$A,"<"&EDATE(DATE(2018,10,1),1),Trans!$C:$C,"Credit") -> 0 | BF13: =SUMIFS(Trans!$D:$D,Trans!$A:$A,">="&DATE(2018,10,1),Trans!$A:$A,"<"&EDATE(DATE(2018,10,1),1),Trans!$C:$C,"Debit") -> 0
B14: =SUMIFS(Trans!$D:$D,Trans!$F:$F,$B$1,Trans!$I:$I,$A14,Trans!$C:$C,"Debit") -> 0 | C14: =SUM(C47+C46+#REF!+#REF!) -> #REF! | D14: =SUM(D47+D46+#REF!+#REF!) -> #REF! | E14: =SUM(E47+E46+#REF!+#REF!) -> #REF! | F14: =SUM(F47+F46+#REF!+#REF!) -> #REF! | G14: =SUM(G47+G46+#REF!+#REF!) -> #REF! | H14: =SUM(H47+H46+H45+H44) -> 0 | I14: =SUM(I47+I46+I45+I44) -> 0 | J14: =SUM(J47+J46+J45+J44) -> 0 | K14: =SUM(K47+K46+K45+K44) -> 0 | M14: =SUM(L47+L46+L45+L44) -> 0 | N14: =SUM(M47+M46+M45+M44) -> 0 | O14: =SUM(K62+K61+K60+K59) -> 0 | P14: =SUM(L62+L61+L60+L59) -> 0 | AH14: =SUM(AH47+AH46+AH45+AH44) -> 0 | AN14: =SUM(R47+R46+R45+R44) -> 0 | AO14: =SUM(S47+S46+S45+S44) -> 0 | AQ14: =SUM(U47+U46+U45+U44) -> 0 | AR14: =SUM(V47+V46+V45+V44) -> 0 | AU14: =SUM(Y47+Y46+Y45+Y44) -> 0 | AV14: =SUM(Z47+Z46+Z45+Z44) -> 0 | AW14: =SUM(AA47+AA46+AA45+AA44) -> 0 | AX14: =SUM(AB47+AB46+AB45+AB44) -> 0 | AY14: =SUMIFS(Trans!$D:$D,Trans!#REF!,#REF!,Trans!$C:$C,"Debit") -> #REF!
A16: Month | B16: Credit | C16: Cr Paid | D16: Cr Payable | E16: Loan | F16: Loan Paid | G16: L Payable | H16: T Liabelity
A17: 2018-11 | B17: =SUMIFS(Trans!$D:$D,Trans!$G:$G,B$1,Trans!$I:$I,$A17,Trans!$C:$C,"Debit") -> 0 | C17: =SUMIFS(Trans!$D:$D,Trans!$G:$G,C$1,Trans!$I:$I,$A17,Trans!$C:$C,"Credit") -> 0 | D17: =C17-B17 -> 0 | E17: =SUMIFS(Trans!$D:$D,Trans!$G:$G,E$1,Trans!$I:$I,$A17,Trans!$C:$C,"Debit") -> 0 | F17: =SUMIFS(Trans!$D:$D,Trans!$G:$G,F$1,Trans!$I:$I,$A17,Trans!$C:$C,"Credit") -> 0
A18: 2018-12 | B18: =SUMIFS(Trans!$D:$D,Trans!$G:$G,B$1,Trans!$I:$I,$A18,Trans!$C:$C,"Debit") -> 0 | C18: =SUMIFS(Trans!$D:$D,Trans!$G:$G,C$1,Trans!$I:$I,$A18,Trans!$C:$C,"Credit") -> 0 | D18: =C18-B18 -> 0 | E18: =SUMIFS(Trans!$D:$D,Trans!$G:$G,E$1,Trans!$I:$I,$A18,Trans!$C:$C,"Debit") -> 0 | F18: =SUMIFS(Trans!$D:$D,Trans!$G:$G,F$1,Trans!$I:$I,$A18,Trans!$C:$C,"Credit") -> 0
A19: 2019-01 | B19: =SUMIFS(Trans!$D:$D,Trans!$G:$G,B$1,Trans!$I:$I,$A19,Trans!$C:$C,"Debit") -> 0 | C19: =SUMIFS(Trans!$D:$D,Trans!$G:$G,C$1,Trans!$I:$I,$A19,Trans!$C:$C,"Credit") -> 0 | D19: =C19-B19 -> 0 | E19: =SUMIFS(Trans!$D:$D,Trans!$G:$G,E$1,Trans!$I:$I,$A19,Trans!$C:$C,"Debit") -> 0 | F19: =SUMIFS(Trans!$D:$D,Trans!$G:$G,F$1,Trans!$I:$I,$A19,Trans!$C:$C,"Credit") -> 0
A20: 2019-02 | B20: =SUMIFS(Trans!$D:$D,Trans!$G:$G,B$1,Trans!$I:$I,$A20,Trans!$C:$C,"Debit") -> 0 | C20: =SUMIFS(Trans!$D:$D,Trans!$G:$G,C$1,Trans!$I:$I,$A20,Trans!$C:$C,"Credit") -> 0 | D20: =C20-B20 -> 0 | E20: =SUMIFS(Trans!$D:$D,Trans!$G:$G,E$1,Trans!$I:$I,$A20,Trans!$C:$C,"Debit") -> 0 | F20: =SUMIFS(Trans!$D:$D,Trans!$G:$G,F$1,Trans!$I:$I,$A20,Trans!$C:$C,"Credit") -> 0
A21: 2019-03 | B21: =SUMIFS(Trans!$D:$D,Trans!$G:$G,B$1,Trans!$I:$I,$A21,Trans!$C:$C,"Debit") -> 0 | C21: =SUMIFS(Trans!$D:$D,Trans!$G:$G,C$1,Trans!$I:$I,$A21,Trans!$C:$C,"Credit") -> 0 | D21: =C21-B21 -> 0 | E21: =SUMIFS(Trans!$D:$D,Trans!$G:$G,E$1,Trans!$I:$I,$A21,Trans!$C:$C,"Debit") -> 0 | F21: =SUMIFS(Trans!$D:$D,Trans!$G:$G,F$1,Trans!$I:$I,$A21,Trans!$C:$C,"Credit") -> 0
A22: 2019-04 | B22: =SUMIFS(Trans!$D:$D,Trans!$G:$G,B$1,Trans!$I:$I,$A22,Trans!$C:$C,"Debit") -> 0 | C22: =SUMIFS(Trans!$D:$D,Trans!$G:$G,C$1,Trans!$I:$I,$A22,Trans!$C:$C,"Credit") -> 0 | D22: =C22-B22 -> 0 | E22: =SUMIFS(Trans!$D:$D,Trans!$G:$G,E$1,Trans!$I:$I,$A22,Trans!$C:$C,"Debit") -> 0 | F22: =SUMIFS(Trans!$D:$D,Trans!$G:$G,F$1,Trans!$I:$I,$A22,Trans!$C:$C,"Credit") -> 0
A23: 2019-05 | B23: =SUMIFS(Trans!$D:$D,Trans!$G:$G,B$1,Trans!$I:$I,$A23,Trans!$C:$C,"Debit") -> 0 | C23: =SUMIFS(Trans!$D:$D,Trans!$G:$G,C$1,Trans!$I:$I,$A23,Trans!$C:$C,"Credit") -> 0 | D23: =C23-B23 -> 0 | E23: =SUMIFS(Trans!$D:$D,Trans!$G:$G,E$1,Trans!$I:$I,$A23,Trans!$C:$C,"Debit") -> 0 | F23: =SUMIFS(Trans!$D:$D,Trans!$G:$G,F$1,Trans!$I:$I,$A23,Trans!$C:$C,"Credit") -> 0
A24: 2019-06 | B24: =SUMIFS(Trans!$D:$D,Trans!$G:$G,B$1,Trans!$I:$I,$A24,Trans!$C:$C,"Debit") -> 0 | C24: =SUMIFS(Trans!$D:$D,Trans!$G:$G,C$1,Trans!$I:$I,$A24,Trans!$C:$C,"Credit") -> 0 | D24: =C24-B24 -> 0 | E24: =SUMIFS(Trans!$D:$D,Trans!$G:$G,E$1,Trans!$I:$I,$A24,Trans!$C:$C,"Debit") -> 0 | F24: =SUMIFS(Trans!$D:$D,Trans!$G:$G,F$1,Trans!$I:$I,$A24,Trans!$C:$C,"Credit") -> 0
A25: 2019-07 | B25: =SUMIFS(Trans!$D:$D,Trans!$G:$G,B$1,Trans!$I:$I,$A25,Trans!$C:$C,"Debit") -> 0 | C25: =SUMIFS(Trans!$D:$D,Trans!$G:$G,C$1,Trans!$I:$I,$A25,Trans!$C:$C,"Credit") -> 0 | D25: =C25-B25 -> 0 | E25: =SUMIFS(Trans!$D:$D,Trans!$G:$G,E$1,Trans!$I:$I,$A25,Trans!$C:$C,"Debit") -> 0 | F25: =SUMIFS(Trans!$D:$D,Trans!$G:$G,F$1,Trans!$I:$I,$A25,Trans!$C:$C,"Credit") -> 0
A26: 2019-08 | B26: =SUMIFS(Trans!$D:$D,Trans!$G:$G,B$1,Trans!$I:$I,$A26,Trans!$C:$C,"Debit") -> 0 | C26: =SUMIFS(Trans!$D:$D,Trans!$G:$G,C$1,Trans!$I:$I,$A26,Trans!$C:$C,"Credit") -> 0 | D26: =C26-B26 -> 0 | E26: =SUMIFS(Trans!$D:$D,Trans!$G:$G,E$1,Trans!$I:$I,$A26,Trans!$C:$C,"Debit") -> 0 | F26: =SUMIFS(Trans!$D:$D,Trans!$G:$G,F$1,Trans!$I:$I,$A26,Trans!$C:$C,"Credit") -> 0
A27: 2019-09 | B27: =SUMIFS(Trans!$D:$D,Trans!$G:$G,B$1,Trans!$I:$I,$A27,Trans!$C:$C,"Debit") -> 0 | C27: =SUMIFS(Trans!$D:$D,Trans!$G:$G,C$1,Trans!$I:$I,$A27,Trans!$C:$C,"Credit") -> 0 | D27: =C27-B27 -> 0 | E27: =SUMIFS(Trans!$D:$D,Trans!$G:$G,E$1,Trans!$I:$I,$A27,Trans!$C:$C,"Debit") -> 0 | F27: =SUMIFS(Trans!$D:$D,Trans!$G:$G,F$1,Trans!$I:$I,$A27,Trans!$C:$C,"Credit") -> 0
A28: 2019-10 | B28: =SUMIFS(Trans!$D:$D,Trans!$G:$G,B$1,Trans!$I:$I,$A28,Trans!$C:$C,"Debit") -> 0 | C28: =SUMIFS(Trans!$D:$D,Trans!$G:$G,C$1,Trans!$I:$I,$A28,Trans!$C:$C,"Credit") -> 0 | D28: =C28-B28 -> 0 | E28: =SUMIFS(Trans!$D:$D,Trans!$G:$G,E$1,Trans!$I:$I,$A28,Trans!$C:$C,"Debit") -> 0 | F28: =SUMIFS(Trans!$D:$D,Trans!$G:$G,F$1,Trans!$I:$I,$A28,Trans!$C:$C,"Credit") -> 0
B29: =SUM(B62+B61+B60+B59) -> 0 | C29: =SUM(C62+C61+C60+C59) -> 0 | E29: =SUM(E62+E61+E60+E59) -> 0 | F29: =SUM(F62+F61+F60+F59) -> 0
A32: Month | B32: WHT | C32: Rev Tax | D32: Dividend | E32: Audit fee | F32: Whl Pur | G32: DC
A33: 2018-11 | B33: =SUMIFS(Trans!$D:$D,Trans!$H:$H,B$32,Trans!$I:$I,$A2,Trans!$C:$C,"Debit") -> 0 | C33: =SUMIFS(Trans!$D:$D,Trans!$H:$H,C$32,Trans!$I:$I,$A2,Trans!$C:$C,"Debit") -> 0 | D33: =SUMIFS(Trans!$D:$D,Trans!$H:$H,D$32,Trans!$I:$I,$A2,Trans!$C:$C,"Debit") -> 0 | E33: =SUMIFS(Trans!$D:$D,Trans!$H:$H,E$32,Trans!$I:$I,$A2,Trans!$C:$C,"Debit") -> 0 | F33: =SUMIFS(Trans!$D:$D,Trans!$G:$G,I$1,Trans!$I:$I,$A17,Trans!$C:$C,"Debit") -> 0 | G33: {=SUM(SUMIFS(Trans!$D:$D,Trans!$H:$H,{"LC","DC","Customs duty","Freight ","Insurance","Related"},Trans!$I:$I,$A17,Trans!$C:$C,"Debit"))} -> 0
A34: 2018-12 | B34: =SUMIFS(Trans!$D:$D,Trans!$H:$H,B$32,Trans!$I:$I,$A3,Trans!$C:$C,"Debit") -> 0 | C34: =SUMIFS(Trans!$D:$D,Trans!$H:$H,C$32,Trans!$I:$I,$A3,Trans!$C:$C,"Debit") -> 0 | D34: =SUMIFS(Trans!$D:$D,Trans!$H:$H,D$32,Trans!$I:$I,$A3,Trans!$C:$C,"Debit") -> 0 | E34: =SUMIFS(Trans!$D:$D,Trans!$H:$H,E$32,Trans!$I:$I,$A3,Trans!$C:$C,"Debit") -> 0 | F34: =SUMIFS(Trans!$D:$D,Trans!$G:$G,I$1,Trans!$I:$I,$A18,Trans!$C:$C,"Debit") -> 0 | G34: =SUM(SUMIFS(Trans!$D:$D,Trans!$H:$H,{"LC","DC","Customs duty","Freight ","Insurance","Related"},Trans!$I:$I,$A18,Trans!$C:$C,"Debit")) -> 0
A35: 2019-01 | B35: =SUMIFS(Trans!$D:$D,Trans!$H:$H,B$32,Trans!$I:$I,$A4,Trans!$C:$C,"Debit") -> 0 | C35: =SUMIFS(Trans!$D:$D,Trans!$H:$H,C$32,Trans!$I:$I,$A4,Trans!$C:$C,"Debit") -> 0 | D35: =SUMIFS(Trans!$D:$D,Trans!$H:$H,D$32,Trans!$I:$I,$A4,Trans!$C:$C,"Debit") -> 0 | E35: =SUMIFS(Trans!$D:$D,Trans!$H:$H,E$32,Trans!$I:$I,$A4,Trans!$C:$C,"Debit") -> 0 | F35: =SUMIFS(Trans!$D:$D,Trans!$G:$G,I$1,Trans!$I:$I,$A19,Trans!$C:$C,"Debit") -> 0 | G35: =SUM(SUMIFS(Trans!$D:$D,Trans!$H:$H,{"LC","DC","Customs duty","Freight ","Insurance","Related"},Trans!$I:$I,$A19,Trans!$C:$C,"Debit")) -> 0
A36: 2019-02 | B36: =SUMIFS(Trans!$D:$D,Trans!$H:$H,B$32,Trans!$I:$I,$A5,Trans!$C:$C,"Debit") -> 0 | C36: =SUMIFS(Trans!$D:$D,Trans!$H:$H,C$32,Trans!$I:$I,$A5,Trans!$C:$C,"Debit") -> 0 | D36: =SUMIFS(Trans!$D:$D,Trans!$H:$H,D$32,Trans!$I:$I,$A5,Trans!$C:$C,"Debit") -> 0 | E36: =SUMIFS(Trans!$D:$D,Trans!$H:$H,E$32,Trans!$I:$I,$A5,Trans!$C:$C,"Debit") -> 0 | F36: =SUMIFS(Trans!$D:$D,Trans!$G:$G,I$1,Trans!$I:$I,$A20,Trans!$C:$C,"Debit") -> 0 | G36: =SUM(SUMIFS(Trans!$D:$D,Trans!$H:$H,{"LC","DC","Customs duty","Freight ","Insurance","Related"},Trans!$I:$I,$A20,Trans!$C:$C,"Debit")) -> 0
A37: 2019-03 | B37: =SUMIFS(Trans!$D:$D,Trans!$H:$H,B$32,Trans!$I:$I,$A6,Trans!$C:$C,"Debit") -> 0 | C37: =SUMIFS(Trans!$D:$D,Trans!$H:$H,C$32,Trans!$I:$I,$A6,Trans!$C:$C,"Debit") -> 0 | D37: =SUMIFS(Trans!$D:$D,Trans!$H:$H,D$32,Trans!$I:$I,$A6,Trans!$C:$C,"Debit") -> 0 | E37: =SUMIFS(Trans!$D:$D,Trans!$H:$H,E$32,Trans!$I:$I,$A6,Trans!$C:$C,"Debit") -> 0 | F37: =SUMIFS(Trans!$D:$D,Trans!$G:$G,I$1,Trans!$I:$I,$A21,Trans!$C:$C,"Debit") -> 0 | G37: =SUM(SUMIFS(Trans!$D:$D,Trans!$H:$H,{"LC","DC","Customs duty","Freight ","Insurance","Related"},Trans!$I:$I,$A21,Trans!$C:$C,"Debit")) -> 0
A38: 2019-04 | B38: =SUMIFS(Trans!$D:$D,Trans!$H:$H,B$32,Trans!$I:$I,$A7,Trans!$C:$C,"Debit") -> 0 | C38: =SUMIFS(Trans!$D:$D,Trans!$H:$H,C$32,Trans!$I:$I,$A7,Trans!$C:$C,"Debit") -> 0 | D38: =SUMIFS(Trans!$D:$D,Trans!$H:$H,D$32,Trans!$I:$I,$A7,Trans!$C:$C,"Debit") -> 0 | E38: =SUMIFS(Trans!$D:$D,Trans!$H:$H,E$32,Trans!$I:$I,$A7,Trans!$C:$C,"Debit") -> 0 | F38: =SUMIFS(Trans!$D:$D,Trans!$G:$G,I$1,Trans!$I:$I,$A22,Trans!$C:$C,"Debit") -> 0 | G38: =SUM(SUMIFS(Trans!$D:$D,Trans!$H:$H,{"LC","DC","Customs duty","Freight ","Insurance","Related"},Trans!$I:$I,$A22,Trans!$C:$C,"Debit")) -> 0
A39: 2019-05 | B39: =SUMIFS(Trans!$D:$D,Trans!$H:$H,B$32,Trans!$I:$I,$A8,Trans!$C:$C,"Debit") -> 0 | C39: =SUMIFS(Trans!$D:$D,Trans!$H:$H,C$32,Trans!$I:$I,$A8,Trans!$C:$C,"Debit") -> 0 | D39: =SUMIFS(Trans!$D:$D,Trans!$H:$H,D$32,Trans!$I:$I,$A8,Trans!$C:$C,"Debit") -> 0 | E39: =SUMIFS(Trans!$D:$D,Trans!$H:$H,E$32,Trans!$I:$I,$A8,Trans!$C:$C,"Debit") -> 0 | F39: =SUMIFS(Trans!$D:$D,Trans!$G:$G,I$1,Trans!$I:$I,$A23,Trans!$C:$C,"Debit") -> 0 | G39: =SUM(SUMIFS(Trans!$D:$D,Trans!$H:$H,{"LC","DC","Customs duty","Freight ","Insurance","Related"},Trans!$I:$I,$A23,Trans!$C:$C,"Debit")) -> 0
A40: 2019-06 | B40: =SUMIFS(Trans!$D:$D,Trans!$H:$H,B$32,Trans!$I:$I,$A9,Trans!$C:$C,"Debit") -> 0 | C40: =SUMIFS(Trans!$D:$D,Trans!$H:$H,C$32,Trans!$I:$I,$A9,Trans!$C:$C,"Debit") -> 0 | D40: =SUMIFS(Trans!$D:$D,Trans!$H:$H,D$32,Trans!$I:$I,$A9,Trans!$C:$C,"Debit") -> 0 | E40: =SUMIFS(Trans!$D:$D,Trans!$H:$H,E$32,Trans!$I:$I,$A9,Trans!$C:$C,"Debit") -> 0 | F40: =SUMIFS(Trans!$D:$D,Trans!$G:$G,I$1,Trans!$I:$I,$A24,Trans!$C:$C,"Debit") -> 0 | G40: =SUM(SUMIFS(Trans!$D:$D,Trans!$H:$H,{"LC","DC","Customs duty","Freight ","Insurance","Related"},Trans!$I:$I,$A24,Trans!$C:$C,"Debit")) -> 0
A41: 2019-07 | B41: =SUMIFS(Trans!$D:$D,Trans!$H:$H,B$32,Trans!$I:$I,$A10,Trans!$C:$C,"Debit") -> 0 | C41: =SUMIFS(Trans!$D:$D,Trans!$H:$H,C$32,Trans!$I:$I,$A10,Trans!$C:$C,"Debit") -> 0 | D41: =SUMIFS(Trans!$D:$D,Trans!$H:$H,D$32,Trans!$I:$I,$A10,Trans!$C:$C,"Debit") -> 0 | E41: =SUMIFS(Trans!$D:$D,Trans!$H:$H,E$32,Trans!$I:$I,$A10,Trans!$C:$C,"Debit") -> 0 | F41: =SUMIFS(Trans!$D:$D,Trans!$G:$G,I$1,Trans!$I:$I,$A25,Trans!$C:$C,"Debit") -> 0 | G41: =SUM(SUMIFS(Trans!$D:$D,Trans!$H:$H,{"LC","DC","Customs duty","Freight ","Insurance","Related"},Trans!$I:$I,$A25,Trans!$C:$C,"Debit")) -> 0
A42: 2019-08 | B42: =SUMIFS(Trans!$D:$D,Trans!$H:$H,B$32,Trans!$I:$I,$A11,Trans!$C:$C,"Debit") -> 0 | C42: =SUMIFS(Trans!$D:$D,Trans!$H:$H,C$32,Trans!$I:$I,$A11,Trans!$C:$C,"Debit") -> 0 | D42: =SUMIFS(Trans!$D:$D,Trans!$H:$H,D$32,Trans!$I:$I,$A11,Trans!$C:$C,"Debit") -> 0 | E42: =SUMIFS(Trans!$D:$D,Trans!$H:$H,E$32,Trans!$I:$I,$A11,Trans!$C:$C,"Debit") -> 0 | F42: =SUMIFS(Trans!$D:$D,Trans!$G:$G,I$1,Trans!$I:$I,$A26,Trans!$C:$C,"Debit") -> 0 | G42: =SUM(SUMIFS(Trans!$D:$D,Trans!$H:$H,{"LC","DC","Customs duty","Freight ","Insurance","Related"},Trans!$I:$I,$A26,Trans!$C:$C,"Debit")) -> 0
A43: 2019-09 | B43: =SUMIFS(Trans!$D:$D,Trans!$H:$H,B$32,Trans!$I:$I,$A12,Trans!$C:$C,"Debit") -> 0 | C43: =SUMIFS(Trans!$D:$D,Trans!$H:$H,C$32,Trans!$I:$I,$A12,Trans!$C:$C,"Debit") -> 0 | D43: =SUMIFS(Trans!$D:$D,Trans!$H:$H,D$32,Trans!$I:$I,$A12,Trans!$C:$C,"Debit") -> 0 | E43: =SUMIFS(Trans!$D:$D,Trans!$H:$H,E$32,Trans!$I:$I,$A12,Trans!$C:$C,"Debit") -> 0 | F43: =SUMIFS(Trans!$D:$D,Trans!$G:$G,I$1,Trans!$I:$I,$A27,Trans!$C:$C,"Debit") -> 0 | G43: =SUM(SUMIFS(Trans!$D:$D,Trans!$H:$H,{"LC","DC","Customs duty","Freight ","Insurance","Related"},Trans!$I:$I,$A27,Trans!$C:$C,"Debit")) -> 0 | AX43: Investment | AY43: =SUMIFS(Trans!$D:$D,Trans!#REF!,AX43,Trans!$C:$C,"Debit") -> #REF!
A44: 2019-10 | B44: =SUMIFS(Trans!$D:$D,Trans!$H:$H,B$32,Trans!$I:$I,$A13,Trans!$C:$C,"Debit") -> 0 | C44: =SUMIFS(Trans!$D:$D,Trans!$H:$H,C$32,Trans!$I:$I,$A13,Trans!$C:$C,"Debit") -> 0 | D44: =SUMIFS(Trans!$D:$D,Trans!$H:$H,D$32,Trans!$I:$I,$A13,Trans!$C:$C,"Debit") -> 0 | E44: =SUMIFS(Trans!$D:$D,Trans!$H:$H,E$32,Trans!$I:$I,$A13,Trans!$C:$C,"Debit") -> 0 | F44: =SUMIFS(Trans!$D:$D,Trans!$G:$G,I$1,Trans!$I:$I,$A28,Trans!$C:$C,"Debit") -> 0 | G44: =SUM(SUMIFS(Trans!$D:$D,Trans!$H:$H,{"LC","DC","Customs duty","Freight ","Insurance","Related"},Trans!$I:$I,$A28,Trans!$C:$C,"Debit")) -> 0 | H44: =SUM(H2:H4) -> 0 | I44: =SUM(I2:I4) -> 0 | J44: =SUM(J2:J4) -> 0 | K44: =SUM(K2:K4) -> 0 | L44: =SUM(M2:M4) -> 0 | M44: =SUM(N2:N4) -> 0 | N44: =SUM(B33:B35) -> 0 | O44: =SUM(C33:C35) -> 0 | P44: =SUM(D33:D35) -> 0 | Q44: =SUM(E33:E35) -> 0 | R44: =SUM(AN2:AN4) -> 0 | S44: =SUM(AO2:AO4) -> 0 | T44: =SUM(AP2:AP4) -> 0 | U44: =SUM(AQ2:AQ4) -> 0 | V44: =SUM(AR2:AR4) -> 0 | Y44: =SUM(AU2:AU4) -> 0 | Z44: =SUM(AV2:AV4) -> 0 | AA44: =SUM(AW2:AW4) -> 0 | AB44: =SUM(AX2:AX4) -> 0 | AH44: =SUMIFS(Trans!$D:$D,Trans!$G:$G,I$1,Trans!$I:$I,$A44,Trans!$C:$C,"Debit") -> 0 | AX44: Adjustement | AY44: =SUMIFS(Trans!$D:$D,Trans!#REF!,AX44,Trans!$C:$C,"Debit") -> #REF!
B45: =SUM(N47+N46+N45+N44) -> 0 | C45: =SUM(O47+O46+O45+O44) -> 0 | D45: =SUM(P47+P46+P45+P44) -> 0 | E45: =SUM(Q47+Q46+Q45+Q44) -> 0 | F45: =SUM(I62+I61+I60+I59) -> 0 | G45: =SUM(J62+J61+J60+J59) -> 0 | H45: =SUM(H5:H7) -> 0 | I45: =SUM(I5:I7) -> 0 | J45: =SUM(J5:J7) -> 0 | K45: =SUM(K5:K7) -> 0 | L45: =SUM(M5:M7) -> 0 | M45: =SUM(N5:N7) -> 0 | N45: =SUM(B36:B38) -> 0 | O45: =SUM(C36:C38) -> 0 | P45: =SUM(D36:D38) -> 0 | Q45: =SUM(E36:E38) -> 0 | R45: =SUM(AN5:AN7) -> 0 | S45: =SUM(AO5:AO7) -> 0 | T45: =SUM(AP5:AP7) -> 0 | U45: =SUM(AQ5:AQ7) -> 0 | V45: =SUM(AR5:AR7) -> 0 | Y45: =SUM(AU5:AU7) -> 0 | Z45: =SUM(AV5:AV7) -> 0 | AA45: =SUM(AW5:AW7) -> 0 | AB45: =SUM(AX5:AX7) -> 0 | AH45: =SUMIFS(Trans!$D:$D,Trans!$G:$G,I$1,Trans!$I:$I,$A45,Trans!$C:$C,"Debit") -> 0
A46: Q3 | B46: =SUM(B8:B10) -> 0 | C46: =SUM(C8:C10) -> 0 | D46: =SUM(D8:D10) -> 0 | E46: =SUM(E8:E10) -> 0 | F46: =SUM(F8:F10) -> 0 | G46: =SUM(G8:G10) -> 0 | H46: =SUM(H8:H10) -> 0 | I46: =SUM(I8:I10) -> 0 | ... K46: =SUM(K8:K10) -> 0 | L46: =SUM(M8:M10) -> 0 | M46: =SUM(N8:N10) -> 0 | N46: =SUM(B39:B41) -> 0 | O46: =SUM(C39:C41) -> 0 | P46: =SUM(D39:D41) -> 0 | Q46: =SUM(E39:E41) -> 0 | R46: =SUM(AN8:AN10) -> 0 | S46: =SUM(AO8:AO10) -> 0 | T46: =SUM(AP8:AP10) -> 0 | U46: =SUM(AQ8:AQ10) -> 0 | V46: =SUM(AR8:AR10) -> 0 | Y46: =SUM(AU8:AU10) -> 0 | Z46: =SUM(AV8:AV10) -> 0 | AA46: =SUM(AW8:AW10) -> 0 | AB46: =SUM(AX8:AX10) -> 0 | AH46: =SUMIFS(Trans!$D:$D,Trans!$G:$G,I$1,Trans!$I:$I,$A46,Trans!$C:$C,"Debit") -> 0
A47: Q4 | B47: =SUM(B11:B13) -> 0 | C47: =SUM(C11:C13) -> 0 | D47: =SUM(D11:D13) -> 0 | E47: =SUM(E11:E13) -> 0 | F47: =SUM(F11:F13) -> 0 | G47: =SUM(G11:G13) -> 0 | H47: =SUM(H11:H13) -> 0 | I47: =SUM(I11:I13) -> 0 | ... K47: =SUM(K11:K13) -> 0 | L47: =SUM(M11:M13) -> 0 | M47: =SUM(N11:N13) -> 0 | N47: =SUM(B42:B44) -> 0 | O47: =SUM(C42:C44) -> 0 | P47: =SUM(D42:D44) -> 0 | Q47: =SUM(E42:E44) -> 0 | R47: =SUM(AN11:AN13) -> 0 | S47: =SUM(AO11:AO13) -> 0 | T47: =SUM(AP11:AP13) -> 0 | U47: =SUM(AQ11:AQ13) -> 0 | V47: =SUM(AR11:AR13) -> 0 | Y47: =SUM(AU11:AU13) -> 0 | Z47: =SUM(AV11:AV13) -> 0 | AA47: =SUM(AW11:AW13) -> 0 | AB47: =SUM(AX11:AX13) -> 0 | AH47: =SUM(AH11:AH13) -> 0
A49: Month | B49: Salaries | C49: Utilities | D49: Fuel | E49: Petty | F49: Rent | G49: Tax & P | H49: Purchase | I49: Incentive | J49: Comm | K49: Service | L49: Non | M49: Other | N49: WHT | O49: Rev Tax | P49: Dividend | Q49: Audit fee | R49: Credit | S49: Payable | T49: Disbursement | U49: Repayment | V49: Liabelity | W49: DC | Y49: Whl Pur | AA49: Adjust | AB49: RTGS | AH49: RTGS

Sheet Sheet1
B1: BANK & CASH FLOW DASHBOARD
B3: ="Live view of bank balances, inflows/outflows and monthly trend | Source: Trans ledger | Generated "&TEXT(TODAY(),"mmmm d, yyyy") -> Live view of bank balances, inflows/outflows and monthly trend | Source: Trans ledger | Generated July 15, 2026
B5: TOTAL CASH POSITION | E5: TOTAL INFLOW (CREDIT) | H5: TOTAL OUTFLOW (DEBIT) | K5: NET CASH FLOW
B6: =SUM(F16:F25) -> 2513678.6 | E6: =SUMIF([1]Trans!$C:$C,"Credit",[1]Trans!$D:$D) -> 2703700 | H6: =SUMIF([1]Trans!$C:$C,"Debit",[1]Trans!$D:$D) -> 130000 | K6: =E6-H6 -> 2573700
B7: ="Across "&COUNTA($B16:$B25)&" bank accounts" -> Across 10 bank accounts | E7: =COUNTIF([1]Trans!$C:$C,"Credit")&" credit transactions" -> 3 credit transactions | H7: =COUNTIF([1]Trans!$C:$C,"Debit")&" debit transactions" -> 2 debit transactions | K7: =IF(K6>=0,"Positive flow","Negative flow") -> Positive flow
B9: TRANSACTIONS RECORDED | E9: AVERAGE TRANSACTION SIZE | H9: HIGHEST BANK BALANCE | K9: LOWEST BANK BALANCE
B10: =COUNTA([1]Trans!$D$2:$D$5000) -> 5 | E10: =IFERROR(AVERAGE([1]Trans!$D$2:$D$5000),0) -> 566740 | H10: =INDEX($B$16:$B$25,MATCH(MAX($F$16:$F$25),$F$16:$F$25,0)) -> Total | K10: =INDEX($B$16:$B$25,MATCH(MIN($F$16:$F$25),$F$16:$F$25,0)) -> BOA
B11: ="Since ledger inception" -> Since ledger inception | E11: ="Per recorded transaction" -> Per recorded transaction | H11: =TEXT(MAX($F$16:$F$25),"#,##0")&" ETB" -> 1,752,081 ETB | K11: =TEXT(MIN($F$16:$F$25),"#,##0")&" ETB" -> 1,354 ETB
B13: CASH POSITION BY BANK
B14: Bank | C14: Opening Bal. | D14: Credit | E14: Debit | F14: Closing Bal. | G14: % of Total
B15: =[1]List!N2 -> CBE | C15: =[1]List!O2 -> 584984 | D15: =IFERROR(SUMIFS(Trans!$D:$D,Trans!$B:$B,$B15,Trans!$C:$C,"Credit"),0) -> 535500 | E15: =IFERROR(SUMIFS([1]Trans!$D:$D,[1]Trans!$B:$B,$B15,[1]Trans!$C:$C,"Debit"),0) -> 130000 | F15: =C15+D15-E15 -> 990484 | G15: =IFERROR(F15/$F$25,0) -> 0.56531852
B16: =[1]List!N3 -> COOP | C16: =[1]List!O3 -> 71149 | D16: =IFERROR(SUMIFS([1]Trans!$D:$D,[1]Trans!$B:$B,$B16,[1]Trans!$C:$C,"Credit"),0) -> 0 | E16: =IFERROR(SUMIFS([1]Trans!$D:$D,[1]Trans!$B:$B,$B16,[1]Trans!$C:$C,"Debit"),0) -> 0 | F16: =C16+D16-E16 -> 71149 | G16: =IFERROR(F16/$F$25,0) -> 0.040608275
B17: =[1]List!N4 -> AIB | C17: =[1]List!O4 -> 151882.3 | D17: =IFERROR(SUMIFS([1]Trans!$D:$D,[1]Trans!$B:$B,$B17,[1]Trans!$C:$C,"Credit"),0) -> 0 | E17: =IFERROR(SUMIFS([1]Trans!$D:$D,[1]Trans!$B:$B,$B17,[1]Trans!$C:$C,"Debit"),0) -> 0 | F17: =C17+D17-E17 -> 151882.3 | G17: =IFERROR(F17/$F$25,0) -> 0.086686788
B18: =[1]List!N5 -> BOA | C18: =[1]List!O5 -> 1354 | D18: =IFERROR(SUMIFS([1]Trans!$D:$D,[1]Trans!$B:$B,$B18,[1]Trans!$C:$C,"Credit"),0) -> 0 | E18: =IFERROR(SUMIFS([1]Trans!$D:$D,[1]Trans!$B:$B,$B18,[1]Trans!$C:$C,"Debit"),0) -> 0 | F18: =C18+D18-E18 -> 1354 | G18: =IFERROR(F18/$F$25,0) -> 0.00077279519
B19: =[1]List!N6 -> Berhan | C19: =[1]List!O6 -> 5928 | D19: =IFERROR(SUMIFS([1]Trans!$D:$D,[1]Trans!$B:$B,$B19,[1]Trans!$C:$C,"Credit"),0) -> 203700 | E19: =IFERROR(SUMIFS([1]Trans!$D:$D,[1]Trans!$B:$B,$B19,[1]Trans!$C:$C,"Debit"),0) -> 0 | F19: =C19+D19-E19 -> 209628 | G19: =IFERROR(F19/$F$25,0) -> 0.11964513
B20: =[1]List!N7 -> Siinqe | C20: =[1]List!O7 -> 225631 | D20: =IFERROR(SUMIFS([1]Trans!$D:$D,[1]Trans!$B:$B,$B20,[1]Trans!$C:$C,"Credit"),0) -> 0 | E20: =IFERROR(SUMIFS([1]Trans!$D:$D,[1]Trans!$B:$B,$B20,[1]Trans!$C:$C,"Debit"),0) -> 0 | F20: =C20+D20-E20 -> 225631 | G20: =IFERROR(F20/$F$25,0) -> 0.12877884
B21: =[1]List!N8 -> Zemen | C21: =[1]List!O8 -> 6581 | D21: =IFERROR(SUMIFS([1]Trans!$D:$D,[1]Trans!$B:$B,$B21,[1]Trans!$C:$C,"Credit"),0) -> 0 | E21: =IFERROR(SUMIFS([1]Trans!$D:$D,[1]Trans!$B:$B,$B21,[1]Trans!$C:$C,"Debit"),0) -> 0 | F21: =C21+D21-E21 -> 6581 | G21: =IFERROR(F21/$F$25,0) -> 0.0037561042
B22: =[1]List!N9 -> OIB | C22: =[1]List!O9 -> 1792 | D22: =IFERROR(SUMIFS([1]Trans!$D:$D,[1]Trans!$B:$B,$B22,[1]Trans!$C:$C,"Credit"),0) -> 0 | E22: =IFERROR(SUMIFS([1]Trans!$D:$D,[1]Trans!$B:$B,$B22,[1]Trans!$C:$C,"Debit"),0) -> 0 | F22: =C22+D22-E22 -> 1792 | G22: =IFERROR(F22/$F$25,0) -> 0.0010227836
B23: =[1]List!N10 -> Hibrate | C23: =[1]List!O10 -> 2795 | D23: =IFERROR(SUMIFS([1]Trans!$D:$D,[1]Trans!$B:$B,$B23,[1]Trans!$C:$C,"Credit"),0) -> 0 | E23: =IFERROR(SUMIFS([1]Trans!$D:$D,[1]Trans!$B:$B,$B23,[1]Trans!$C:$C,"Debit"),0) -> 0 | F23: =C23+D23-E23 -> 2795 | G23: =IFERROR(F23/$F$25,0) -> 0.0015952456
B24: =[1]List!N11 -> Dashin | C24: =[1]List!O11 -> 90785 | D24: =IFERROR(SUMIFS([1]Trans!$D:$D,[1]Trans!$B:$B,$B24,[1]Trans!$C:$C,"Credit"),0) -> 0 | E24: =IFERROR(SUMIFS([1]Trans!$D:$D,[1]Trans!$B:$B,$B24,[1]Trans!$C:$C,"Debit"),0) -> 0 | F24: =C24+D24-E24 -> 90785 | G24: =IFERROR(F24/$F$25,0) -> 0.051815518
B25: Total | C25: =SUM(C15:C24) -> 1142881.3 | D25: =SUM(D15:D24) -> 739200 | E25: =SUM(E15:E24) -> 130000 | F25: =SUM(F15:F24) -> 1752081.3 | G25: =SUM(G15:G24) -> 1
B27: MONTHLY CASH FLOW TREND (Ethiopian Calendar Month)
B28: Month | C28: Inflow (Credit) | D28: Outflow (Debit) | E28: Net Cash Flow
B29: 2018-11 | C29: =SUMIFS([1]Trans!$D:$D,[1]Trans!$I:$I,$B29,[1]Trans!$C:$C,"Credit") -> 2703700 | D29: =SUMIFS([1]Trans!$D:$D,[1]Trans!$I:$I,$B29,[1]Trans!$C:$C,"Debit") -> 130000 | E29: =C29-D29 -> 2573700
B30: 2018-12 | C30: =SUMIFS([1]Trans!$D:$D,[1]Trans!$I:$I,$B30,[1]Trans!$C:$C,"Credit") -> 0 | D30: =SUMIFS([1]Trans!$D:$D,[1]Trans!$I:$I,$B30,[1]Trans!$C:$C,"Debit") -> 0 | E30: =C30-D30 -> 0
B31: 2019-01 | C31: =SUMIFS([1]Trans!$D:$D,[1]Trans!$I:$I,$B31,[1]Trans!$C:$C,"Credit") -> 0 | D31: =SUMIFS([1]Trans!$D:$D,[1]Trans!$I:$I,$B31,[1]Trans!$C:$C,"Debit") -> 0 | E31: =C31-D31 -> 0
B32: 2019-02 | C32: =SUMIFS([1]Trans!$D:$D,[1]Trans!$I:$I,$B32,[1]Trans!$C:$C,"Credit") -> 0 | D32: =SUMIFS([1]Trans!$D:$D,[1]Trans!$I:$I,$B32,[1]Trans!$C:$C,"Debit") -> 0 | E32: =C32-D32 -> 0
B33: 2019-03 | C33: =SUMIFS([1]Trans!$D:$D,[1]Trans!$I:$I,$B33,[1]Trans!$C:$C,"Credit") -> 0 | D33: =SUMIFS([1]Trans!$D:$D,[1]Trans!$I:$I,$B33,[1]Trans!$C:$C,"Debit") -> 0 | E33: =C33-D33 -> 0
B34: 2019-04 | C34: =SUMIFS([1]Trans!$D:$D,[1]Trans!$I:$I,$B34,[1]Trans!$C:$C,"Credit") -> 0 | D34: =SUMIFS([1]Trans!$D:$D,[1]Trans!$I:$I,$B34,[1]Trans!$C:$C,"Debit") -> 0 | E34: =C34-D34 -> 0
B35: 2019-05 | C35: =SUMIFS([1]Trans!$D:$D,[1]Trans!$I:$I,$B35,[1]Trans!$C:$C,"Credit") -> 0 | D35: =SUMIFS([1]Trans!$D:$D,[1]Trans!$I:$I,$B35,[1]Trans!$C:$C,"Debit") -> 0 | E35: =C35-D35 -> 0
B36: 2019-06 | C36: =SUMIFS([1]Trans!$D:$D,[1]Trans!$I:$I,$B36,[1]Trans!$C:$C,"Credit") -> 0 | D36: =SUMIFS([1]Trans!$D:$D,[1]Trans!$I:$I,$B36,[1]Trans!$C:$C,"Debit") -> 0 | E36: =C36-D36 -> 0
B37: 2019-07 | C37: =SUMIFS([1]Trans!$D:$D,[1]Trans!$I:$I,$B37,[1]Trans!$C:$C,"Credit") -> 0 | D37: =SUMIFS([1]Trans!$D:$D,[1]Trans!$I:$I,$B37,[1]Trans!$C:$C,"Debit") -> 0 | E37: =C37-D37 -> 0
B38: 2019-08 | C38: =SUMIFS([1]Trans!$D:$D,[1]Trans!$I:$I,$B38,[1]Trans!$C:$C,"Credit") -> 0 | D38: =SUMIFS([1]Trans!$D:$D,[1]Trans!$I:$I,$B38,[1]Trans!$C:$C,"Debit") -> 0 | E38: =C38-D38 -> 0
B39: 2019-09 | C39: =SUMIFS([1]Trans!$D:$D,[1]Trans!$I:$I,$B39,[1]Trans!$C:$C,"Credit") -> 0 | D39: =SUMIFS([1]Trans!$D:$D,[1]Trans!$I:$I,$B39,[1]Trans!$C:$C,"Debit") -> 0 | E39: =C39-D39 -> 0
B40: 2019-10 | C40: =SUMIFS([1]Trans!$D:$D,[1]Trans!$I:$I,$B40,[1]Trans!$C:$C,"Credit") -> 0 | D40: =SUMIFS([1]Trans!$D:$D,[1]Trans!$I:$I,$B40,[1]Trans!$C:$C,"Debit") -> 0 | E40: =C40-D40 -> 0
B41: Total | C41: =SUM(C29:C40) -> 2703700 | D41: =SUM(D29:D40) -> 130000 | E41: =SUM(E29:E40) -> 2573700
B43: CASH FLOW BY CATEGORY (source: Trans ledger)
B44: Income Sources | E44: Operating Expenses | H44: Non-Operating / Payables | K44: Taxes & COGS
B45: =[1]List!$A3 -> Ca sales | C45: =IFERROR(SUMIF([1]Trans!$E:$E,B45,[1]Trans!$D:$D),0) -> 0 | E45: =[1]List!$B3 -> Salaries | F45: =IFERROR(SUMIF([1]Trans!$F:$F,E45,[1]Trans!$D:$D),0) -> 0 | H45: =[1]List!$C3 -> Purchase | I45: =IFERROR(SUMIF([1]Trans!$G:$G,H45,[1]Trans!$D:$D),0) -> 0 | K45: =[1]List!$D3 -> WHT | L45: =IFERROR(SUMIF([1]Trans!$H:$H,K45,[1]Trans!$D:$D),0) -> 0
B46: =[1]List!$A4 -> Collected | C46: =IFERROR(SUMIF([1]Trans!$E:$E,B46,[1]Trans!$D:$D),0) -> 203700 | E46: =[1]List!$B4 -> Utilities | F46: =IFERROR(SUMIF([1]Trans!$F:$F,E46,[1]Trans!$D:$D),0) -> 0 | H46: =[1]List!$C4 -> Incentive | I46: =IFERROR(SUMIF([1]Trans!$G:$G,H46,[1]Trans!$D:$D),0) -> 0 | K46: =[1]List!$D4 -> Rev Tax | L46: =IFERROR(SUMIF([1]Trans!$H:$H,K46,[1]Trans!$D:$D),0) -> 0
B47: =[1]List!$A5 -> Loan | C47: =IFERROR(SUMIF([1]Trans!$E:$E,B47,[1]Trans!$D:$D),0) -> 0 | E47: =[1]List!$B5 -> Tax & P | F47: =IFERROR(SUMIF([1]Trans!$F:$F,E47,[1]Trans!$D:$D),0) -> 0 | H47: =[1]List!$C5 -> Repair | I47: =IFERROR(SUMIF([1]Trans!$G:$G,H47,[1]Trans!$D:$D),0) -> 0 | K47: =[1]List!$D5 -> Dividend | L47: =IFERROR(SUMIF([1]Trans!$H:$H,K47,[1]Trans!$D:$D),0) -> 0
B48: =[1]List!$A6 -> Credit | C48: =IFERROR(SUMIF([1]Trans!$E:$E,B48,[1]Trans!$D:$D),0) -> 0 | E48: =[1]List!$B6 -> Petty | F48: =IFERROR(SUMIF([1]Trans!$F:$F,E48,[1]Trans!$D:$D),0) -> 0 | H48: =[1]List!$C6 -> Payable | I48: =IFERROR(SUMIF([1]Trans!$G:$G,H48,[1]Trans!$D:$D),0) -> 0 | K48: =[1]List!$D6 -> Audit fee | L48: =IFERROR(SUMIF([1]Trans!$H:$H,K48,[1]Trans!$D:$D),0) -> 0
B49: =[1]List!$A7 -> Other Inc | C49: =IFERROR(SUMIF([1]Trans!$E:$E,B49,[1]Trans!$D:$D),0) -> 2500000 | E49: =[1]List!$B7 -> Fuel | F49: =IFERROR(SUMIF([1]Trans!$F:$F,E49,[1]Trans!$D:$D),0) -> 30000 | H49: =[1]List!$C7 -> Collectable | I49: =IFERROR(SUMIF([1]Trans!$G:$G,H49,[1]Trans!$D:$D),0) -> 0 | K49: =[1]List!$D7 -> Whl Pur | L49: =IFERROR(SUMIF([1]Trans!$H:$H,K49,[1]Trans!$D:$D),0) -> 0
E50: =[1]List!$B8 -> Rent | F50: =IFERROR(SUMIF([1]Trans!$F:$F,E50,[1]Trans!$D:$D),0) -> 0 | H50: =[1]List!$C8 -> Loan Paid | I50: =IFERROR(SUMIF([1]Trans!$G:$G,H50,[1]Trans!$D:$D),0) -> 0 | K50: =[1]List!$D8 -> LC | L50: =IFERROR(SUMIF([1]Trans!$H:$H,K50,[1]Trans!$D:$D),0) -> 0
E51: =[1]List!$B9 -> Comm | F51: =IFERROR(SUMIF([1]Trans!$F:$F,E51,[1]Trans!$D:$D),0) -> 0 | H51: =[1]List!$C9 -> Cr Paid | I51: =IFERROR(SUMIF([1]Trans!$G:$G,H51,[1]Trans!$D:$D),0) -> 100000 | K51: =[1]List!$D9 -> Insurance | L51: =IFERROR(SUMIF([1]Trans!$H:$H,K51,[1]Trans!$D:$D),0) -> 0
H52: =[1]List!$C10 -> Other | I52: =IFERROR(SUMIF([1]Trans!$G:$G,H52,[1]Trans!$D:$D),0) -> 0 | K52: =[1]List!$D10 -> Freight | L52: =IFERROR(SUMIF([1]Trans!$H:$H,K52,[1]Trans!$D:$D),0) -> 0
H53: =[1]List!$C11 -> Non | I53: =IFERROR(SUMIF([1]Trans!$G:$G,H53,[1]Trans!$D:$D),0) -> 0 | K53: =[1]List!$D11 -> Customs duty | L53: =IFERROR(SUMIF([1]Trans!$H:$H,K53,[1]Trans!$D:$D),0) -> 0
H54: =[1]List!$C12 -> RTGS | I54: =IFERROR(SUMIF([1]Trans!$G:$G,H54,[1]Trans!$D:$D),0) -> 0 | K54: =[1]List!$D12 -> Related | L54: =IFERROR(SUMIF([1]Trans!$H:$H,K54,[1]Trans!$D:$D),0) -> 0
H55: =[1]List!$C13 -> Adjust | I55: =IFERROR(SUMIF([1]Trans!$G:$G,H55,[1]Trans!$D:$D),0) -> 0
B56: Total | C56: =SUM(C45:C55) -> 2703700 | E56: Total | F56: =SUM(F45:F55) -> 30000 | H56: Total | I56: =SUM(I45:I55) -> 100000 | K56: Total | L56: =SUM(L45:L55) -> 0
B58: Note: All figures pull live from the "Trans" ledger and "List" master data — update those sheets and this dashboard recalculates automatically. Bank opening balances are anchored to List!O2:O11.

Sheet Sheet4
A1: Row Labels | B1: Sum of Amount
A2: Jacaranda | B2: 209400
A3: Grand Total | B3: 209400
C22: =GETPIVOTDATA("Amount",$A$1) -> 209400
A27: Credit Status | B27: Sum of Amount
A28: FP need | B28: 209400 | C28: =GETPIVOTDATA("Amount",$A$27,"C Status","Due soon") -> #REF!
A29: Grand Total | B29: 209400 | C29: =GETPIVOTDATA("Amount",$A$27,"C Status","FP need") -> 209400
C30: =GETPIVOTDATA("Amount",$A$27,"C Status","Over Due") -> #REF!
C31: =GETPIVOTDATA("Amount",$A$27,"C Status","Pending") -> #REF!
C32: =GETPIVOTDATA("Amount",$A$27,"C Status","Settled") -> #REF!
C33: =GETPIVOTDATA("Amount",$A$27) -> 209400
A44: Row Labels | B44: Sum of Amount2
A45: ሰኔ | B45: 60000
A46: ግንቦት | B46: 149400
A47: Grand Total | B47: 209400
C49: =GETPIVOTDATA("Amount",$A$44) -> 209400
A54: Row Labels | B54: Sum of Amount
A55: Credit | B55: 209400
A56: Grand Total | B56: 209400

Sheet D

Sheet CreditS (2)
A1: SN | B1: Buyer | C1: Amount | D1: Date | E1: DD | F1: P Status | G1: C Status | H1: Month | I1: CD | J1: DSO | K1: DOP | L1: Expd | M1: Rrk | N1: PP | O1: Left | Q1: =TODAY() -> 46218 | R1: Over Due | S1: =_xlfn.XLOOKUP(R1,G2:G1005,F2:F1005) -> Credit | T1: Parcial | U1: T credit | W1: Etc Sold Date | X1: Mth | Y1: Month of Sold | Z1: Etc Paid date | AA1: MthP | AB1: Etc Paid Month | AD1: WK Sold | AE1: WK Paid
A2: 1 | B2: Eman | C2: 62000 | D2: 46104 | E2: =IF(D2="","",IF(F2="paid",0,I2-J2)) -> -54 | F2: Credit | G2: =IF(F2="Paid","Settled",IF(E2="","",IF(E2<0,"Over Due",IF(E2<=10,"Due soon",IF(E2<=20,"FP need",IF(E2<=30,"Pending","Pending")))))) -> Over Due | H2: =IFERROR(CHOOSE($X2,"መስከረም","ጥቅምት","ህዳር ","ታህሳስ ","ጥር ","የካቲት ","መጋቢት ","ሚይዚያ ","ግንቦት ","ሰኔ ","ሐምሌ ","ነሐሴ ","Pagume"),"") -> መጋቢት | I2: 60 | J2: =IF(D2="","-",$Q$1-D2) -> 114 | L2: =IF(E2="","",$Q$1+E2) -> 46164 | M2: ሰኔ18 | O2: {=SUMPRODUCT(($F2:$F2="Parcial")*ABS($C2:$C2-$N2:$N2))} -> 0 | R2: =SUMIFS(C2:C1005,G2:G1005,R1) -> 1048130 | S2: =SUMIFS(C2:C1000,F2:F1000,S1) -> 2627080 | T2: =SUMIFS(O2:O1005,F2:F1005,T1) -> 13050 | U2: =T2+S2 -> 2640130 | W2: =IF($D2="","",_xlfn.LET(_xlpm.gDate,D2,_xlpm.ethYear,IF(_xlpm.gDate>=DATE(YEAR(_xlpm.gDate),9,11),YEAR(_xlpm.gDate)-7,YEAR(_xlpm.gDate)-8),_xlpm.prevEthYear,_xlpm.ethYear-1,_xlpm.startDate,IF(_xlpm.gDate>=DATE(YEAR(_xlpm.gDate),9,11),DATE(YEAR(_xlpm.gDate),9,11)+IF(MOD(_xlpm.prevEthYear,4)=3,1,0),DATE(YEAR(_xlpm.gDate)-1,9,11)+IF(MOD(_xlpm.prevEthYear,4)=3,1,0)),_xlpm.dayOfYear,_xlpm.gDate-_xlpm.startDate+1,_xlpm.month,IF(_xlpm.dayOfYear<=360,CEILING(_xlpm.dayOfYear/30,1),13),_xlpm.day,IF(_xlpm.month=13,_xlpm.dayOfYear-360,_xlpm.dayOfYear-(_xlpm.month-1)*30),TEXT(_xlpm.ethYear,"0000")&"-"&TEXT(_xlpm.month,"00")&"-"&TEXT(_xlpm.day,"00"))) -> 2018-07-14 | X2: =IF($W2="","",TEXT($W2,"mm")) -> 07 | Y2: =IFERROR(CHOOSE(X2,"መስከረም","ጥቅምት","ህዳር ","ታህሳስ ","ጥር ","የካቲት ","መጋቢት18","ሚይዚያ ","ግንቦት18","ሰኔ18","ሐምሌ ","ነሐሴ ","Pagume"),"") -> መጋቢት18 | Z2: =IF($K2="","",_xlfn.LET(_xlpm.gDate,K2,_xlpm.ethYear,IF(_xlpm.gDate>=DATE(YEAR(_xlpm.gDate),9,11),YEAR(_xlpm.gDate)-7,YEAR(_xlpm.gDate)-8),_xlpm.prevEthYear,_xlpm.ethYear-1,_xlpm.startDate,IF(_xlpm.gDate>=DATE(YEAR(_xlpm.gDate),9,11),DATE(YEAR(_xlpm.gDate),9,11)+IF(MOD(_xlpm.prevEthYear,4)=3,1,0),DATE(YEAR(_xlpm.gDate)-1,9,11)+IF(MOD(_xlpm.prevEthYear,4)=3,1,0)),_xlpm.dayOfYear,_xlpm.gDate-_xlpm.startDate+1,_xlpm.month,IF(_xlpm.dayOfYear<=360,CEILING(_xlpm.dayOfYear/30,1),13),_xlpm.day,IF(_xlpm.month=13,_xlpm.dayOfYear-360,_xlpm.dayOfYear-(_xlpm.month-1)*30),TEXT(_xlpm.ethYear,"0000")&"-"&TEXT(_xlpm.month,"00")&"-"&TEXT(_xlpm.day,"00"))) | AA2: =IF($Z2="","",TEXT($Z2,"mm")) | AB2: =IFERROR(CHOOSE(AA2,"መስከረም","ጥቅምት","ህዳር ","ታህሳስ ","ጥር ","የካቲት ","መጋቢት ","ሚይዚያ ","ግንቦት ","ሰኔ ","ሐምሌ ","ነሐሴ ","Pagume"),"") | AD2: =IF($D2="","",YEAR(D2)&"-W"&WEEKNUM(D2,2)) -> 2026-W13 | AE2: =IF($K2="","",YEAR(K2)&"-W"&WEEKNUM(K2,2))
A3: 2 | B3: Eman | C3: 353600 | D3: 46155 | E3: =IF(D3="","",IF(F3="paid",0,I3-J3)) -> -3 | F3: Credit | G3: =IF(F3="Paid","Settled",IF(E3="","",IF(E3<0,"Over Due",IF(E3<=10,"Due soon",IF(E3<=20,"FP need",IF(E3<=30,"Pending","Pending")))))) -> Over Due | H3: =IFERROR(CHOOSE($X3,"መስከረም","ጥቅምት","ህዳር ","ታህሳስ ","ጥር ","የካቲት ","መጋቢት ","ሚይዚያ ","ግንቦት ","ሰኔ ","ሐምሌ ","ነሐሴ ","Pagume"),"") -> ግንቦት | I3: 60 | J3: =IF(D3="","-",$Q$1-D3) -> 63 | L3: =IF(E3="","",$Q$1+E3) -> 46215 | M3: ሰኔ18 | O3: {=SUMPRODUCT(($F3:$F3="Parcial")*ABS($C3:$C3-$N3:$N3))} -> 0 | R3: =COUNTIF(G2:G984,R1) -> 12 | S3: =COUNTIF(F2:F984,S1) -> 30 | T3: =COUNTIF(F2:F984,T1) -> 1 | U3: =T3+S3 -> 31 | W3: =IF($D3="","",_xlfn.LET(_xlpm.gDate,D3,_xlpm.ethYear,IF(_xlpm.gDate>=DATE(YEAR(_xlpm.gDate),9,11),YEAR(_xlpm.gDate)-7,YEAR(_xlpm.gDate)-8),_xlpm.prevEthYear,_xlpm.ethYear-1,_xlpm.startDate,IF(_xlpm.gDate>=DATE(YEAR(_xlpm.gDate),9,11),DATE(YEAR(_xlpm.gDate),9,11)+IF(MOD(_xlpm.prevEthYear,4)=3,1,0),DATE(YEAR(_xlpm.gDate)-1,9,11)+IF(MOD(_xlpm.prevEthYear,4)=3,1,0)),_xlpm.dayOfYear,_xlpm.gDate-_xlpm.startDate+1,_xlpm.month,IF(_xlpm.dayOfYear<=360,CEILING(_xlpm.dayOfYear/30,1),13),_xlpm.day,IF(_xlpm.month=13,_xlpm.dayOfYear-360,_xlpm.dayOfYear-(_xlpm.month-1)*30),TEXT(_xlpm.ethYear,"0000")&"-"&TEXT(_xlpm.month,"00")&"-"&TEXT(_xlpm.day,"00"))) -> 2018-09-05 | X3: =IF($W3="","",TEXT($W3,"mm")) -> 09 | Y3: =IFERROR(CHOOSE(X3,"መስከረም","ጥቅምት","ህዳር ","ታህሳስ ","ጥር ","የካቲት ","መጋቢት18","ሚይዚያ ","ግንቦት18","ሰኔ18","ሐምሌ ","ነሐሴ ","Pagume"),"") -> ግንቦት18 | Z3: =IF($K3="","",_xlfn.LET(_xlpm.gDate,K3,_xlpm.ethYear,IF(_xlpm.gDate>=DATE(YEAR(_xlpm.gDate),9,11),YEAR(_xlpm.gDate)-7,YEAR(_xlpm.gDate)-8),_xlpm.prevEthYear,_xlpm.ethYear-1,_xlpm.startDate,IF(_xlpm.gDate>=DATE(YEAR(_xlpm.gDate),9,11),DATE(YEAR(_xlpm.gDate),9,11)+IF(MOD(_xlpm.prevEthYear,4)=3,1,0),DATE(YEAR(_xlpm.gDate)-1,9,11)+IF(MOD(_xlpm.prevEthYear,4)=3,1,0)),_xlpm.dayOfYear,_xlpm.gDate-_xlpm.startDate+1,_xlpm.month,IF(_xlpm.dayOfYear<=360,CEILING(_xlpm.dayOfYear/30,1),13),_xlpm.day,IF(_xlpm.month=13,_xlpm.dayOfYear-360,_xlpm.dayOfYear-(_xlpm.month-1)*30),TEXT(_xlpm.ethYear,"0000")&"-"&TEXT(_xlpm.month,"00")&"-"&TEXT(_xlpm.day,"00"))) | AA3: =IF($Z3="","",TEXT($Z3,"mm")) | AB3: =IFERROR(CHOOSE(AA3,"መስከረም","ጥቅምት","ህዳር ","ታህሳስ ","ጥር ","የካቲት ","መጋቢት ","ሚይዚያ ","ግንቦት ","ሰኔ ","ሐምሌ ","ነሐሴ ","Pagume"),"") | AD3: =IF($D3="","",YEAR(D3)&"-W"&WEEKNUM(D3,2)) -> 2026-W20 | AE3: =IF($K3="","",YEAR(K3)&"-W"&WEEKNUM(K3,2))
A4: 3 | B4: wilget | C4: 59900 | D4: 46155 | E4: =IF(D4="","",IF(F4="paid",0,I4-J4)) -> -33 | F4: Credit | G4: =IF(F4="Paid","Settled",IF(E4="","",IF(E4<0,"Over Due",IF(E4<=10,"Due soon",IF(E4<=20,"FP need",IF(E4<=30,"Pending","Pending")))))) -> Over Due | H4: =IFERROR(CHOOSE($X4,"መስከረም","ጥቅምት","ህዳር ","ታህሳስ ","ጥር ","የካቲት ","መጋቢት ","ሚይዚያ ","ግንቦት ","ሰኔ ","ሐምሌ ","ነሐሴ ","Pagume"),"") -> ግንቦት | I4: 30 | J4: =IF(D4="","-",$Q$1-D4) -> 63 | L4: =IF(E4="","",$Q$1+E4) -> 46185 | M4: ሰኔ18 | O4: {=SUMPRODUCT(($F4:$F4="Parcial")*ABS($C4:$C4-$N4:$N4))} -> 0 | W4: =IF($D4="","",_xlfn.LET(_xlpm.gDate,D4,_xlpm.ethYear,IF(_xlpm.gDate>=DATE(YEAR(_xlpm.gDate),9,11),YEAR(_xlpm.gDate)-7,YEAR(_xlpm.gDate)-8),_xlpm.prevEthYear,_xlpm.ethYear-1,_xlpm.startDate,IF(_xlpm.gDate>=DATE(YEAR(_xlpm.gDate),9,11),DATE(YEAR(_xlpm.gDate),9,11)+IF(MOD(_xlpm.prevEthYear,4)=3,1,0),DATE(YEAR(_xlpm.gDate)-1,9,11)+IF(MOD(_xlpm.prevEthYear,4)=3,1,0)),_xlpm.dayOfYear,_xlpm.gDate-_xlpm.startDate+1,_xlpm.month,IF(_xlpm.dayOfYear<=360,CEILING(_xlpm.dayOfYear/30,1),13),_xlpm.day,IF(_xlpm.month=13,_xlpm.dayOfYear-360,_xlpm.dayOfYear-(_xlpm.month-1)*30),TEXT(_xlpm.ethYear,"0000")&"-"&TEXT(_xlpm.month,"00")&"-"&TEXT(_xlpm.day,"00"))) -> 2018-09-05 | X4: =IF($W4="","",TEXT($W4,"mm")) -> 09 | Y4: =IFERROR(CHOOSE(X4,"መስከረም","ጥቅምት","ህዳር ","ታህሳስ ","ጥር ","የካቲት ","መጋቢት18","ሚይዚያ ","ግንቦት18","ሰኔ18","ሐምሌ ","ነሐሴ ","Pagume"),"") -> ግንቦት18 | Z4: =IF($K4="","",_xlfn.LET(_xlpm.gDate,K4,_xlpm.ethYear,IF(_xlpm.gDate>=DATE(YEAR(_xlpm.gDate),9,11),YEAR(_xlpm.gDate)-7,YEAR(_xlpm.gDate)-8),_xlpm.prevEthYear,_xlpm.ethYear-1,_xlpm.startDate,IF(_xlpm.gDate>=DATE(YEAR(_xlpm.gDate),9,11),DATE(YEAR(_xlpm.gDate),9,11)+IF(MOD(_xlpm.prevEthYear,4)=3,1,0),DATE(YEAR(_xlpm.gDate)-1,9,11)+IF(MOD(_xlpm.prevEthYear,4)=3,1,0)),_xlpm.dayOfYear,_xlpm.gDate-_xlpm.startDate+1,_xlpm.month,IF(_xlpm.dayOfYear<=360,CEILING(_xlpm.dayOfYear/30,1),13),_xlpm.day,IF(_xlpm.month=13,_xlpm.dayOfYear-360,_xlpm.dayOfYear-(_xlpm.month-1)*30),TEXT(_xlpm.ethYear,"0000")&"-"&TEXT(_xlpm.month,"00")&"-"&TEXT(_xlpm.day,"00"))) | AA4: =IF($Z4="","",TEXT($Z4,"mm")) | AB4: =IFERROR(CHOOSE(AA4,"መስከረም","ጥቅምት","ህዳር ","ታህሳስ ","ጥር ","የካቲት ","መጋቢት ","ሚይዚያ ","ግንቦት ","ሰኔ ","ሐምሌ ","ነሐሴ ","Pagume"),"") | AD4: =IF($D4="","",YEAR(D4)&"-W"&WEEKNUM(D4,2)) -> 2026-W20 | AE4: =IF($K4="","",YEAR(K4)&"-W"&WEEKNUM(K4,2))
A5: 4 | B5: Abune/A | C5: 43800 | D5: 46157 | E5: =IF(D5="","",IF(F5="paid",0,I5-J5)) -> -31 | F5: Credit | G5: =IF(F5="Paid","Settled",IF(E5="","",IF(E5<0,"Over Due",IF(E5<=10,"Due soon",IF(E5<=20,"FP need",IF(E5<=30,"Pending","Pending")))))) -> Over Due | H5: =IFERROR(CHOOSE($X5,"መስከረም","ጥቅምት","ህዳር ","ታህሳስ ","ጥር ","የካቲት ","መጋቢት ","ሚይዚያ ","ግንቦት ","ሰኔ ","ሐምሌ ","ነሐሴ ","Pagume"),"") -> ግንቦት | I5: 30 | J5: =IF(D5="","-",$Q$1-D5) -> 61 | L5: =IF(E5="","",$Q$1+E5) -> 46187 | M5: ሰኔ18 | O5: {=SUMPRODUCT(($F5:$F5="Parcial")*ABS($C5:$C5-$N5:$N5))} -> 0 | W5: =IF($D5="","",_xlfn.LET(_xlpm.gDate,D5,_xlpm.ethYear,IF(_xlpm.gDate>=DATE(YEAR(_xlpm.gDate),9,11),YEAR(_xlpm.gDate)-7,YEAR(_xlpm.gDate)-8),_xlpm.prevEthYear,_xlpm.ethYear-1,_xlpm.startDate,IF(_xlpm.gDate>=DATE(YEAR(_xlpm.gDate),9,11),DATE(YEAR(_xlpm.gDate),9,11)+IF(MOD(_xlpm.prevEthYear,4)=3,1,0),DATE(YEAR(_xlpm.gDate)-1,9,11)+IF(MOD(_xlpm.prevEthYear,4)=3,1,0)),_xlpm.dayOfYear,_xlpm.gDate-_xlpm.startDate+1,_xlpm.month,IF(_xlpm.dayOfYear<=360,CEILING(_xlpm.dayOfYear/30,1),13),_xlpm.day,IF(_xlpm.month=13,_xlpm.dayOfYear-360,_xlpm.dayOfYear-(_xlpm.month-1)*30),TEXT(_xlpm.ethYear,"0000")&"-"&TEXT(_xlpm.month,"00")&"-"&TEXT(_xlpm.day,"00"))) -> 2018-09-07 | X5: =IF($W5="","",TEXT($W5,"mm")) -> 09 | Y5: =IFERROR(CHOOSE(X5,"መስከረም","ጥቅምት","ህዳር ","ታህሳስ ","ጥር ","የካቲት ","መጋቢት18","ሚይዚያ ","ግንቦት18","ሰኔ18","ሐምሌ ","ነሐሴ ","Pagume"),"") -> ግንቦት18 | Z5: =IF($K5="","",_xlfn.LET(_xlpm.gDate,K5,_xlpm.ethYear,IF(_xlpm.gDate>=DATE(YEAR(_xlpm.gDate),9,11),YEAR(_xlpm.gDate)-7,YEAR(_xlpm.gDate)-8),_xlpm.prevEthYear,_xlpm.ethYear-1,_xlpm.startDate,IF(_xlpm.gDate>=DATE(YEAR(_xlpm.gDate),9,11),DATE(YEAR(_xlpm.gDate),9,11)+IF(MOD(_xlpm.prevEthYear,4)=3,1,0),DATE(YEAR(_xlpm.gDate)-1,9,11)+IF(MOD(_xlpm.prevEthYear,4)=3,1,0)),_xlpm.dayOfYear,_xlpm.gDate-_xlpm.startDate+1,_xlpm.month,IF(_xlpm.dayOfYear<=360,CEILING(_xlpm.dayOfYear/30,1),13),_xlpm.day,IF(_xlpm.month=13,_xlpm.dayOfYear-360,_xlpm.dayOfYear-(_xlpm.month-1)*30),TEXT(_xlpm.ethYear,"0000")&"-"&TEXT(_xlpm.month,"00")&"-"&TEXT(_xlpm.day,"00"))) | AA5: =IF($Z5="","",TEXT($Z5,"mm")) | AB5: =IFERROR(CHOOSE(AA5,"መስከረም","ጥቅምት","ህዳር ","ታህሳስ ","ጥር ","የካቲት ","መጋቢት ","ሚይዚያ ","ግንቦት ","ሰኔ ","ሐምሌ ","ነሐሴ ","Pagume"),"") | AD5: =IF($D5="","",YEAR(D5)&"-W"&WEEKNUM(D5,2)) -> 2026-W20 | AE5: =IF($K5="","",YEAR(K5)&"-W"&WEEKNUM(K5,2))
A6: 5 | B6: Dr nigatu | C6: 218455 | D6: 46161 | E6: =IF(D6="","",IF(F6="paid",0,I6-J6)) -> -27 | F6: Credit | G6: =IF(F6="Paid","Settled",IF(E6="","",IF(E6<0,"Over Due",IF(E6<=10,"Due soon",IF(E6<=20,"FP need",IF(E6<=30,"Pending","Pending")))))) -> Over Due | H6: =IFERROR(CHOOSE($X6,"መስከረም","ጥቅምት","ህዳር ","ታህሳስ ","ጥር ","የካቲት ","መጋቢት ","ሚይዚያ ","ግንቦት ","ሰኔ ","ሐምሌ ","ነሐሴ ","Pagume"),"") -> ግንቦት | I6: 30 | J6: =IF(D6="","-",$Q$1-D6) -> 57 | L6: =IF(E6="","",$Q$1+E6) -> 46191 | M6: ሰኔ18 | O6: {=SUMPRODUCT(($F6:$F6="Parcial")*ABS($C6:$C6-$N6:$N6))} -> 0 | W6: =IF($D6="","",_xlfn.LET(_xlpm.gDate,D6,_xlpm.ethYear,IF(_xlpm.gDate>=DATE(YEAR(_xlpm.gDate),9,11),YEAR(_xlpm.gDate)-7,YEAR(_xlpm.gDate)-8),_xlpm.prevEthYear,_xlpm.ethYear-1,_xlpm.startDate,IF(_xlpm.gDate>=DATE(YEAR(_xlpm.gDate),9,11),DATE(YEAR(_xlpm.gDate),9,11)+IF(MOD(_xlpm.prevEthYear,4)=3,1,0),DATE(YEAR(_xlpm.gDate)-1,9,11)+IF(MOD(_xlpm.prevEthYear,4)=3,1,0)),_xlpm.dayOfYear,_xlpm.gDate-_xlpm.startDate+1,_xlpm.month,IF(_xlpm.dayOfYear<=360,CEILING(_xlpm.dayOfYear/30,1),13),_xlpm.day,IF(_xlpm.month=13,_xlpm.dayOfYear-360,_xlpm.dayOfYear-(_xlpm.month-1)*30),TEXT(_xlpm.ethYear,"0000")&"-"&TEXT(_xlpm.month,"00")&"-"&TEXT(_xlpm.day,"00"))) -> 2018-09-11 | X6: =IF($W6="","",TEXT($W6,"mm")) -> 09 | Y6: =IFERROR(CHOOSE(X6,"መስከረም","ጥቅምት","ህዳር ","ታህሳስ ","ጥር ","የካቲት ","መጋቢት18","ሚይዚያ ","ግንቦት18","ሰኔ18","ሐምሌ ","ነሐሴ ","Pagume"),"") -> ግንቦት18 | Z6: =IF($K6="","",_xlfn.LET(_xlpm.gDate,K6,_xlpm.ethYear,IF(_xlpm.gDate>=DATE(YEAR(_xlpm.gDate),9,11),YEAR(_xlpm.gDate)-7,YEAR(_xlpm.gDate)-8),_xlpm.prevEthYear,_xlpm.ethYear-1,_xlpm.startDate,IF(_xlpm.gDate>=DATE(YEAR(_xlpm.gDate),9,11),DATE(YEAR(_xlpm.gDate),9,11)+IF(MOD(_xlpm.prevEthYear,4)=3,1,0),DATE(YEAR(_xlpm.gDate)-1,9,11)+IF(MOD(_xlpm.prevEthYear,4)=3,1,0)),_xlpm.dayOfYear,_xlpm.gDate-_xlpm.startDate+1,_xlpm.month,IF(_xlpm.dayOfYear<=360,CEILING(_xlpm.dayOfYear/30,1),13),_xlpm.day,IF(_xlpm.month=13,_xlpm.dayOfYear-360,_xlpm.dayOfYear-(_xlpm.month-1)*30),TEXT(_xlpm.ethYear,"0000")&"-"&TEXT(_xlpm.month,"00")&"-"&TEXT(_xlpm.day,"00"))) | AA6: =IF($Z6="","",TEXT($Z6,"mm")) | AB6: =IFERROR(CHOOSE(AA6,"መስከረም","ጥቅምት","ህዳር ","ታህሳስ ","ጥር ","የካቲት ","መጋቢት ","ሚይዚያ ","ግንቦት ","ሰኔ ","ሐምሌ ","ነሐሴ ","Pagume"),"") | AD6: =IF($D6="","",YEAR(D6)&"-W"&WEEKNUM(D6,2)) -> 2026-W21 | AE6: =IF($K6="","",YEAR(K6)&"-W"&WEEKNUM(K6,2))
A7: 6 | B7: Zemen | C7: 35500 | D7: 46161 | E7: =IF(D7="","",IF(F7="paid",0,I7-J7)) -> -27 | F7: Credit | G7: =IF(F7="Paid","Settled",IF(E7="","",IF(E7<0,"Over Due",IF(E7<=10,"Due soon",IF(E7<=20,"FP need",IF(E7<=30,"Pending","Pending")))))) -> Over Due | H7: =IFERROR(CHOOSE($X7,"መስከረም","ጥቅምት","ህዳር ","ታህሳስ ","ጥር ","የካቲት ","መጋቢት ","ሚይዚያ ","ግንቦት ","ሰኔ ","ሐምሌ ","ነሐሴ ","Pagume"),"") -> ግንቦት | I7: 30 | J7: =IF(D7="","-",$Q$1-D7) -> 57 | L7: =IF(E7="","",$Q$1+E7) -> 46191 | M7: ሰኔ18 | O7: {=SUMPRODUCT(($F7:$F7="Parcial")*ABS($C7:$C7-$N7:$N7))} -> 0 | W7: =IF($D7="","",_xlfn.LET(_xlpm.gDate,D7,_xlpm.ethYear,IF(_xlpm.gDate>=DATE(YEAR(_xlpm.gDate),9,11),YEAR(_xlpm.gDate)-7,YEAR(_xlpm.gDate)-8),_xlpm.prevEthYear,_xlpm.ethYear-1,_xlpm.startDate,IF(_xlpm.gDate>=DATE(YEAR(_xlpm.gDate),9,11),DATE(YEAR(_xlpm.gDate),9,11)+IF(MOD(_xlpm.prevEthYear,4)=3,1,0),DATE(YEAR(_xlpm.gDate)-1,9,11)+IF(MOD(_xlpm.prevEthYear,4)=3,1,0)),_xlpm.dayOfYear,_xlpm.gDate-_xlpm.startDate+1,_xlpm.month,IF(_xlpm.dayOfYear<=360,CEILING(_xlpm.dayOfYear/30,1),13),_xlpm.day,IF(_xlpm.month=13,_xlpm.dayOfYear-360,_xlpm.dayOfYear-(_xlpm.month-1)*30),TEXT(_xlpm.ethYear,"0000")&"-"&TEXT(_xlpm.month,"00")&"-"&TEXT(_xlpm.day,"00"))) -> 2018-09-11 | X7: =IF($W7="","",TEXT($W7,"mm")) -> 09 | Y7: =IFERROR(CHOOSE(X7,"መስከረም","ጥቅምት","ህዳር ","ታህሳስ ","ጥር ","የካቲት ","መጋቢት18","ሚይዚያ ","ግንቦት18","ሰኔ18","ሐምሌ ","ነሐሴ ","Pagume"),"") -> ግንቦት18 | Z7: =IF($K7="","",_xlfn.LET(_xlpm.gDate,K7,_xlpm.ethYear,IF(_xlpm.gDate>=DATE(YEAR(_xlpm.gDate),9,11),YEAR(_xlpm.gDate)-7,YEAR(_xlpm.gDate)-8),_xlpm.prevEthYear,_xlpm.ethYear-1,_xlpm.startDate,IF(_xlpm.gDate>=DATE(YEAR(_xlpm.gDate),9,11),DATE(YEAR(_xlpm.gDate),9,11)+IF(MOD(_xlpm.prevEthYear,4)=3,1,0),DATE(YEAR(_xlpm.gDate)-1,9,11)+IF(MOD(_xlpm.prevEthYear,4)=3,1,0)),_xlpm.dayOfYear,_xlpm.gDate-_xlpm.startDate+1,_xlpm.month,IF(_xlpm.dayOfYear<=360,CEILING(_xlpm.dayOfYear/30,1),13),_xlpm.day,IF(_xlpm.month=13,_xlpm.dayOfYear-360,_xlpm.dayOfYear-(_xlpm.month-1)*30),TEXT(_xlpm.ethYear,"0000")&"-"&TEXT(_xlpm.month,"00")&"-"&TEXT(_xlpm.day,"00"))) | AA7: =IF($Z7="","",TEXT($Z7,"mm")) | AB7: =IFERROR(CHOOSE(AA7,"መስከረም","ጥቅምት","ህዳር ","ታህሳስ ","ጥር ","የካቲት ","መጋቢት ","ሚይዚያ ","ግንቦት ","ሰኔ ","ሐምሌ ","ነሐሴ ","Pagume"),"") | AD7: =IF($D7="","",YEAR(D7)&"-W"&WEEKNUM(D7,2)) -> 2026-W21 | AE7: =IF($K7="","",YEAR(K7)&"-W"&WEEKNUM(K7,2))
A8: 7 | B8: Yeorit pharm | C8: 33050 | D8: 46164 | E8: =IF(D8="","",IF(F8="paid",0,I8-J8)) -> -24 | F8: Parcial | G8: =IF(F8="Paid","Settled",IF(E8="","",IF(E8<0,"Over Due",IF(E8<=10,"Due soon",IF(E8<=20,"FP need",IF(E8<=30,"Pending","Pending")))))) -> Over Due | H8: =IFERROR(CHOOSE($X8,"መስከረም","ጥቅምት","ህዳር ","ታህሳስ ","ጥር ","የካቲት ","መጋቢት ","ሚይዚያ ","ግንቦት ","ሰኔ ","ሐምሌ ","ነሐሴ ","Pagume"),"") -> ግንቦት | I8: 30 | J8: =IF(D8="","-",$Q$1-D8) -> 54 | K8: 46183 | L8: =IF(E8="","",$Q$1+E8) -> 46194 | M8: ሰኔ18 | N8: 20000 | O8: {=SUMPRODUCT(($F8:$F8="Parcial")*ABS($C8:$C8-$N8:$N8))} -> 13050 | W8: =IF($D8="","",_xlfn.LET(_xlpm.gDate,D8,_xlpm.ethYear,IF(_xlpm.gDate>=DATE(YEAR(_xlpm.gDate),9,11),YEAR(_xlpm.gDate)-7,YEAR(_xlpm.gDate)-8),_xlpm.prevEthYear,_xlpm.ethYear-1,_xlpm.startDate,IF(_xlpm.gDate>=DATE(YEAR(_xlpm.gDate),9,11),DATE(YEAR(_xlpm.gDate),9,11)+IF(MOD(_xlpm.prevEthYear,4)=3,1,0),DATE(YEAR(_xlpm.gDate)-1,9,11)+IF(MOD(_xlpm.prevEthYear,4)=3,1,0)),_xlpm.dayOfYear,_xlpm.gDate-_xlpm.startDate+1,_xlpm.month,IF(_xlpm.dayOfYear<=360,CEILING(_xlpm.dayOfYear/30,1),13),_xlpm.day,IF(_xlpm.month=13,_xlpm.dayOfYear-360,_xlpm.dayOfYear-(_xlpm.month-1)*30),TEXT(_xlpm.ethYear,"0000")&"-"&TEXT(_xlpm.month,"00")&"-"&TEXT(_xlpm.day,"00"))) -> 2018-09-14 | X8: =IF($W8="","",TEXT($W8,"mm")) -> 09 | Y8: =IFERROR(CHOOSE(X8,"መስከረም","ጥቅምት","ህዳር ","ታህሳስ ","ጥር ","የካቲት ","መጋቢት18","ሚይዚያ ","ግንቦት18","ሰኔ18","ሐምሌ ","ነሐሴ ","Pagume"),"") -> ግንቦት18 | Z8: =IF($K8="","",_xlfn.LET(_xlpm.gDate,K8,_xlpm.ethYear,IF(_xlpm.gDate>=DATE(YEAR(_xlpm.gDate),9,11),YEAR(_xlpm.gDate)-7,YEAR(_xlpm.gDate)-8),_xlpm.prevEthYear,_xlpm.ethYear-1,_xlpm.startDate,IF(_xlpm.gDate>=DATE(YEAR(_xlpm.gDate),9,11),DATE(YEAR(_xlpm.gDate),9,11)+IF(MOD(_xlpm.prevEthYear,4)=3,1,0),DATE(YEAR(_xlpm.gDate)-1,9,11)+IF(MOD(_xlpm.prevEthYear,4)=3,1,0)),_xlpm.dayOfYear,_xlpm.gDate-_xlpm.startDate+1,_xlpm.month,IF(_xlpm.dayOfYear<=360,CEILING(_xlpm.dayOfYear/30,1),13),_xlpm.day,IF(_xlpm.month=13,_xlpm.dayOfYear-360,_xlpm.dayOfYear-(_xlpm.month-1)*30),TEXT(_xlpm.ethYear,"0000")&"-"&TEXT(_xlpm.month,"00")&"-"&TEXT(_xlpm.day,"00"))) -> 2018-10-03 | AA8: =IF($Z8="","",TEXT($Z8,"mm")) -> 10 | AB8: =IFERROR(CHOOSE(AA8,"መስከረም","ጥቅምት","ህዳር ","ታህሳስ ","ጥር ","የካቲት ","መጋቢት ","ሚይዚያ ","ግንቦት ","ሰኔ ","ሐምሌ ","ነሐሴ ","Pagume"),"") -> ሰኔ | AD8: =IF($D8="","",YEAR(D8)&"-W"&WEEKNUM(D8,2)) -> 2026-W21 | AE8: =IF($K8="","",YEAR(K8)&"-W"&WEEKNUM(K8,2)) -> 2026-W24
A9: 8 | B9: Flora | C9: 183875 | D9: 46164 | E9: =IF(D9="","",IF(F9="paid",0,I9-J9)) -> -24 | F9: Credit | G9: =IF(F9="Paid","Settled",IF(E9="","",IF(E9<0,"Over Due",IF(E9<=10,"Due soon",IF(E9<=20,"FP need",IF(E9<=30,"Pending","Pending")))))) -> Over Due | H9: =IFERROR(CHOOSE($X9,"መስከረም","ጥቅምት","ህዳር ","ታህሳስ ","ጥር ","የካቲት ","መጋቢት ","ሚይዚያ ","ግንቦት ","ሰኔ ","ሐምሌ ","ነሐሴ ","Pagume"),"") -> ግንቦት | I9: 30 | J9: =IF(D9="","-",$Q$1-D9) -> 54 | L9: =IF(E9="","",$Q$1+E9) -> 46194 | M9: ሰኔ18 | O9: {=SUMPRODUCT(($F9:$F9="Parcial")*ABS($C9:$C9-$N9:$N9))} -> 0 | W9: =IF($D9="","",_xlfn.LET(_xlpm.gDate,D9,_xlpm.ethYear,IF(_xlpm.gDate>=DATE(YEAR(_xlpm.gDate),9,11),YEAR(_xlpm.gDate)-7,YEAR(_xlpm.gDate)-8),_xlpm.prevEthYear,_xlpm.ethYear-1,_xlpm.startDate,IF(_xlpm.gDate>=DATE(YEAR(_xlpm.gDate),9,11),DATE(YEAR(_xlpm.gDate),9,11)+IF(MOD(_xlpm.prevEthYear,4)=3,1,0),DATE(YEAR(_xlpm.gDate)-1,9,11)+IF(MOD(_xlpm.prevEthYear,4)=3,1,0)),_xlpm.dayOfYear,_xlpm.gDate-_xlpm.startDate+1,_xlpm.month,IF(_xlpm.dayOfYear<=360,CEILING(_xlpm.dayOfYear/30,1),13),_xlpm.day,IF(_xlpm.month=13,_xlpm.dayOfYear-360,_xlpm.dayOfYear-(_xlpm.month-1)*30),TEXT(_xlpm.ethYear,"0000")&"-"&TEXT(_xlpm.month,"00")&"-"&TEXT(_xlpm.day,"00"))) -> 2018-09-14 | X9: =IF($W9="","",TEXT($W9,"mm")) -> 09 | Y9: =IFERROR(CHOOSE(X9,"መስከረም","ጥቅምት","ህዳር ","ታህሳስ ","ጥር ","የካቲት ","መጋቢት18","ሚይዚያ ","ግንቦት18","ሰኔ18","ሐምሌ ","ነሐሴ ","Pagume"),"") -> ግንቦት18 | Z9: =IF($K9="","",_xlfn.LET(_xlpm.gDate,K9,_xlpm.ethYear,IF(_xlpm.gDate>=DATE(YEAR(_xlpm.gDate),9,11),YEAR(_xlpm.gDate)-7,YEAR(_xlpm.gDate)-8),_xlpm.prevEthYear,_xlpm.ethYear-1,_xlpm.startDate,IF(_xlpm.gDate>=DATE(YEAR(_xlpm.gDate),9,11),DATE(YEAR(_xlpm.gDate),9,11)+IF(MOD(_xlpm.prevEthYear,4)=3,1,0),DATE(YEAR(_xlpm.gDate)-1,9,11)+IF(MOD(_xlpm.prevEthYear,4)=3,1,0)),_xlpm.dayOfYear,_xlpm.gDate-_xlpm.startDate+1,_xlpm.month,IF(_xlpm.dayOfYear<=360,CEILING(_xlpm.dayOfYear/30,1),13),_xlpm.day,IF(_xlpm.month=13,_xlpm.dayOfYear-360,_xlpm.dayOfYear-(_xlpm.month-1)*30),TEXT(_xlpm.ethYear,"0000")&"-"&TEXT(_xlpm.month,"00")&"-"&TEXT(_xlpm.day,"00"))) | AA9: =IF($Z9="","",TEXT($Z9,"mm")) | AB9: =IFERROR(CHOOSE(AA9,"መስከረም","ጥቅምት","ህዳር ","ታህሳስ ","ጥር ","የካቲት ","መጋቢት ","ሚይዚያ ","ግንቦት ","ሰኔ ","ሐምሌ ","ነሐሴ ","Pagume"),"") | AD9: =IF($D9="","",YEAR(D9)&"-W"&WEEKNUM(D9,2)) -> 2026-W21 | AE9: =IF($K9="","",YEAR(K9)&"-W"&WEEKNUM(K9,2))
A10: 9 | B10: Kidus/M | C10: 21950 | D10: 46165 | E10: =IF(D10="","",IF(F10="paid",0,I10-J10)) -> -23 | F10: Credit | G10: =IF(F10="Paid","Settled",IF(E10="","",IF(E10<0,"Over Due",IF(E10<=10,"Due soon",IF(E10<=20,"FP need",IF(E10<=30,"Pending","Pending")))))) -> Over Due | H10: =IFERROR(CHOOSE($X10,"መስከረም","ጥቅምት","ህዳር ","ታህሳስ ","ጥር ","የካቲት ","መጋቢት ","ሚይዚያ ","ግንቦት ","ሰኔ ","ሐምሌ ","ነሐሴ ","Pagume"),"") -> ግንቦት | I10: 30 | J10: =IF(D10="","-",$Q$1-D10) -> 53 | L10: =IF(E10="","",$Q$1+E10) -> 46195 | M10: ሰኔ18 | O10: {=SUMPRODUCT(($F10:$F10="Parcial")*ABS($C10:$C10-$N10:$N10))} -> 0 | W10: =IF($D10="","",_xlfn.LET(_xlpm.gDate,D10,_xlpm.ethYear,IF(_xlpm.gDate>=DATE(YEAR(_xlpm.gDate),9,11),YEAR(_xlpm.gDate)-7,YEAR(_xlpm.gDate)-8),_xlpm.prevEthYear,_xlpm.ethYear-1,_xlpm.startDate,IF(_xlpm.gDate>=DATE(YEAR(_xlpm.gDate),9,11),DATE(YEAR(_xlpm.gDate),9,11)+IF(MOD(_xlpm.prevEthYear,4)=3,1,0),DATE(YEAR(_xlpm.gDate)-1,9,11)+IF(MOD(_xlpm.prevEthYear,4)=3,1,0)),_xlpm.dayOfYear,_xlpm.gDate-_xlpm.startDate+1,_xlpm.month,IF(_xlpm.dayOfYear<=360,CEILING(_xlpm.dayOfYear/30,1),13),_xlpm.day,IF(_xlpm.month=13,_xlpm.dayOfYear-360,_xlpm.dayOfYear-(_xlpm.month-1)*30),TEXT(_xlpm.ethYear,"0000")&"-"&TEXT(_xlpm.month,"00")&"-"&TEXT(_xlpm.day,"00"))) -> 2018-09-15 | X10: =IF($W10="","",TEXT($W10,"mm")) -> 09 | Y10: =IFERROR(CHOOSE(X10,"መስከረም","ጥቅምት","ህዳር ","ታህሳስ ","ጥር ","የካቲት ","መጋቢት18","ሚይዚያ ","ግንቦት18","ሰኔ18","ሐምሌ ","ነሐሴ ","Pagume"),"") -> ግንቦት18 | Z10: =IF($K10="","",_xlfn.LET(_xlpm.gDate,K10,_xlpm.ethYear,IF(_xlpm.gDate>=DATE(YEAR(_xlpm.gDate),9,11),YEAR(_xlpm.gDate)-7,YEAR(_xlpm.gDate)-8),_xlpm.prevEthYear,_xlpm.ethYear-1,_xlpm.startDate,IF(_xlpm.gDate>=DATE(YEAR(_xlpm.gDate),9,11),DATE(YEAR(_xlpm.gDate),9,11)+IF(MOD(_xlpm.prevEthYear,4)=3,1,0),DATE(YEAR(_xlpm.gDate)-1,9,11)+IF(MOD(_xlpm.prevEthYear,4)=3,1,0)),_xlpm.dayOfYear,_xlpm.gDate-_xlpm.startDate+1,_xlpm.month,IF(_xlpm.dayOfYear<=360,CEILING(_xlpm.dayOfYear/30,1),13),_xlpm.day,IF(_xlpm.month=13,_xlpm.dayOfYear-360,_xlpm.dayOfYear-(_xlpm.month-1)*30),TEXT(_xlpm.ethYear,"0000")&"-"&TEXT(_xlpm.month,"00")&"-"&TEXT(_xlpm.day,"00"))) | AA10: =IF($Z10="","",TEXT($Z10,"mm")) | AB10: =IFERROR(CHOOSE(AA10,"መስከረም","ጥቅምት","ህዳር ","ታህሳስ ","ጥር ","የካቲት ","መጋቢት ","ሚይዚያ ","ግንቦት ","ሰኔ ","ሐምሌ ","ነሐሴ ","Pagume"),"") | AD10: =IF($D10="","",YEAR(D10)&"-W"&WEEKNUM(D10,2)) -> 2026-W21 | AE10: =IF($K10="","",YEAR(K10)&"-W"&WEEKNUM(K10,2))
A11: 10 | B11: wilget | C11: 85750 | D11: 46165 | E11: =IF(D11="","",IF(F11="paid",0,I11-J11)) -> 7 | F11: Credit | G11: =IF(F11="Paid","Settled",IF(E11="","",IF(E11<0,"Over Due",IF(E11<=10,"Due soon",IF(E11<=20,"FP need",IF(E11<=30,"Pending","Pending")))))) -> Due soon | H11: =IFERROR(CHOOSE($X11,"መስከረም","ጥቅምት","ህዳር ","ታህሳስ ","ጥር ","የካቲት ","መጋቢት ","ሚይዚያ ","ግንቦት ","ሰኔ ","ሐምሌ ","ነሐሴ ","Pagume"),"") -> ግንቦት | I11: 60 | J11: =IF(D11="","-",$Q$1-D11) -> 53 | L11: =IF(E11="","",$Q$1+E11) -> 46225 | M11: ሰኔ18 | O11: {=SUMPRODUCT(($F11:$F11="Parcial")*ABS($C11:$C11-$N11:$N11))} -> 0 | W11: =IF($D11="","",_xlfn.LET(_xlpm.gDate,D11,_xlpm.ethYear,IF(_xlpm.gDate>=DATE(YEAR(_xlpm.gDate),9,11),YEAR(_xlpm.gDate)-7,YEAR(_xlpm.gDate)-8),_xlpm.prevEthYear,_xlpm.ethYear-1,_xlpm.startDate,IF(_xlpm.gDate>=DATE(YEAR(_xlpm.gDate),9,11),DATE(YEAR(_xlpm.gDate),9,11)+IF(MOD(_xlpm.prevEthYear,4)=3,1,0),DATE(YEAR(_xlpm.gDate)-1,9,11)+IF(MOD(_xlpm.prevEthYear,4)=3,1,0)),_xlpm.dayOfYear,_xlpm.gDate-_xlpm.startDate+1,_xlpm.month,IF(_xlpm.dayOfYear<=360,CEILING(_xlpm.dayOfYear/30,1),13),_xlpm.day,IF(_xlpm.month=13,_xlpm.dayOfYear-360,_xlpm.dayOfYear-(_xlpm.month-1)*30),TEXT(_xlpm.ethYear,"0000")&"-"&TEXT(_xlpm.month,"00")&"-"&TEXT(_xlpm.day,"00"))) -> 2018-09-15 | X11: =IF($W11="","",TEXT($W11,"mm")) -> 09 | Y11: =IFERROR(CHOOSE(X11,"መስከረም","ጥቅምት","ህዳር ","ታህሳስ ","ጥር ","የካቲት ","መጋቢት18","ሚይዚያ ","ግንቦት18","ሰኔ18","ሐምሌ ","ነሐሴ ","Pagume"),"") -> ግንቦት18 | Z11: =IF($K11="","",_xlfn.LET(_xlpm.gDate,K11,_xlpm.ethYear,IF(_xlpm.gDate>=DATE(YEAR(_xlpm.gDate),9,11),YEAR(_xlpm.gDate)-7,YEAR(_xlpm.gDate)-8),_xlpm.prevEthYear,_xlpm.ethYear-1,_xlpm.startDate,IF(_xlpm.gDate>=DATE(YEAR(_xlpm.gDate),9,11),DATE(YEAR(_xlpm.gDate),9,11)+IF(MOD(_xlpm.prevEthYear,4)=3,1,0),DATE(YEAR(_xlpm.gDate)-1,9,11)+IF(MOD(_xlpm.prevEthYear,4)=3,1,0)),_xlpm.dayOfYear,_xlpm.gDate-_xlpm.startDate+1,_xlpm.month,IF(_xlpm.dayOfYear<=360,CEILING(_xlpm.dayOfYear/30,1),13),_xlpm.day,IF(_xlpm.month=13,_xlpm.dayOfYear-360,_xlpm.dayOfYear-(_xlpm.month-1)*30),TEXT(_xlpm.ethYear,"0000")&"-"&TEXT(_xlpm.month,"00")&"-"&TEXT(_xlpm.day,"00"))) | AA11: =IF($Z11="","",TEXT($Z11,"mm")) | AB11: =IFERROR(CHOOSE(AA11,"መስከረም","ጥቅምት","ህዳር ","ታህሳስ ","ጥር ","የካቲት ","መጋቢት ","ሚይዚያ ","ግንቦት ","ሰኔ ","ሐምሌ ","ነሐሴ ","Pagume"),"") | AD11: =IF($D11="","",YEAR(D11)&"-W"&WEEKNUM(D11,2)) -> 2026-W21 | AE11: =IF($K11="","",YEAR(K11)&"-W"&WEEKNUM(K11,2))
A12: 11 | B12: Jacaranda | C12: 60000 | D12: 46168 | E12: =IF(D12="","",IF(F12="paid",0,I12-J12)) -> 10 | F12: Credit | G12: =IF(F12="Paid","Settled",IF(E12="","",IF(E12<0,"Over Due",IF(E12<=10,"Due soon",IF(E12<=20,"FP need",IF(E12<=30,"Pending","Pending")))))) -> Due soon | H12: =IFERROR(CHOOSE($X12,"መስከረም","ጥቅምት","ህዳር ","ታህሳስ ","ጥር ","የካቲት ","መጋቢት ","ሚይዚያ ","ግንቦት ","ሰኔ ","ሐምሌ ","ነሐሴ ","Pagume"),"") -> ግንቦት | I12: 60 | J12: =IF(D12="","-",$Q$1-D12) -> 50 | L12: =IF(E12="","",$Q$1+E12) -> 46228 | M12: ሰኔ18 | O12: {=SUMPRODUCT(($F12:$F12="Parcial")*ABS($C12:$C12-$N12:$N12))} -> 0 | W12: =IF($D12="","",_xlfn.LET(_xlpm.gDate,D12,_xlpm.ethYear,IF(_xlpm.gDate>=DATE(YEAR(_xlpm.gDate),9,11),YEAR(_xlpm.gDate)-7,YEAR(_xlpm.gDate)-8),_xlpm.prevEthYear,_xlpm.ethYear-1,_xlpm.startDate,IF(_xlpm.gDate>=DATE(YEAR(_xlpm.gDate),9,11),DATE(YEAR(_xlpm.gDate),9,11)+IF(MOD(_xlpm.prevEthYear,4)=3,1,0),DATE(YEAR(_xlpm.gDate)-1,9,11)+IF(MOD(_xlpm.prevEthYear,4)=3,1,0)),_xlpm.dayOfYear,_xlpm.gDate-_xlpm.startDate+1,_xlpm.month,IF(_xlpm.dayOfYear<=360,CEILING(_xlpm.dayOfYear/30,1),13),_xlpm.day,IF(_xlpm.month=13,_xlpm.dayOfYear-360,_xlpm.dayOfYear-(_xlpm.month-1)*30),TEXT(_xlpm.ethYear,"0000")&"-"&TEXT(_xlpm.month,"00")&"-"&TEXT(_xlpm.day,"00"))) -> 2018-09-18 | X12: =IF($W12="","",TEXT($W12,"mm")) -> 09 | Y12: =IFERROR(CHOOSE(X12,"መስከረም","ጥቅምት","ህዳር ","ታህሳስ ","ጥር ","የካቲት ","መጋቢት18","ሚይዚያ ","ግንቦት18","ሰኔ18","ሐምሌ ","ነሐሴ ","Pagume"),"") -> ግንቦት18 | Z12: =IF($K12="","",_xlfn.LET(_xlpm.gDate,K12,_xlpm.ethYear,IF(_xlpm.gDate>=DATE(YEAR(_xlpm.gDate),9,11),YEAR(_xlpm.gDate)-7,YEAR(_xlpm.gDate)-8),_xlpm.prevEthYear,_xlpm.ethYear-1,_xlpm.startDate,IF(_xlpm.gDate>=DATE(YEAR(_xlpm.gDate),9,11),DATE(YEAR(_xlpm.gDate),9,11)+IF(MOD(_xlpm.prevEthYear,4)=3,1,0),DATE(YEAR(_xlpm.gDate)-1,9,11)+IF(MOD(_xlpm.prevEthYear,4)=3,1,0)),_xlpm.dayOfYear,_xlpm.gDate-_xlpm.startDate+1,_xlpm.month,IF(_xlpm.dayOfYear<=360,CEILING(_xlpm.dayOfYear/30,1),13),_xlpm.day,IF(_xlpm.month=13,_xlpm.dayOfYear-360,_xlpm.dayOfYear-(_xlpm.month-1)*30),TEXT(_xlpm.ethYear,"0000")&"-"&TEXT(_xlpm.month,"00")&"-"&TEXT(_xlpm.day,"00"))) | AA12: =IF($Z12="","",TEXT($Z12,"mm")) | AB12: =IFERROR(CHOOSE(AA12,"መስከረም","ጥቅምት","ህዳር ","ታህሳስ ","ጥር ","የካቲት ","መጋቢት ","ሚይዚያ ","ግንቦት ","ሰኔ ","ሐምሌ ","ነሐሴ ","Pagume"),"") | AD12: =IF($D12="","",YEAR(D12)&"-W"&WEEKNUM(D12,2)) -> 2026-W22 | AE12: =IF($K12="","",YEAR(K12)&"-W"&WEEKNUM(K12,2))
A13: 12 | B13: Jacaranda | C13: 89400 | D13: 46176 | E13: =IF(D13="","",IF(F13="paid",0,I13-J13)) -> 18 | F13: Credit | G13: =IF(F13="Paid","Settled",IF(E13="","",IF(E13<0,"Over Due",IF(E13<=10,"Due soon",IF(E13<=20,"FP need",IF(E13<=30,"Pending","Pending")))))) -> FP need | H13: =IFERROR(CHOOSE($X13,"መስከረም","ጥቅምት","ህዳር ","ታህሳስ ","ጥር ","የካቲት ","መጋቢት ","ሚይዚያ ","ግንቦት ","ሰኔ ","ሐምሌ ","ነሐሴ ","Pagume"),"") -> ግንቦት | I13: 60 | J13: =IF(D13="","-",$Q$1-D13) -> 42 | L13: =IF(E13="","",$Q$1+E13) -> 46236 | M13: ሰኔ18 | O13: {=SUMPRODUCT(($F13:$F13="Parcial")*ABS($C13:$C13-$N13:$N13))} -> 0 | W13: =IF($D13="","",_xlfn.LET(_xlpm.gDate,D13,_xlpm.ethYear,IF(_xlpm.gDate>=DATE(YEAR(_xlpm.gDate),9,11),YEAR(_xlpm.gDate)-7,YEAR(_xlpm.gDate)-8),_xlpm.prevEthYear,_xlpm.ethYear-1,_xlpm.startDate,IF(_xlpm.gDate>=DATE(YEAR(_xlpm.gDate),9,11),DATE(YEAR(_xlpm.gDate),9,11)+IF(MOD(_xlpm.prevEthYear,4)=3,1,0),DATE(YEAR(_xlpm.gDate)-1,9,11)+IF(MOD(_xlpm.prevEthYear,4)=3,1,0)),_xlpm.dayOfYear,_xlpm.gDate-_xlpm.startDate+1,_xlpm.month,IF(_xlpm.dayOfYear<=360,CEILING(_xlpm.dayOfYear/30,1),13),_xlpm.day,IF(_xlpm.month=13,_xlpm.dayOfYear-360,_xlpm.dayOfYear-(_xlpm.month-1)*30),TEXT(_xlpm.ethYear,"0000")&"-"&TEXT(_xlpm.month,"00")&"-"&TEXT(_xlpm.day,"00"))) -> 2018-09-26 | X13: =IF($W13="","",TEXT($W13,"mm")) -> 09 | Y13: =IFERROR(CHOOSE(X13,"መስከረም","ጥቅምት","ህዳር ","ታህሳስ ","ጥር ","የካቲት ","መጋቢት18","ሚይዚያ ","ግንቦት18","ሰኔ18","ሐምሌ ","ነሐሴ ","Pagume"),"") -> ግንቦት18 | Z13: =IF($K13="","",_xlfn.LET(_xlpm.gDate,K13,_xlpm.ethYear,IF(_xlpm.gDate>=DATE(YEAR(_xlpm.gDate),9,11),YEAR(_xlpm.gDate)-7,YEAR(_xlpm.gDate)-8),_xlpm.prevEthYear,_xlpm.ethYear-1,_xlpm.startDate,IF(_xlpm.gDate>=DATE(YEAR(_xlpm.gDate),9,11),DATE(YEAR(_xlpm.gDate),9,11)+IF(MOD(_xlpm.prevEthYear,4)=3,1,0),DATE(YEAR(_xlpm.gDate)-1,9,11)+IF(MOD(_xlpm.prevEthYear,4)=3,1,0)),_xlpm.dayOfYear,_xlpm.gDate-_xlpm.startDate+1,_xlpm.month,IF(_xlpm.dayOfYear<=360,CEILING(_xlpm.dayOfYear/30,1),13),_xlpm.day,IF(_xlpm.month=13,_xlpm.dayOfYear-360,_xlpm.dayOfYear-(_xlpm.month-1)*30),TEXT(_xlpm.ethYear,"0000")&"-"&TEXT(_xlpm.month,"00")&"-"&TEXT(_xlpm.day,"00"))) | AA13: =IF($Z13="","",TEXT($Z13,"mm")) | AB13: =IFERROR(CHOOSE(AA13,"መስከረም","ጥቅምት","ህዳር ","ታህሳስ ","ጥር ","የካቲት ","መጋቢት ","ሚይዚያ ","ግንቦት ","ሰኔ ","ሐምሌ ","ነሐሴ ","Pagume"),"") | AD13: =IF($D13="","",YEAR(D13)&"-W"&WEEKNUM(D13,2)) -> 2026-W23 | AE13: =IF($K13="","",YEAR(K13)&"-W"&WEEKNUM(K13,2))
A14: 13 | B14: mah | C14: 17500 | D14: 46176 | E14: =IF(D14="","",IF(F14="paid",0,I14-J14)) -> -12 | F14: Credit | G14: =IF(F14="Paid","Settled",IF(E14="","",IF(E14<0,"Over Due",IF(E14<=10,"Due soon",IF(E14<=20,"FP need",IF(E14<=30,"Pending","Pending")))))) -> Over Due | H14: =IFERROR(CHOOSE($X14,"መስከረም","ጥቅምት","ህዳር ","ታህሳስ ","ጥር ","የካቲት ","መጋቢት ","ሚይዚያ ","ግንቦት ","ሰኔ ","ሐምሌ ","ነሐሴ ","Pagume"),"") -> ግንቦት | I14: 30 | J14: =IF(D14="","-",$Q$1-D14) -> 42 | L14: =IF(E14="","",$Q$1+E14) -> 46206 | M14: ሰኔ18 | O14: {=SUMPRODUCT(($F14:$F14="Parcial")*ABS($C14:$C14-$N14:$N14))} -> 0 | W14: =IF($D14="","",_xlfn.LET(_xlpm.gDate,D14,_xlpm.ethYear,IF(_xlpm.gDate>=DATE(YEAR(_xlpm.gDate),9,11),YEAR(_xlpm.gDate)-7,YEAR(_xlpm.gDate)-8),_xlpm.prevEthYear,_xlpm.ethYear-1,_xlpm.startDate,IF(_xlpm.gDate>=DATE(YEAR(_xlpm.gDate),9,11),DATE(YEAR(_xlpm.gDate),9,11)+IF(MOD(_xlpm.prevEthYear,4)=3,1,0),DATE(YEAR(_xlpm.gDate)-1,9,11)+IF(MOD(_xlpm.prevEthYear,4)=3,1,0)),_xlpm.dayOfYear,_xlpm.gDate-_xlpm.startDate+1,_xlpm.month,IF(_xlpm.dayOfYear<=360,CEILING(_xlpm.dayOfYear/30,1),13),_xlpm.day,IF(_xlpm.month=13,_xlpm.dayOfYear-360,_xlpm.dayOfYear-(_xlpm.month-1)*30),TEXT(_xlpm.ethYear,"0000")&"-"&TEXT(_xlpm.month,"00")&"-"&TEXT(_xlpm.day,"00"))) -> 2018-09-26 | X14: =IF($W14="","",TEXT($W14,"mm")) -> 09 | Y14: =IFERROR(CHOOSE(X14,"መስከረም","ጥቅምት","ህዳር ","ታህሳስ ","ጥር ","የካቲት ","መጋቢት18","ሚይዚያ ","ግንቦት18","ሰኔ18","ሐምሌ ","ነሐሴ ","Pagume"),"") -> ግንቦት18 | Z14: =IF($K14="","",_xlfn.LET(_xlpm.gDate,K14,_xlpm.ethYear,IF(_xlpm.gDate>=DATE(YEAR(_xlpm.gDate),9,11),YEAR(_xlpm.gDate)-7,YEAR(_xlpm.gDate)-8),_xlpm.prevEthYear,_xlpm.ethYear-1,_xlpm.startDate,IF(_xlpm.gDate>=DATE(YEAR(_xlpm.gDate),9,11),DATE(YEAR(_xlpm.gDate),9,11)+IF(MOD(_xlpm.prevEthYear,4)=3,1,0),DATE(YEAR(_xlpm.gDate)-1,9,11)+IF(MOD(_xlpm.prevEthYear,4)=3,1,0)),_xlpm.dayOfYear,_xlpm.gDate-_xlpm.startDate+1,_xlpm.month,IF(_xlpm.dayOfYear<=360,CEILING(_xlpm.dayOfYear/30,1),13),_xlpm.day,IF(_xlpm.month=13,_xlpm.dayOfYear-360,_xlpm.dayOfYear-(_xlpm.month-1)*30),TEXT(_xlpm.ethYear,"0000")&"-"&TEXT(_xlpm.month,"00")&"-"&TEXT(_xlpm.day,"00"))) | AA14: =IF($Z14="","",TEXT($Z14,"mm")) | AB14: =IFERROR(CHOOSE(AA14,"መስከረም","ጥቅምት","ህዳር ","ታህሳስ ","ጥር ","የካቲት ","መጋቢት ","ሚይዚያ ","ግንቦት ","ሰኔ ","ሐምሌ ","ነሐሴ ","Pagume"),"") | AD14: =IF($D14="","",YEAR(D14)&"-W"&WEEKNUM(D14,2)) -> 2026-W23 | AE14: =IF($K14="","",YEAR(K14)&"-W"&WEEKNUM(K14,2))
A15: 14 | B15: wajin | C15: 102000 | D15: 46177 | E15: =IF(D15="","",IF(F15="paid",0,I15-J15)) -> 19 | F15: Credit | G15: =IF(F15="Paid","Settled",IF(E15="","",IF(E15<0,"Over Due",IF(E15<=10,"Due soon",IF(E15<=20,"FP need",IF(E15<=30,"Pending","Pending")))))) -> FP need | H15: =IFERROR(CHOOSE($X15,"መስከረም","ጥቅምት","ህዳር ","ታህሳስ ","ጥር ","የካቲት ","መጋቢት ","ሚይዚያ ","ግንቦት ","ሰኔ ","ሐምሌ ","ነሐሴ ","Pagume"),"") -> ግንቦት | I15: 60 | J15: =IF(D15="","-",$Q$1-D15) -> 41 | L15: =IF(E15="","",$Q$1+E15) -> 46237 | M15: ሰኔ18 | O15: {=SUMPRODUCT(($F15:$F15="Parcial")*ABS($C15:$C15-$N15:$N15))} -> 0 | W15: =IF($D15="","",_xlfn.LET(_xlpm.gDate,D15,_xlpm.ethYear,IF(_xlpm.gDate>=DATE(YEAR(_xlpm.gDate),9,11),YEAR(_xlpm.gDate)-7,YEAR(_xlpm.gDate)-8),_xlpm.prevEthYear,_xlpm.ethYear-1,_xlpm.startDate,IF(_xlpm.gDate>=DATE(YEAR(_xlpm.gDate),9,11),DATE(YEAR(_xlpm.gDate),9,11)+IF(MOD(_xlpm.prevEthYear,4)=3,1,0),DATE(YEAR(_xlpm.gDate)-1,9,11)+IF(MOD(_xlpm.prevEthYear,4)=3,1,0)),_xlpm.dayOfYear,_xlpm.gDate-_xlpm.startDate+1,_xlpm.month,IF(_xlpm.dayOfYear<=360,CEILING(_xlpm.dayOfYear/30,1),13),_xlpm.day,IF(_xlpm.month=13,_xlpm.dayOfYear-360,_xlpm.dayOfYear-(_xlpm.month-1)*30),TEXT(_xlpm.ethYear,"0000")&"-"&TEXT(_xlpm.month,"00")&"-"&TEXT(_xlpm.day,"00"))) -> 2018-09-27 | X15: =IF($W15="","",TEXT($W15,"mm")) -> 09 | Y15: =IFERROR(CHOOSE(X15,"መስከረም","ጥቅምት","ህዳር ","ታህሳስ ","ጥር ","የካቲት ","መጋቢት18","ሚይዚያ ","ግንቦት18","ሰኔ18","ሐምሌ ","ነሐሴ ","Pagume"),"") -> ግንቦት18 | Z15: =IF($K15="","",_xlfn.LET(_xlpm.gDate,K15,_xlpm.ethYear,IF(_xlpm.gDate>=DATE(YEAR(_xlpm.gDate),9,11),YEAR(_xlpm.gDate)-7,YEAR(_xlpm.gDate)-8),_xlpm.prevEthYear,_xlpm.ethYear-1,_xlpm.startDate,IF(_xlpm.gDate>=DATE(YEAR(_xlpm.gDate),9,11),DATE(YEAR(_xlpm.gDate),9,11)+IF(MOD(_xlpm.prevEthYear,4)=3,1,0),DATE(YEAR(_xlpm.gDate)-1,9,11)+IF(MOD(_xlpm.prevEthYear,4)=3,1,0)),_xlpm.dayOfYear,_xlpm.gDate-_xlpm.startDate+1,_xlpm.month,IF(_xlpm.dayOfYear<=360,CEILING(_xlpm.dayOfYear/30,1),13),_xlpm.day,IF(_xlpm.month=13,_xlpm.dayOfYear-360,_xlpm.dayOfYear-(_xlpm.month-1)*30),TEXT(_xlpm.ethYear,"0000")&"-"&TEXT(_xlpm.month,"00")&"-"&TEXT(_xlpm.day,"00"))) | AA15: =IF($Z15="","",TEXT($Z15,"mm")) | AB15: =IFERROR(CHOOSE(AA15,"መስከረም","ጥቅምት","ህዳር ","ታህሳስ ","ጥር ","የካቲት ","መጋቢት ","ሚይዚያ ","ግንቦት ","ሰኔ ","ሐምሌ ","ነሐሴ ","Pagume"),"") | AD15: =IF($D15="","",YEAR(D15)&"-W"&WEEKNUM(D15,2)) -> 2026-W23 | AE15: =IF($K15="","",YEAR(K15)&"-W"&WEEKNUM(K15,2))
A16: 15 | B16: Kidus/M | C16: 6000 | D16: 46178 | E16: =IF(D16="","",IF(F16="paid",0,I16-J16)) -> -10 | F16: Credit | G16: =IF(F16="Paid","Settled",IF(E16="","",IF(E16<0,"Over Due",IF(E16<=10,"Due soon",IF(E16<=20,"FP need",IF(E16<=30,"Pending","Pending")))))) -> Over Due | H16: =IFERROR(CHOOSE($X16,"መስከረም","ጥቅምት","ህዳር ","ታህሳስ ","ጥር ","የካቲት ","መጋቢት ","ሚይዚያ ","ግንቦት ","ሰኔ ","ሐምሌ ","ነሐሴ ","Pagume"),"") -> ግንቦት | I16: 30 | J16: =IF(D16="","-",$Q$1-D16) -> 40 | L16: =IF(E16="","",$Q$1+E16) -> 46208 | M16: ሰኔ18 | O16: {=SUMPRODUCT(($F16:$F16="Parcial")*ABS($C16:$C16-$N16:$N16))} -> 0 | W16: =IF($D16="","",_xlfn.LET(_xlpm.gDate,D16,_xlpm.ethYear,IF(_xlpm.gDate>=DATE(YEAR(_xlpm.gDate),9,11),YEAR(_xlpm.gDate)-7,YEAR(_xlpm.gDate)-8),_xlpm.prevEthYear,_xlpm.ethYear-1,_xlpm.startDate,IF(_xlpm.gDate>=DATE(YEAR(_xlpm.gDate),9,11),DATE(YEAR(_xlpm.gDate),9,11)+IF(MOD(_xlpm.prevEthYear,4)=3,1,0),DATE(YEAR(_xlpm.gDate)-1,9,11)+IF(MOD(_xlpm.prevEthYear,4)=3,1,0)),_xlpm.dayOfYear,_xlpm.gDate-_xlpm.startDate+1,_xlpm.month,IF(_xlpm.dayOfYear<=360,CEILING(_xlpm.dayOfYear/30,1),13),_xlpm.day,IF(_xlpm.month=13,_xlpm.dayOfYear-360,_xlpm.dayOfYear-(_xlpm.month-1)*30),TEXT(_xlpm.ethYear,"0000")&"-"&TEXT(_xlpm.month,"00")&"-"&TEXT(_xlpm.day,"00"))) -> 2018-09-28 | X16: =IF($W16="","",TEXT($W16,"mm")) -> 09 | Y16: =IFERROR(CHOOSE(X16,"መስከረም","ጥቅምት","ህዳር ","ታህሳስ ","ጥር ","የካቲት ","መጋቢት18","ሚይዚያ ","ግንቦት18","ሰኔ18","ሐምሌ ","ነሐሴ ","Pagume"),"") -> ግንቦት18 | Z16: =IF($K16="","",_xlfn.LET(_xlpm.gDate,K16,_xlpm.ethYear,IF(_xlpm.gDate>=DATE(YEAR(_xlpm.gDate),9,11),YEAR(_xlpm.gDate)-7,YEAR(_xlpm.gDate)-8),_xlpm.prevEthYear,_xlpm.ethYear-1,_xlpm.startDate,IF(_xlpm.gDate>=DATE(YEAR(_xlpm.gDate),9,11),DATE(YEAR(_xlpm.gDate),9,11)+IF(MOD(_xlpm.prevEthYear,4)=3,1,0),DATE(YEAR(_xlpm.gDate)-1,9,11)+IF(MOD(_xlpm.prevEthYear,4)=3,1,0)),_xlpm.dayOfYear,_xlpm.gDate-_xlpm.startDate+1,_xlpm.month,IF(_xlpm.dayOfYear<=360,CEILING(_xlpm.dayOfYear/30,1),13),_xlpm.day,IF(_xlpm.month=13,_xlpm.dayOfYear-360,_xlpm.dayOfYear-(_xlpm.month-1)*30),TEXT(_xlpm.ethYear,"0000")&"-"&TEXT(_xlpm.month,"00")&"-"&TEXT(_xlpm.day,"00"))) | AA16: =IF($Z16="","",TEXT($Z16,"mm")) | AB16: =IFERROR(CHOOSE(AA16,"መስከረም","ጥቅምት","ህዳር ","ታህሳስ ","ጥር ","የካቲት ","መጋቢት ","ሚይዚያ ","ግንቦት ","ሰኔ ","ሐምሌ ","ነሐሴ ","Pagume"),"") | AD16: =IF($D16="","",YEAR(D16)&"-W"&WEEKNUM(D16,2)) -> 2026-W23 | AE16: =IF($K16="","",YEAR(K16)&"-W"&WEEKNUM(K16,2))
A17: 16 | B17: Wajin | C17: 110000 | D17: 46182 | E17: =IF(D17="","",IF(F17="paid",0,I17-J17)) -> 24 | F17: Credit | G17: =IF(F17="Paid","Settled",IF(E17="","",IF(E17<0,"Over Due",IF(E17<=10,"Due soon",IF(E17<=20,"FP need",IF(E17<=30,"Pending","Pending")))))) -> Pending | H17: =IFERROR(CHOOSE($X17,"መስከረም","ጥቅምት","ህዳር ","ታህሳስ ","ጥር ","የካቲት ","መጋቢት ","ሚይዚያ ","ግንቦት ","ሰኔ ","ሐምሌ ","ነሐሴ ","Pagume"),"") -> ሰኔ | I17: 60 | J17: =IF(D17="","-",$Q$1-D17) -> 36 | L17: =IF(E17="","",$Q$1+E17) -> 46242 | M17: ሰኔ18 | O17: {=SUMPRODUCT(($F17:$F17="Parcial")*ABS($C17:$C17-$N17:$N17))} -> 0 | W17: =IF($D17="","",_xlfn.LET(_xlpm.gDate,D17,_xlpm.ethYear,IF(_xlpm.gDate>=DATE(YEAR(_xlpm.gDate),9,11),YEAR(_xlpm.gDate)-7,YEAR(_xlpm.gDate)-8),_xlpm.prevEthYear,_xlpm.ethYear-1,_xlpm.startDate,IF(_xlpm.gDate>=DATE(YEAR(_xlpm.gDate),9,11),DATE(YEAR(_xlpm.gDate),9,11)+IF(MOD(_xlpm.prevEthYear,4)=3,1,0),DATE(YEAR(_xlpm.gDate)-1,9,11)+IF(MOD(_xlpm.prevEthYear,4)=3,1,0)),_xlpm.dayOfYear,_xlpm.gDate-_xlpm.startDate+1,_xlpm.month,IF(_xlpm.dayOfYear<=360,CEILING(_xlpm.dayOfYear/30,1),13),_xlpm.day,IF(_xlpm.month=13,_xlpm.dayOfYear-360,_xlpm.dayOfYear-(_xlpm.month-1)*30),TEXT(_xlpm.ethYear,"0000")&"-"&TEXT(_xlpm.month,"00")&"-"&TEXT(_xlpm.day,"00"))) -> 2018-10-02 | X17: =IF($W17="","",TEXT($W17,"mm")) -> 10 | Y17: =IFERROR(CHOOSE(X17,"መስከረም","ጥቅምት","ህዳር ","ታህሳስ ","ጥር ","የካቲት ","መጋቢት18","ሚይዚያ ","ግንቦት18","ሰኔ18","ሐምሌ ","ነሐሴ ","Pagume"),"") -> ሰኔ18 | Z17: =IF($K17="","",_xlfn.LET(_xlpm.gDate,K17,_xlpm.ethYear,IF(_xlpm.gDate>=DATE(YEAR(_xlpm.gDate),9,11),YEAR(_xlpm.gDate)-7,YEAR(_xlpm.gDate)-8),_xlpm.prevEthYear,_xlpm.ethYear-1,_xlpm.startDate,IF(_xlpm.gDate>=DATE(YEAR(_xlpm.gDate),9,11),DATE(YEAR(_xlpm.gDate),9,11)+IF(MOD(_xlpm.prevEthYear,4)=3,1,0),DATE(YEAR(_xlpm.gDate)-1,9,11)+IF(MOD(_xlpm.prevEthYear,4)=3,1,0)),_xlpm.dayOfYear,_xlpm.gDate-_xlpm.startDate+1,_xlpm.month,IF(_xlpm.dayOfYear<=360,CEILING(_xlpm.dayOfYear/30,1),13),_xlpm.day,IF(_xlpm.month=13,_xlpm.dayOfYear-360,_xlpm.dayOfYear-(_xlpm.month-1)*30),TEXT(_xlpm.ethYear,"0000")&"-"&TEXT(_xlpm.month,"00")&"-"&TEXT(_xlpm.day,"00"))) | AA17: =IF($Z17="","",TEXT($Z17,"mm")) | AB17: =IFERROR(CHOOSE(AA17,"መስከረም","ጥቅምት","ህዳር ","ታህሳስ ","ጥር ","የካቲት ","መጋቢት ","ሚይዚያ ","ግንቦት ","ሰኔ ","ሐምሌ ","ነሐሴ ","Pagume"),"") | AD17: =IF($D17="","",YEAR(D17)&"-W"&WEEKNUM(D17,2)) -> 2026-W24 | AE17: =IF($K17="","",YEAR(K17)&"-W"&WEEKNUM(K17,2))
A18: 17 | B18: Yeorit pharm | C18: 12500 | D18: 46183 | E18: =IF(D18="","",IF(F18="paid",0,I18-J18)) -> -5 | F18: Credit | G18: =IF(F18="Paid","Settled",IF(E18="","",IF(E18<0,"Over Due",IF(E18<=10,"Due soon",IF(E18<=20,"FP need",IF(E18<=30,"Pending","Pending")))))) -> Over Due | H18: =IFERROR(CHOOSE($X18,"መስከረም","ጥቅምት","ህዳር ","ታህሳስ ","ጥር ","የካቲት ","መጋቢት ","ሚይዚያ ","ግንቦት ","ሰኔ ","ሐምሌ ","ነሐሴ ","Pagume"),"") -> ሰኔ | I18: 30 | J18: =IF(D18="","-",$Q$1-D18) -> 35 | L18: =IF(E18="","",$Q$1+E18) -> 46213 | M18: ሰኔ18 | O18: {=SUMPRODUCT(($F18:$F18="Parcial")*ABS($C18:$C18-$N18:$N18))} -> 0 | W18: =IF($D18="","",_xlfn.LET(_xlpm.gDate,D18,_xlpm.ethYear,IF(_xlpm.gDate>=DATE(YEAR(_xlpm.gDate),9,11),YEAR(_xlpm.gDate)-7,YEAR(_xlpm.gDate)-8),_xlpm.prevEthYear,_xlpm.ethYear-1,_xlpm.startDate,IF(_xlpm.gDate>=DATE(YEAR(_xlpm.gDate),9,11),DATE(YEAR(_xlpm.gDate),9,11)+IF(MOD(_xlpm.prevEthYear,4)=3,1,0),DATE(YEAR(_xlpm.gDate)-1,9,11)+IF(MOD(_xlpm.prevEthYear,4)=3,1,0)),_xlpm.dayOfYear,_xlpm.gDate-_xlpm.startDate+1,_xlpm.month,IF(_xlpm.dayOfYear<=360,CEILING(_xlpm.dayOfYear/30,1),13),_xlpm.day,IF(_xlpm.month=13,_xlpm.dayOfYear-360,_xlpm.dayOfYear-(_xlpm.month-1)*30),TEXT(_xlpm.ethYear,"0000")&"-"&TEXT(_xlpm.month,"00")&"-"&TEXT(_xlpm.day,"00"))) -> 2018-10-03 | X18: =IF($W18="","",TEXT($W18,"mm")) -> 10 | Y18: =IFERROR(CHOOSE(X18,"መስከረም","ጥቅምት","ህዳር ","ታህሳስ ","ጥር ","የካቲት ","መጋቢት18","ሚይዚያ ","ግንቦት18","ሰኔ18","ሐምሌ ","ነሐሴ ","Pagume"),"") -> ሰኔ18 | Z18: =IF($K18="","",_xlfn.LET(_xlpm.gDate,K18,_xlpm.ethYear,IF(_xlpm.gDate>=DATE(YEAR(_xlpm.gDate),9,11),YEAR(_xlpm.gDate)-7,YEAR(_xlpm.gDate)-8),_xlpm.prevEthYear,_xlpm.ethYear-1,_xlpm.startDate,IF(_xlpm.gDate>=DATE(YEAR(_xlpm.gDate),9,11),DATE(YEAR(_xlpm.gDate),9,11)+IF(MOD(_xlpm.prevEthYear,4)=3,1,0),DATE(YEAR(_xlpm.gDate)-1,9,11)+IF(MOD(_xlpm.prevEthYear,4)=3,1,0)),_xlpm.dayOfYear,_xlpm.gDate-_xlpm.startDate+1,_xlpm.month,IF(_xlpm.dayOfYear<=360,CEILING(_xlpm.dayOfYear/30,1),13),_xlpm.day,IF(_xlpm.month=13,_xlpm.dayOfYear-360,_xlpm.dayOfYear-(_xlpm.month-1)*30),TEXT(_xlpm.ethYear,"0000")&"-"&TEXT(_xlpm.month,"00")&"-"&TEXT(_xlpm.day,"00"))) | AA18: =IF($Z18="","",TEXT($Z18,"mm")) | AB18: =IFERROR(CHOOSE(AA18,"መስከረም","ጥቅምት","ህዳር ","ታህሳስ ","ጥር ","የካቲት ","መጋቢት ","ሚይዚያ ","ግንቦት ","ሰኔ ","ሐምሌ ","ነሐሴ ","Pagume"),"") | AD18: =IF($D18="","",YEAR(D18)&"-W"&WEEKNUM(D18,2)) -> 2026-W24 | AE18: =IF($K18="","",YEAR(K18)&"-W"&WEEKNUM(K18,2))
A19: 18 | B19: Droga | C19: 210000 | D19: 46184 | E19: =IF(D19="","",IF(F19="paid",0,I19-J19)) -> 0 | F19: Paid | G19: =IF(F19="Paid","Settled",IF(E19="","",IF(E19<0,"Over Due",IF(E19<=10,"Due soon",IF(E19<=20,"FP need",IF(E19<=30,"Pending","Pending")))))) -> Settled | H19: =IFERROR(CHOOSE($X19,"መስከረም","ጥቅምት","ህዳር ","ታህሳስ ","ጥር ","የካቲት ","መጋቢት ","ሚይዚያ ","ግንቦት ","ሰኔ ","ሐምሌ ","ነሐሴ ","Pagume"),"") -> ሰኔ | I19: 30 | J19: =IF(D19="","-",$Q$1-D19) -> 34 | K19: 46214 | L19: =IF(E19="","",$Q$1+E19) -> 46218 | M19: ሰኔ18 | O19: {=SUMPRODUCT(($F19:$F19="Parcial")*ABS($C19:$C19-$N19:$N19))} -> 0 | W19: =IF($D19="","",_xlfn.LET(_xlpm.gDate,D19,_xlpm.ethYear,IF(_xlpm.gDate>=DATE(YEAR(_xlpm.gDate),9,11),YEAR(_xlpm.gDate)-7,YEAR(_xlpm.gDate)-8),_xlpm.prevEthYear,_xlpm.ethYear-1,_xlpm.startDate,IF(_xlpm.gDate>=DATE(YEAR(_xlpm.gDate),9,11),DATE(YEAR(_xlpm.gDate),9,11)+IF(MOD(_xlpm.prevEthYear,4)=3,1,0),DATE(YEAR(_xlpm.gDate)-1,9,11)+IF(MOD(_xlpm.prevEthYear,4)=3,1,0)),_xlpm.dayOfYear,_xlpm.gDate-_xlpm.startDate+1,_xlpm.month,IF(_xlpm.dayOfYear<=360,CEILING(_xlpm.dayOfYear/30,1),13),_xlpm.day,IF(_xlpm.month=13,_xlpm.dayOfYear-360,_xlpm.dayOfYear-(_xlpm.month-1)*30),TEXT(_xlpm.ethYear,"0000")&"-"&TEXT(_xlpm.month,"00")&"-"&TEXT(_xlpm.day,"00"))) -> 2018-10-04 | X19: =IF($W19="","",TEXT($W19,"mm")) -> 10 | Y19: =IFERROR(CHOOSE(X19,"መስከረም","ጥቅምት","ህዳር ","ታህሳስ ","ጥር ","የካቲት ","መጋቢት18","ሚይዚያ ","ግንቦት18","ሰኔ18","ሐምሌ ","ነሐሴ ","Pagume"),"") -> ሰኔ18 | Z19: =IF($K19="","",_xlfn.LET(_xlpm.gDate,K19,_xlpm.ethYear,IF(_xlpm.gDate>=DATE(YEAR(_xlpm.gDate),9,11),YEAR(_xlpm.gDate)-7,YEAR(_xlpm.gDate)-8),_xlpm.prevEthYear,_xlpm.ethYear-1,_xlpm.startDate,IF(_xlpm.gDate>=DATE(YEAR(_xlpm.gDate),9,11),DATE(YEAR(_xlpm.gDate),9,11)+IF(MOD(_xlpm.prevEthYear,4)=3,1,0),DATE(YEAR(_xlpm.gDate)-1,9,11)+IF(MOD(_xlpm.prevEthYear,4)=3,1,0)),_xlpm.dayOfYear,_xlpm.gDate-_xlpm.startDate+1,_xlpm.month,IF(_xlpm.dayOfYear<=360,CEILING(_xlpm.dayOfYear/30,1),13),_xlpm.day,IF(_xlpm.month=13,_xlpm.dayOfYear-360,_xlpm.dayOfYear-(_xlpm.month-1)*30),TEXT(_xlpm.ethYear,"0000")&"-"&TEXT(_xlpm.month,"00")&"-"&TEXT(_xlpm.day,"00"))) -> 2018-11-04 | AA19: =IF($Z19="","",TEXT($Z19,"mm")) -> 11 | AB19: =IFERROR(CHOOSE(AA19,"መስከረም","ጥቅምት","ህዳር ","ታህሳስ ","ጥር ","የካቲት ","መጋቢት ","ሚይዚያ ","ግንቦት ","ሰኔ ","ሐምሌ ","ነሐሴ ","Pagume"),"") -> ሐምሌ | AD19: =IF($D19="","",YEAR(D19)&"-W"&WEEKNUM(D19,2)) -> 2026-W24 | AE19: =IF($K19="","",YEAR(K19)&"-W"&WEEKNUM(K19,2)) -> 2026-W28
A20: 19 | B20: Droga | C20: 48300 | D20: 46185 | E20: =IF(D20="","",IF(F20="paid",0,I20-J20)) -> 0 | F20: Paid | G20: =IF(F20="Paid","Settled",IF(E20="","",IF(E20<0,"Over Due",IF(E20<=10,"Due soon",IF(E20<=20,"FP need",IF(E20<=30,"Pending","Pending")))))) -> Settled | H20: =IFERROR(CHOOSE($X20,"መስከረም","ጥቅምት","ህዳር ","ታህሳስ ","ጥር ","የካቲት ","መጋቢት ","ሚይዚያ ","ግንቦት ","ሰኔ ","ሐምሌ ","ነሐሴ ","Pagume"),"") -> ሰኔ | I20: 30 | J20: =IF(D20="","-",$Q$1-D20) -> 33 | K20: 46216 | L20: =IF(E20="","",$Q$1+E20) -> 46218 | M20: ሰኔ18 | O20: {=SUMPRODUCT(($F20:$F20="Parcial")*ABS($C20:$C20-$N20:$N20))} -> 0 | Q20: Check | W20: =IF($D20="","",_xlfn.LET(_xlpm.gDate,D20,_xlpm.ethYear,IF(_xlpm.gDate>=DATE(YEAR(_xlpm.gDate),9,11),YEAR(_xlpm.gDate)-7,YEAR(_xlpm.gDate)-8),_xlpm.prevEthYear,_xlpm.ethYear-1,_xlpm.startDate,IF(_xlpm.gDate>=DATE(YEAR(_xlpm.gDate),9,11),DATE(YEAR(_xlpm.gDate),9,11)+IF(MOD(_xlpm.prevEthYear,4)=3,1,0),DATE(YEAR(_xlpm.gDate)-1,9,11)+IF(MOD(_xlpm.prevEthYear,4)=3,1,0)),_xlpm.dayOfYear,_xlpm.gDate-_xlpm.startDate+1,_xlpm.month,IF(_xlpm.dayOfYear<=360,CEILING(_xlpm.dayOfYear/30,1),13),_xlpm.day,IF(_xlpm.month=13,_xlpm.dayOfYear-360,_xlpm.dayOfYear-(_xlpm.month-1)*30),TEXT(_xlpm.ethYear,"0000")&"-"&TEXT(_xlpm.month,"00")&"-"&TEXT(_xlpm.day,"00"))) -> 2018-10-05 | X20: =IF($W20="","",TEXT($W20,"mm")) -> 10 | Y20: =IFERROR(CHOOSE(X20,"መስከረም","ጥቅምት","ህዳር ","ታህሳስ ","ጥር ","የካቲት ","መጋቢት18","ሚይዚያ ","ግንቦት18","ሰኔ18","ሐምሌ ","ነሐሴ ","Pagume"),"") -> ሰኔ18 | Z20: =IF($K20="","",_xlfn.LET(_xlpm.gDate,K20,_xlpm.ethYear,IF(_xlpm.gDate>=DATE(YEAR(_xlpm.gDate),9,11),YEAR(_xlpm.gDate)-7,YEAR(_xlpm.gDate)-8),_xlpm.prevEthYear,_xlpm.ethYear-1,_xlpm.startDate,IF(_xlpm.gDate>=DATE(YEAR(_xlpm.gDate),9,11),DATE(YEAR(_xlpm.gDate),9,11)+IF(MOD(_xlpm.prevEthYear,4)=3,1,0),DATE(YEAR(_xlpm.gDate)-1,9,11)+IF(MOD(_xlpm.prevEthYear,4)=3,1,0)),_xlpm.dayOfYear,_xlpm.gDate-_xlpm.startDate+1,_xlpm.month,IF(_xlpm.dayOfYear<=360,CEILING(_xlpm.dayOfYear/30,1),13),_xlpm.day,IF(_xlpm.month=13,_xlpm.dayOfYear-360,_xlpm.dayOfYear-(_xlpm.month-1)*30),TEXT(_xlpm.ethYear,"0000")&"-"&TEXT(_xlpm.month,"00")&"-"&TEXT(_xlpm.day,"00"))) -> 2018-11-06 | AA20: =IF($Z20="","",TEXT($Z20,"mm")) -> 11 | AB20: =IFERROR(CHOOSE(AA20,"መስከረም","ጥቅምት","ህዳር ","ታህሳስ ","ጥር ","የካቲት ","መጋቢት ","ሚይዚያ ","ግንቦት ","ሰኔ ","ሐምሌ ","ነሐሴ ","Pagume"),"") -> ሐምሌ | AD20: =IF($D20="","",YEAR(D20)&"-W"&WEEKNUM(D20,2)) -> 2026-W24 | AE20: =IF($K20="","",YEAR(K20)&"-W"&WEEKNUM(K20,2)) -> 2026-W29
A21: 20 | B21: Eman | C21: 133250 | D21: 46188 | E21: =IF(D21="","",IF(F21="paid",0,I21-J21)) -> 30 | F21: Credit | G21: =IF(F21="Paid","Settled",IF(E21="","",IF(E21<0,"Over Due",IF(E21<=10,"Due soon",IF(E21<=20,"FP need",IF(E21<=30,"Pending","Pending")))))) -> Pending | H21: =IFERROR(CHOOSE($X21,"መስከረም","ጥቅምት","ህዳር ","ታህሳስ ","ጥር ","የካቲት ","መጋቢት ","ሚይዚያ ","ግንቦት ","ሰኔ ","ሐምሌ ","ነሐሴ ","Pagume"),"") -> ሰኔ | I21: 60 | J21: =IF(D21="","-",$Q$1-D21) -> 30 | L21: =IF(E21="","",$Q$1+E21) -> 46248 | M21: ሰኔ18 | O21: {=SUMPRODUCT(($F21:$F21="Parcial")*ABS($C21:$C21-$N21:$N21))} -> 0 | W21: =IF($D21="","",_xlfn.LET(_xlpm.gDate,D21,_xlpm.ethYear,IF(_xlpm.gDate>=DATE(YEAR(_xlpm.gDate),9,11),YEAR(_xlpm.gDate)-7,YEAR(_xlpm.gDate)-8),_xlpm.prevEthYear,_xlpm.ethYear-1,_xlpm.startDate,IF(_xlpm.gDate>=DATE(YEAR(_xlpm.gDate),9,11),DATE(YEAR(_xlpm.gDate),9,11)+IF(MOD(_xlpm.prevEthYear,4)=3,1,0),DATE(YEAR(_xlpm.gDate)-1,9,11)+IF(MOD(_xlpm.prevEthYear,4)=3,1,0)),_xlpm.dayOfYear,_xlpm.gDate-_xlpm.startDate+1,_xlpm.month,IF(_xlpm.dayOfYear<=360,CEILING(_xlpm.dayOfYear/30,1),13),_xlpm.day,IF(_xlpm.month=13,_xlpm.dayOfYear-360,_xlpm.dayOfYear-(_xlpm.month-1)*30),TEXT(_xlpm.ethYear,"0000")&"-"&TEXT(_xlpm.month,"00")&"-"&TEXT(_xlpm.day,"00"))) -> 2018-10-08 | X21: =IF($W21="","",TEXT($W21,"mm")) -> 10 | Y21: =IFERROR(CHOOSE(X21,"መስከረም","ጥቅምት","ህዳር ","ታህሳስ ","ጥር ","የካቲት ","መጋቢት18","ሚይዚያ ","ግንቦት18","ሰኔ18","ሐምሌ ","ነሐሴ ","Pagume"),"") -> ሰኔ18 | Z21: =IF($K21="","",_xlfn.LET(_xlpm.gDate,K21,_xlpm.ethYear,IF(_xlpm.gDate>=DATE(YEAR(_xlpm.gDate),9,11),YEAR(_xlpm.gDate)-7,YEAR(_xlpm.gDate)-8),_xlpm.prevEthYear,_xlpm.ethYear-1,_xlpm.startDate,IF(_xlpm.gDate>=DATE(YEAR(_xlpm.gDate),9,11),DATE(YEAR(_xlpm.gDate),9,11)+IF(MOD(_xlpm.prevEthYear,4)=3,1,0),DATE(YEAR(_xlpm.gDate)-1,9,11)+IF(MOD(_xlpm.prevEthYear,4)=3,1,0)),_xlpm.dayOfYear,_xlpm.gDate-_xlpm.startDate+1,_xlpm.month,IF(_xlpm.dayOfYear<=360,CEILING(_xlpm.dayOfYear/30,1),13),_xlpm.day,IF(_xlpm.month=13,_xlpm.dayOfYear-360,_xlpm.dayOfYear-(_xlpm.month-1)*30),TEXT(_xlpm.ethYear,"0000")&"-"&TEXT(_xlpm.month,"00")&"-"&TEXT(_xlpm.day,"00"))) | AA21: =IF($Z21="","",TEXT($Z21,"mm")) | AB21: =IFERROR(CHOOSE(AA21,"መስከረም","ጥቅምት","ህዳር ","ታህሳስ ","ጥር ","የካቲት ","መጋቢት ","ሚይዚያ ","ግንቦት ","ሰኔ ","ሐምሌ ","ነሐሴ ","Pagume"),"") | AD21: =IF($D21="","",YEAR(D21)&"-W"&WEEKNUM(D21,2)) -> 2026-W25 | AE21: =IF($K21="","",YEAR(K21)&"-W"&WEEKNUM(K21,2))
A22: 21 | B22: Dr haile phar | C22: 35000 | D22: 46189 | E22: =IF(D22="","",IF(F22="paid",0,I22-J22)) -> 1 | F22: Credit | G22: =IF(F22="Paid","Settled",IF(E22="","",IF(E22<0,"Over Due",IF(E22<=10,"Due soon",IF(E22<=20,"FP need",IF(E22<=30,"Pending","Pending")))))) -> Due soon | H22: =IFERROR(CHOOSE($X22,"መስከረም","ጥቅምት","ህዳር ","ታህሳስ ","ጥር ","የካቲት ","መጋቢት ","ሚይዚያ ","ግንቦት ","ሰኔ ","ሐምሌ ","ነሐሴ ","Pagume"),"") -> ሰኔ | I22: 30 | J22: =IF(D22="","-",$Q$1-D22) -> 29 | L22: =IF(E22="","",$Q$1+E22) -> 46219 | M22: ሰኔ18 | O22: {=SUMPRODUCT(($F22:$F22="Parcial")*ABS($C22:$C22-$N22:$N22))} -> 0 | W22: =IF($D22="","",_xlfn.LET(_xlpm.gDate,D22,_xlpm.ethYear,IF(_xlpm.gDate>=DATE(YEAR(_xlpm.gDate),9,11),YEAR(_xlpm.gDate)-7,YEAR(_xlpm.gDate)-8),_xlpm.prevEthYear,_xlpm.ethYear-1,_xlpm.startDate,IF(_xlpm.gDate>=DATE(YEAR(_xlpm.gDate),9,11),DATE(YEAR(_xlpm.gDate),9,11)+IF(MOD(_xlpm.prevEthYear,4)=3,1,0),DATE(YEAR(_xlpm.gDate)-1,9,11)+IF(MOD(_xlpm.prevEthYear,4)=3,1,0)),_xlpm.dayOfYear,_xlpm.gDate-_xlpm.startDate+1,_xlpm.month,IF(_xlpm.dayOfYear<=360,CEILING(_xlpm.dayOfYear/30,1),13),_xlpm.day,IF(_xlpm.month=13,_xlpm.dayOfYear-360,_xlpm.dayOfYear-(_xlpm.month-1)*30),TEXT(_xlpm.ethYear,"0000")&"-"&TEXT(_xlpm.month,"00")&"-"&TEXT(_xlpm.day,"00"))) -> 2018-10-09 | X22: =IF($W22="","",TEXT($W22,"mm")) -> 10 | Y22: =IFERROR(CHOOSE(X22,"መስከረም","ጥቅምት","ህዳር ","ታህሳስ ","ጥር ","የካቲት ","መጋቢት18","ሚይዚያ ","ግንቦት18","ሰኔ18","ሐምሌ ","ነሐሴ ","Pagume"),"") -> ሰኔ18 | Z22: =IF($K22="","",_xlfn.LET(_xlpm.gDate,K22,_xlpm.ethYear,IF(_xlpm.gDate>=DATE(YEAR(_xlpm.gDate),9,11),YEAR(_xlpm.gDate)-7,YEAR(_xlpm.gDate)-8),_xlpm.prevEthYear,_xlpm.ethYear-1,_xlpm.startDate,IF(_xlpm.gDate>=DATE(YEAR(_xlpm.gDate),9,11),DATE(YEAR(_xlpm.gDate),9,11)+IF(MOD(_xlpm.prevEthYear,4)=3,1,0),DATE(YEAR(_xlpm.gDate)-1,9,11)+IF(MOD(_xlpm.prevEthYear,4)=3,1,0)),_xlpm.dayOfYear,_xlpm.gDate-_xlpm.startDate+1,_xlpm.month,IF(_xlpm.dayOfYear<=360,CEILING(_xlpm.dayOfYear/30,1),13),_xlpm.day,IF(_xlpm.month=13,_xlpm.dayOfYear-360,_xlpm.dayOfYear-(_xlpm.month-1)*30),TEXT(_xlpm.ethYear,"0000")&"-"&TEXT(_xlpm.month,"00")&"-"&TEXT(_xlpm.day,"00"))) | AA22: =IF($Z22="","",TEXT($Z22,"mm")) | AB22: =IFERROR(CHOOSE(AA22,"መስከረም","ጥቅምት","ህዳር ","ታህሳስ ","ጥር ","የካቲት ","መጋቢት ","ሚይዚያ ","ግንቦት ","ሰኔ ","ሐምሌ ","ነሐሴ ","Pagume"),"") | AD22: =IF($D22="","",YEAR(D22)&"-W"&WEEKNUM(D22,2)) -> 2026-W25 | AE22: =IF($K22="","",YEAR(K22)&"-W"&WEEKNUM(K22,2))
A23: 22 | B23: Kidus/M | C23: 29500 | D23: 46192 | E23: =IF(D23="","",IF(F23="paid",0,I23-J23)) -> 4 | F23: Credit | G23: =IF(F23="Paid","Settled",IF(E23="","",IF(E23<0,"Over Due",IF(E23<=10,"Due soon",IF(E23<=20,"FP need",IF(E23<=30,"Pending","Pending")))))) -> Due soon | H23: =IFERROR(CHOOSE($X23,"መስከረም","ጥቅምት","ህዳር ","ታህሳስ ","ጥር ","የካቲት ","መጋቢት ","ሚይዚያ ","ግንቦት ","ሰኔ ","ሐምሌ ","ነሐሴ ","Pagume"),"") -> ሰኔ | I23: 30 | J23: =IF(D23="","-",$Q$1-D23) -> 26 | L23: =IF(E23="","",$Q$1+E23) -> 46222 | M23: ሰኔ18 | O23: {=SUMPRODUCT(($F23:$F23="Parcial")*ABS($C23:$C23-$N23:$N23))} -> 0 | W23: =IF($D23="","",_xlfn.LET(_xlpm.gDate,D23,_xlpm.ethYear,IF(_xlpm.gDate>=DATE(YEAR(_xlpm.gDate),9,11),YEAR(_xlpm.gDate)-7,YEAR(_xlpm.gDate)-8),_xlpm.prevEthYear,_xlpm.ethYear-1,_xlpm.startDate,IF(_xlpm.gDate>=DATE(YEAR(_xlpm.gDate),9,11),DATE(YEAR(_xlpm.gDate),9,11)+IF(MOD(_xlpm.prevEthYear,4)=3,1,0),DATE(YEAR(_xlpm.gDate)-1,9,11)+IF(MOD(_xlpm.prevEthYear,4)=3,1,0)),_xlpm.dayOfYear,_xlpm.gDate-_xlpm.startDate+1,_xlpm.month,IF(_xlpm.dayOfYear<=360,CEILING(_xlpm.dayOfYear/30,1),13),_xlpm.day,IF(_xlpm.month=13,_xlpm.dayOfYear-360,_xlpm.dayOfYear-(_xlpm.month-1)*30),TEXT(_xlpm.ethYear,"0000")&"-"&TEXT(_xlpm.month,"00")&"-"&TEXT(_xlpm.day,"00"))) -> 2018-10-12 | X23: =IF($W23="","",TEXT($W23,"mm")) -> 10 | Y23: =IFERROR(CHOOSE(X23,"መስከረም","ጥቅምት","ህዳር ","ታህሳስ ","ጥር ","የካቲት ","መጋቢት18","ሚይዚያ ","ግንቦት18","ሰኔ18","ሐምሌ ","ነሐሴ ","Pagume"),"") -> ሰኔ18 | Z23: =IF($K23="","",_xlfn.LET(_xlpm.gDate,K23,_xlpm.ethYear,IF(_xlpm.gDate>=DATE(YEAR(_xlpm.gDate),9,11),YEAR(_xlpm.gDate)-7,YEAR(_xlpm.gDate)-8),_xlpm.prevEthYear,_xlpm.ethYear-1,_xlpm.startDate,IF(_xlpm.gDate>=DATE(YEAR(_xlpm.gDate),9,11),DATE(YEAR(_xlpm.gDate),9,11)+IF(MOD(_xlpm.prevEthYear,4)=3,1,0),DATE(YEAR(_xlpm.gDate)-1,9,11)+IF(MOD(_xlpm.prevEthYear,4)=3,1,0)),_xlpm.dayOfYear,_xlpm.gDate-_xlpm.startDate+1,_xlpm.month,IF(_xlpm.dayOfYear<=360,CEILING(_xlpm.dayOfYear/30,1),13),_xlpm.day,IF(_xlpm.month=13,_xlpm.dayOfYear-360,_xlpm.dayOfYear-(_xlpm.month-1)*30),TEXT(_xlpm.ethYear,"0000")&"-"&TEXT(_xlpm.month,"00")&"-"&TEXT(_xlpm.day,"00"))) | AA23: =IF($Z23="","",TEXT($Z23,"mm")) | AB23: =IFERROR(CHOOSE(AA23,"መስከረም","ጥቅምት","ህዳር ","ታህሳስ ","ጥር ","የካቲት ","መጋቢት ","ሚይዚያ ","ግንቦት ","ሰኔ ","ሐምሌ ","ነሐሴ ","Pagume"),"") | AD23: =IF($D23="","",YEAR(D23)&"-W"&WEEKNUM(D23,2)) -> 2026-W25 | AE23: =IF($K23="","",YEAR(K23)&"-W"&WEEKNUM(K23,2))
A24: 23 | B24: Pharmasafe | C24: 60000 | D24: 46195 | E24: =IF(D24="","",IF(F24="paid",0,I24-J24)) -> 7 | F24: Credit | G24: =IF(F24="Paid","Settled",IF(E24="","",IF(E24<0,"Over Due",IF(E24<=10,"Due soon",IF(E24<=20,"FP need",IF(E24<=30,"Pending","Pending")))))) -> Due soon | H24: =IFERROR(CHOOSE($X24,"መስከረም","ጥቅምት","ህዳር ","ታህሳስ ","ጥር ","የካቲት ","መጋቢት ","ሚይዚያ ","ግንቦት ","ሰኔ ","ሐምሌ ","ነሐሴ ","Pagume"),"") -> ሰኔ | I24: 30 | J24: =IF(D24="","-",$Q$1-D24) -> 23 | L24: =IF(E24="","",$Q$1+E24) -> 46225 | M24: ሰኔ18 | O24: {=SUMPRODUCT(($F24:$F24="Parcial")*ABS($C24:$C24-$N24:$N24))} -> 0 | W24: =IF($D24="","",_xlfn.LET(_xlpm.gDate,D24,_xlpm.ethYear,IF(_xlpm.gDate>=DATE(YEAR(_xlpm.gDate),9,11),YEAR(_xlpm.gDate)-7,YEAR(_xlpm.gDate)-8),_xlpm.prevEthYear,_xlpm.ethYear-1,_xlpm.startDate,IF(_xlpm.gDate>=DATE(YEAR(_xlpm.gDate),9,11),DATE(YEAR(_xlpm.gDate),9,11)+IF(MOD(_xlpm.prevEthYear,4)=3,1,0),DATE(YEAR(_xlpm.gDate)-1,9,11)+IF(MOD(_xlpm.prevEthYear,4)=3,1,0)),_xlpm.dayOfYear,_xlpm.gDate-_xlpm.startDate+1,_xlpm.month,IF(_xlpm.dayOfYear<=360,CEILING(_xlpm.dayOfYear/30,1),13),_xlpm.day,IF(_xlpm.month=13,_xlpm.dayOfYear-360,_xlpm.dayOfYear-(_xlpm.month-1)*30),TEXT(_xlpm.ethYear,"0000")&"-"&TEXT(_xlpm.month,"00")&"-"&TEXT(_xlpm.day,"00"))) -> 2018-10-15 | X24: =IF($W24="","",TEXT($W24,"mm")) -> 10 | Y24: =IFERROR(CHOOSE(X24,"መስከረም","ጥቅምት","ህዳር ","ታህሳስ ","ጥር ","የካቲት ","መጋቢት18","ሚይዚያ ","ግንቦት18","ሰኔ18","ሐምሌ ","ነሐሴ ","Pagume"),"") -> ሰኔ18 | Z24: =IF($K24="","",_xlfn.LET(_xlpm.gDate,K24,_xlpm.ethYear,IF(_xlpm.gDate>=DATE(YEAR(_xlpm.gDate),9,11),YEAR(_xlpm.gDate)-7,YEAR(_xlpm.gDate)-8),_xlpm.prevEthYear,_xlpm.ethYear-1,_xlpm.startDate,IF(_xlpm.gDate>=DATE(YEAR(_xlpm.gDate),9,11),DATE(YEAR(_xlpm.gDate),9,11)+IF(MOD(_xlpm.prevEthYear,4)=3,1,0),DATE(YEAR(_xlpm.gDate)-1,9,11)+IF(MOD(_xlpm.prevEthYear,4)=3,1,0)),_xlpm.dayOfYear,_xlpm.gDate-_xlpm.startDate+1,_xlpm.month,IF(_xlpm.dayOfYear<=360,CEILING(_xlpm.dayOfYear/30,1),13),_xlpm.day,IF(_xlpm.month=13,_xlpm.dayOfYear-360,_xlpm.dayOfYear-(_xlpm.month-1)*30),TEXT(_xlpm.ethYear,"0000")&"-"&TEXT(_xlpm.month,"00")&"-"&TEXT(_xlpm.day,"00"))) | AA24: =IF($Z24="","",TEXT($Z24,"mm")) | AB24: =IFERROR(CHOOSE(AA24,"መስከረም","ጥቅምት","ህዳር ","ታህሳስ ","ጥር ","የካቲት ","መጋቢት ","ሚይዚያ ","ግንቦት ","ሰኔ ","ሐምሌ ","ነሐሴ ","Pagume"),"") | AD24: =IF($D24="","",YEAR(D24)&"-W"&WEEKNUM(D24,2)) -> 2026-W26 | AE24: =IF($K24="","",YEAR(K24)&"-W"&WEEKNUM(K24,2))
A25: 24 | B25: Meba | C25: 69500 | D25: 46197 | E25: =IF(D25="","",IF(F25="paid",0,I25-J25)) -> 9 | F25: Credit | G25: =IF(F25="Paid","Settled",IF(E25="","",IF(E25<0,"Over Due",IF(E25<=10,"Due soon",IF(E25<=20,"FP need",IF(E25<=30,"Pending","Pending")))))) -> Due soon | H25: =IFERROR(CHOOSE($X25,"መስከረም","ጥቅምት","ህዳር ","ታህሳስ ","ጥር ","የካቲት ","መጋቢት ","ሚይዚያ ","ግንቦት ","ሰኔ ","ሐምሌ ","ነሐሴ ","Pagume"),"") -> ሰኔ | I25: 30 | J25: =IF(D25="","-",$Q$1-D25) -> 21 | L25: =IF(E25="","",$Q$1+E25) -> 46227 | M25: ሰኔ18 | O25: {=SUMPRODUCT(($F25:$F25="Parcial")*ABS($C25:$C25-$N25:$N25))} -> 0 | W25: =IF($D25="","",_xlfn.LET(_xlpm.gDate,D25,_xlpm.ethYear,IF(_xlpm.gDate>=DATE(YEAR(_xlpm.gDate),9,11),YEAR(_xlpm.gDate)-7,YEAR(_xlpm.gDate)-8),_xlpm.prevEthYear,_xlpm.ethYear-1,_xlpm.startDate,IF(_xlpm.gDate>=DATE(YEAR(_xlpm.gDate),9,11),DATE(YEAR(_xlpm.gDate),9,11)+IF(MOD(_xlpm.prevEthYear,4)=3,1,0),DATE(YEAR(_xlpm.gDate)-1,9,11)+IF(MOD(_xlpm.prevEthYear,4)=3,1,0)),_xlpm.dayOfYear,_xlpm.gDate-_xlpm.startDate+1,_xlpm.month,IF(_xlpm.dayOfYear<=360,CEILING(_xlpm.dayOfYear/30,1),13),_xlpm.day,IF(_xlpm.month=13,_xlpm.dayOfYear-360,_xlpm.dayOfYear-(_xlpm.month-1)*30),TEXT(_xlpm.ethYear,"0000")&"-"&TEXT(_xlpm.month,"00")&"-"&TEXT(_xlpm.day,"00"))) -> 2018-10-17 | X25: =IF($W25="","",TEXT($W25,"mm")) -> 10 | Y25: =IFERROR(CHOOSE(X25,"መስከረም","ጥቅምት","ህዳር ","ታህሳስ ","ጥር ","የካቲት ","መጋቢት18","ሚይዚያ ","ግንቦት18","ሰኔ18","ሐምሌ ","ነሐሴ ","Pagume"),"") -> ሰኔ18 | Z25: =IF($K25="","",_xlfn.LET(_xlpm.gDate,K25,_xlpm.ethYear,IF(_xlpm.gDate>=DATE(YEAR(_xlpm.gDate),9,11),YEAR(_xlpm.gDate)-7,YEAR(_xlpm.gDate)-8),_xlpm.prevEthYear,_xlpm.ethYear-1,_xlpm.startDate,IF(_xlpm.gDate>=DATE(YEAR(_xlpm.gDate),9,11),DATE(YEAR(_xlpm.gDate),9,11)+IF(MOD(_xlpm.prevEthYear,4)=3,1,0),DATE(YEAR(_xlpm.gDate)-1,9,11)+IF(MOD(_xlpm.prevEthYear,4)=3,1,0)),_xlpm.dayOfYear,_xlpm.gDate-_xlpm.startDate+1,_xlpm.month,IF(_xlpm.dayOfYear<=360,CEILING(_xlpm.dayOfYear/30,1),13),_xlpm.day,IF(_xlpm.month=13,_xlpm.dayOfYear-360,_xlpm.dayOfYear-(_xlpm.month-1)*30),TEXT(_xlpm.ethYear,"0000")&"-"&TEXT(_xlpm.month,"00")&"-"&TEXT(_xlpm.day,"00"))) | AA25: =IF($Z25="","",TEXT($Z25,"mm")) | AB25: =IFERROR(CHOOSE(AA25,"መስከረም","ጥቅምት","ህዳር ","ታህሳስ ","ጥር ","የካቲት ","መጋቢት ","ሚይዚያ ","ግንቦት ","ሰኔ ","ሐምሌ ","ነሐሴ ","Pagume"),"") | AD25: =IF($D25="","",YEAR(D25)&"-W"&WEEKNUM(D25,2)) -> 2026-W26 | AE25: =IF($K25="","",YEAR(K25)&"-W"&WEEKNUM(K25,2))
A26: 25 | B26: Zemene/ Y | C26: 45700 | D26: 46190 | E26: =IF(D26="","",IF(F26="paid",0,I26-J26)) -> 2 | F26: Credit | G26: =IF(F26="Paid","Settled",IF(E26="","",IF(E26<0,"Over Due",IF(E26<=10,"Due soon",IF(E26<=20,"FP need",IF(E26<=30,"Pending","Pending")))))) -> Due soon | H26: =IFERROR(CHOOSE($X26,"መስከረም","ጥቅምት","ህዳር ","ታህሳስ ","ጥር ","የካቲት ","መጋቢት ","ሚይዚያ ","ግንቦት ","ሰኔ ","ሐምሌ ","ነሐሴ ","Pagume"),"") -> ሰኔ | I26: 30 | J26: =IF(D26="","-",$Q$1-D26) -> 28 | L26: =IF(E26="","",$Q$1+E26) -> 46220 | M26: ሰኔ18 | O26: {=SUMPRODUCT(($F26:$F26="Parcial")*ABS($C26:$C26-$N26:$N26))} -> 0 | W26: =IF($D26="","",_xlfn.LET(_xlpm.gDate,D26,_xlpm.ethYear,IF(_xlpm.gDate>=DATE(YEAR(_xlpm.gDate),9,11),YEAR(_xlpm.gDate)-7,YEAR(_xlpm.gDate)-8),_xlpm.prevEthYear,_xlpm.ethYear-1,_xlpm.startDate,IF(_xlpm.gDate>=DATE(YEAR(_xlpm.gDate),9,11),DATE(YEAR(_xlpm.gDate),9,11)+IF(MOD(_xlpm.prevEthYear,4)=3,1,0),DATE(YEAR(_xlpm.gDate)-1,9,11)+IF(MOD(_xlpm.prevEthYear,4)=3,1,0)),_xlpm.dayOfYear,_xlpm.gDate-_xlpm.startDate+1,_xlpm.month,IF(_xlpm.dayOfYear<=360,CEILING(_xlpm.dayOfYear/30,1),13),_xlpm.day,IF(_xlpm.month=13,_xlpm.dayOfYear-360,_xlpm.dayOfYear-(_xlpm.month-1)*30),TEXT(_xlpm.ethYear,"0000")&"-"&TEXT(_xlpm.month,"00")&"-"&TEXT(_xlpm.day,"00"))) -> 2018-10-10 | X26: =IF($W26="","",TEXT($W26,"mm")) -> 10 | Y26: =IFERROR(CHOOSE(X26,"መስከረም","ጥቅምት","ህዳር ","ታህሳስ ","ጥር ","የካቲት ","መጋቢት18","ሚይዚያ ","ግንቦት18","ሰኔ18","ሐምሌ ","ነሐሴ ","Pagume"),"") -> ሰኔ18 | Z26: =IF($K26="","",_xlfn.LET(_xlpm.gDate,K26,_xlpm.ethYear,IF(_xlpm.gDate>=DATE(YEAR(_xlpm.gDate),9,11),YEAR(_xlpm.gDate)-7,YEAR(_xlpm.gDate)-8),_xlpm.prevEthYear,_xlpm.ethYear-1,_xlpm.startDate,IF(_xlpm.gDate>=DATE(YEAR(_xlpm.gDate),9,11),DATE(YEAR(_xlpm.gDate),9,11)+IF(MOD(_xlpm.prevEthYear,4)=3,1,0),DATE(YEAR(_xlpm.gDate)-1,9,11)+IF(MOD(_xlpm.prevEthYear,4)=3,1,0)),_xlpm.dayOfYear,_xlpm.gDate-_xlpm.startDate+1,_xlpm.month,IF(_xlpm.dayOfYear<=360,CEILING(_xlpm.dayOfYear/30,1),13),_xlpm.day,IF(_xlpm.month=13,_xlpm.dayOfYear-360,_xlpm.dayOfYear-(_xlpm.month-1)*30),TEXT(_xlpm.ethYear,"0000")&"-"&TEXT(_xlpm.month,"00")&"-"&TEXT(_xlpm.day,"00"))) | AA26: =IF($Z26="","",TEXT($Z26,"mm")) | AB26: =IFERROR(CHOOSE(AA26,"መስከረም","ጥቅምት","ህዳር ","ታህሳስ ","ጥር ","የካቲት ","መጋቢት ","ሚይዚያ ","ግንቦት ","ሰኔ ","ሐምሌ ","ነሐሴ ","Pagume"),"") | AD26: =IF($D26="","",YEAR(D26)&"-W"&WEEKNUM(D26,2)) -> 2026-W25 | AE26: =IF($K26="","",YEAR(K26)&"-W"&WEEKNUM(K26,2))
A27: 26 | B27: Abune/A | C27: 23200 | D27: 46197 | E27: =IF(D27="","",IF(F27="paid",0,I27-J27)) -> 9 | F27: Credit | G27: =IF(F27="Paid","Settled",IF(E27="","",IF(E27<0,"Over Due",IF(E27<=10,"Due soon",IF(E27<=20,"FP need",IF(E27<=30,"Pending","Pending")))))) -> Due soon | H27: =IFERROR(CHOOSE($X27,"መስከረም","ጥቅምት","ህዳር ","ታህሳስ ","ጥር ","የካቲት ","መጋቢት ","ሚይዚያ ","ግንቦት ","ሰኔ ","ሐምሌ ","ነሐሴ ","Pagume"),"") -> ሰኔ | I27: 30 | J27: =IF(D27="","-",$Q$1-D27) -> 21 | L27: =IF(E27="","",$Q$1+E27) -> 46227 | M27: ሰኔ18 | O27: {=SUMPRODUCT(($F27:$F27="Parcial")*ABS($C27:$C27-$N27:$N27))} -> 0 | W27: =IF($D27="","",_xlfn.LET(_xlpm.gDate,D27,_xlpm.ethYear,IF(_xlpm.gDate>=DATE(YEAR(_xlpm.gDate),9,11),YEAR(_xlpm.gDate)-7,YEAR(_xlpm.gDate)-8),_xlpm.prevEthYear,_xlpm.ethYear-1,_xlpm.startDate,IF(_xlpm.gDate>=DATE(YEAR(_xlpm.gDate),9,11),DATE(YEAR(_xlpm.gDate),9,11)+IF(MOD(_xlpm.prevEthYear,4)=3,1,0),DATE(YEAR(_xlpm.gDate)-1,9,11)+IF(MOD(_xlpm.prevEthYear,4)=3,1,0)),_xlpm.dayOfYear,_xlpm.gDate-_xlpm.startDate+1,_xlpm.month,IF(_xlpm.dayOfYear<=360,CEILING(_xlpm.dayOfYear/30,1),13),_xlpm.day,IF(_xlpm.month=13,_xlpm.dayOfYear-360,_xlpm.dayOfYear-(_xlpm.month-1)*30),TEXT(_xlpm.ethYear,"0000")&"-"&TEXT(_xlpm.month,"00")&"-"&TEXT(_xlpm.day,"00"))) -> 2018-10-17 | X27: =IF($W27="","",TEXT($W27,"mm")) -> 10 | Y27: =IFERROR(CHOOSE(X27,"መስከረም","ጥቅምት","ህዳር ","ታህሳስ ","ጥር ","የካቲት ","መጋቢት18","ሚይዚያ ","ግንቦት18","ሰኔ18","ሐምሌ ","ነሐሴ ","Pagume"),"") -> ሰኔ18 | Z27: =IF($K27="","",_xlfn.LET(_xlpm.gDate,K27,_xlpm.ethYear,IF(_xlpm.gDate>=DATE(YEAR(_xlpm.gDate),9,11),YEAR(_xlpm.gDate)-7,YEAR(_xlpm.gDate)-8),_xlpm.prevEthYear,_xlpm.ethYear-1,_xlpm.startDate,IF(_xlpm.gDate>=DATE(YEAR(_xlpm.gDate),9,11),DATE(YEAR(_xlpm.gDate),9,11)+IF(MOD(_xlpm.prevEthYear,4)=3,1,0),DATE(YEAR(_xlpm.gDate)-1,9,11)+IF(MOD(_xlpm.prevEthYear,4)=3,1,0)),_xlpm.dayOfYear,_xlpm.gDate-_xlpm.startDate+1,_xlpm.month,IF(_xlpm.dayOfYear<=360,CEILING(_xlpm.dayOfYear/30,1),13),_xlpm.day,IF(_xlpm.month=13,_xlpm.dayOfYear-360,_xlpm.dayOfYear-(_xlpm.month-1)*30),TEXT(_xlpm.ethYear,"0000")&"-"&TEXT(_xlpm.month,"00")&"-"&TEXT(_xlpm.day,"00"))) | AA27: =IF($Z27="","",TEXT($Z27,"mm")) | AB27: =IFERROR(CHOOSE(AA27,"መስከረም","ጥቅምት","ህዳር ","ታህሳስ ","ጥር ","የካቲት ","መጋቢት ","ሚይዚያ ","ግንቦት ","ሰኔ ","ሐምሌ ","ነሐሴ ","Pagume"),"") | AD27: =IF($D27="","",YEAR(D27)&"-W"&WEEKNUM(D27,2)) -> 2026-W26 | AE27: =IF($K27="","",YEAR(K27)&"-W"&WEEKNUM(K27,2))
A28: 27 | B28: Sebez | C28: 13000 | D28: 46198 | E28: =IF(D28="","",IF(F28="paid",0,I28-J28)) -> 10 | F28: Credit | G28: =IF(F28="Paid","Settled",IF(E28="","",IF(E28<0,"Over Due",IF(E28<=10,"Due soon",IF(E28<=20,"FP need",IF(E28<=30,"Pending","Pending")))))) -> Due soon | H28: =IFERROR(CHOOSE($X28,"መስከረም","ጥቅምት","ህዳር ","ታህሳስ ","ጥር ","የካቲት ","መጋቢት ","ሚይዚያ ","ግንቦት ","ሰኔ ","ሐምሌ ","ነሐሴ ","Pagume"),"") -> ሰኔ | I28: 30 | J28: =IF(D28="","-",$Q$1-D28) -> 20 | L28: =IF(E28="","",$Q$1+E28) -> 46228 | M28: ሰኔ18 | O28: {=SUMPRODUCT(($F28:$F28="Parcial")*ABS($C28:$C28-$N28:$N28))} -> 0 | W28: =IF($D28="","",_xlfn.LET(_xlpm.gDate,D28,_xlpm.ethYear,IF(_xlpm.gDate>=DATE(YEAR(_xlpm.gDate),9,11),YEAR(_xlpm.gDate)-7,YEAR(_xlpm.gDate)-8),_xlpm.prevEthYear,_xlpm.ethYear-1,_xlpm.startDate,IF(_xlpm.gDate>=DATE(YEAR(_xlpm.gDate),9,11),DATE(YEAR(_xlpm.gDate),9,11)+IF(MOD(_xlpm.prevEthYear,4)=3,1,0),DATE(YEAR(_xlpm.gDate)-1,9,11)+IF(MOD(_xlpm.prevEthYear,4)=3,1,0)),_xlpm.dayOfYear,_xlpm.gDate-_xlpm.startDate+1,_xlpm.month,IF(_xlpm.dayOfYear<=360,CEILING(_xlpm.dayOfYear/30,1),13),_xlpm.day,IF(_xlpm.month=13,_xlpm.dayOfYear-360,_xlpm.dayOfYear-(_xlpm.month-1)*30),TEXT(_xlpm.ethYear,"0000")&"-"&TEXT(_xlpm.month,"00")&"-"&TEXT(_xlpm.day,"00"))) -> 2018-10-18 | X28: =IF($W28="","",TEXT($W28,"mm")) -> 10 | Y28: =IFERROR(CHOOSE(X28,"መስከረም","ጥቅምት","ህዳር ","ታህሳስ ","ጥር ","የካቲት ","መጋቢት18","ሚይዚያ ","ግንቦት18","ሰኔ18","ሐምሌ ","ነሐሴ ","Pagume"),"") -> ሰኔ18 | Z28: =IF($K28="","",_xlfn.LET(_xlpm.gDate,K28,_xlpm.ethYear,IF(_xlpm.gDate>=DATE(YEAR(_xlpm.gDate),9,11),YEAR(_xlpm.gDate)-7,YEAR(_xlpm.gDate)-8),_xlpm.prevEthYear,_xlpm.ethYear-1,_xlpm.startDate,IF(_xlpm.gDate>=DATE(YEAR(_xlpm.gDate),9,11),DATE(YEAR(_xlpm.gDate),9,11)+IF(MOD(_xlpm.prevEthYear,4)=3,1,0),DATE(YEAR(_xlpm.gDate)-1,9,11)+IF(MOD(_xlpm.prevEthYear,4)=3,1,0)),_xlpm.dayOfYear,_xlpm.gDate-_xlpm.startDate+1,_xlpm.month,IF(_xlpm.dayOfYear<=360,CEILING(_xlpm.dayOfYear/30,1),13),_xlpm.day,IF(_xlpm.month=13,_xlpm.dayOfYear-360,_xlpm.dayOfYear-(_xlpm.month-1)*30),TEXT(_xlpm.ethYear,"0000")&"-"&TEXT(_xlpm.month,"00")&"-"&TEXT(_xlpm.day,"00"))) | AA28: =IF($Z28="","",TEXT($Z28,"mm")) | AB28: =IFERROR(CHOOSE(AA28,"መስከረም","ጥቅምት","ህዳር ","ታህሳስ ","ጥር ","የካቲት ","መጋቢት ","ሚይዚያ ","ግንቦት ","ሰኔ ","ሐምሌ ","ነሐሴ ","Pagume"),"") | AD28: =IF($D28="","",YEAR(D28)&"-W"&WEEKNUM(D28,2)) -> 2026-W26 | AE28: =IF($K28="","",YEAR(K28)&"-W"&WEEKNUM(K28,2))
A29: 28 | B29: Wilget | C29: 99000 | D29: 46199 | E29: =IF(D29="","",IF(F29="paid",0,I29-J29)) -> 41 | F29: Credit | G29: =IF(F29="Paid","Settled",IF(E29="","",IF(E29<0,"Over Due",IF(E29<=10,"Due soon",IF(E29<=20,"FP need",IF(E29<=30,"Pending","Pending")))))) -> Pending | H29: =IFERROR(CHOOSE($X29,"መስከረም","ጥቅምት","ህዳር ","ታህሳስ ","ጥር ","የካቲት ","መጋቢት ","ሚይዚያ ","ግንቦት ","ሰኔ ","ሐምሌ ","ነሐሴ ","Pagume"),"") -> ሰኔ | I29: 60 | J29: =IF(D29="","-",$Q$1-D29) -> 19 | L29: =IF(E29="","",$Q$1+E29) -> 46259 | M29: ሰኔ18 | O29: {=SUMPRODUCT(($F29:$F29="Parcial")*ABS($C29:$C29-$N29:$N29))} -> 0 | W29: =IF($D29="","",_xlfn.LET(_xlpm.gDate,D29,_xlpm.ethYear,IF(_xlpm.gDate>=DATE(YEAR(_xlpm.gDate),9,11),YEAR(_xlpm.gDate)-7,YEAR(_xlpm.gDate)-8),_xlpm.prevEthYear,_xlpm.ethYear-1,_xlpm.startDate,IF(_xlpm.gDate>=DATE(YEAR(_xlpm.gDate),9,11),DATE(YEAR(_xlpm.gDate),9,11)+IF(MOD(_xlpm.prevEthYear,4)=3,1,0),DATE(YEAR(_xlpm.gDate)-1,9,11)+IF(MOD(_xlpm.prevEthYear,4)=3,1,0)),_xlpm.dayOfYear,_xlpm.gDate-_xlpm.startDate+1,_xlpm.month,IF(_xlpm.dayOfYear<=360,CEILING(_xlpm.dayOfYear/30,1),13),_xlpm.day,IF(_xlpm.month=13,_xlpm.dayOfYear-360,_xlpm.dayOfYear-(_xlpm.month-1)*30),TEXT(_xlpm.ethYear,"0000")&"-"&TEXT(_xlpm.month,"00")&"-"&TEXT(_xlpm.day,"00"))) -> 2018-10-19 | X29: =IF($W29="","",TEXT($W29,"mm")) -> 10 | Y29: =IFERROR(CHOOSE(X29,"መስከረም","ጥቅምት","ህዳር ","ታህሳስ ","ጥር ","የካቲት ","መጋቢት18","ሚይዚያ ","ግንቦት18","ሰኔ18","ሐምሌ ","ነሐሴ ","Pagume"),"") -> ሰኔ18 | Z29: =IF($K29="","",_xlfn.LET(_xlpm.gDate,K29,_xlpm.ethYear,IF(_xlpm.gDate>=DATE(YEAR(_xlpm.gDate),9,11),YEAR(_xlpm.gDate)-7,YEAR(_xlpm.gDate)-8),_xlpm.prevEthYear,_xlpm.ethYear-1,_xlpm.startDate,IF(_xlpm.gDate>=DATE(YEAR(_xlpm.gDate),9,11),DATE(YEAR(_xlpm.gDate),9,11)+IF(MOD(_xlpm.prevEthYear,4)=3,1,0),DATE(YEAR(_xlpm.gDate)-1,9,11)+IF(MOD(_xlpm.prevEthYear,4)=3,1,0)),_xlpm.dayOfYear,_xlpm.gDate-_xlpm.startDate+1,_xlpm.month,IF(_xlpm.dayOfYear<=360,CEILING(_xlpm.dayOfYear/30,1),13),_xlpm.day,IF(_xlpm.month=13,_xlpm.dayOfYear-360,_xlpm.dayOfYear-(_xlpm.month-1)*30),TEXT(_xlpm.ethYear,"0000")&"-"&TEXT(_xlpm.month,"00")&"-"&TEXT(_xlpm.day,"00"))) | AA29: =IF($Z29="","",TEXT($Z29,"mm")) | AB29: =IFERROR(CHOOSE(AA29,"መስከረም","ጥቅምት","ህዳር ","ታህሳስ ","ጥር ","የካቲት ","መጋቢት ","ሚይዚያ ","ግንቦት ","ሰኔ ","ሐምሌ ","ነሐሴ ","Pagume"),"") | AD29: =IF($D29="","",YEAR(D29)&"-W"&WEEKNUM(D29,2)) -> 2026-W26 | AE29: =IF($K29="","",YEAR(K29)&"-W"&WEEKNUM(K29,2))
A30: 29 | B30: Jacaranda | C30: 60000 | D30: 46199 | E30: =IF(D30="","",IF(F30="paid",0,I30-J30)) -> 11 | F30: Credit | G30: =IF(F30="Paid","Settled",IF(E30="","",IF(E30<0,"Over Due",IF(E30<=10,"Due soon",IF(E30<=20,"FP need",IF(E30<=30,"Pending","Pending")))))) -> FP need | H30: =IFERROR(CHOOSE($X30,"መስከረም","ጥቅምት","ህዳር ","ታህሳስ ","ጥር ","የካቲት ","መጋቢት ","ሚይዚያ ","ግንቦት ","ሰኔ ","ሐምሌ ","ነሐሴ ","Pagume"),"") -> ሰኔ | I30: 30 | J30: =IF(D30="","-",$Q$1-D30) -> 19 | L30: =IF(E30="","",$Q$1+E30) -> 46229 | M30: ሰኔ18 | O30: {=SUMPRODUCT(($F30:$F30="Parcial")*ABS($C30:$C30-$N30:$N30))} -> 0 | W30: =IF($D30="","",_xlfn.LET(_xlpm.gDate,D30,_xlpm.ethYear,IF(_xlpm.gDate>=DATE(YEAR(_xlpm.gDate),9,11),YEAR(_xlpm.gDate)-7,YEAR(_xlpm.gDate)-8),_xlpm.prevEthYear,_xlpm.ethYear-1,_xlpm.startDate,IF(_xlpm.gDate>=DATE(YEAR(_xlpm.gDate),9,11),DATE(YEAR(_xlpm.gDate),9,11)+IF(MOD(_xlpm.prevEthYear,4)=3,1,0),DATE(YEAR(_xlpm.gDate)-1,9,11)+IF(MOD(_xlpm.prevEthYear,4)=3,1,0)),_xlpm.dayOfYear,_xlpm.gDate-_xlpm.startDate+1,_xlpm.month,IF(_xlpm.dayOfYear<=360,CEILING(_xlpm.dayOfYear/30,1),13),_xlpm.day,IF(_xlpm.month=13,_xlpm.dayOfYear-360,_xlpm.dayOfYear-(_xlpm.month-1)*30),TEXT(_xlpm.ethYear,"0000")&"-"&TEXT(_xlpm.month,"00")&"-"&TEXT(_xlpm.day,"00"))) -> 2018-10-19 | X30: =IF($W30="","",TEXT($W30,"mm")) -> 10 | Y30: =IFERROR(CHOOSE(X30,"መስከረም","ጥቅምት","ህዳር ","ታህሳስ ","ጥር ","የካቲት ","መጋቢት18","ሚይዚያ ","ግንቦት18","ሰኔ18","ሐምሌ ","ነሐሴ ","Pagume"),"") -> ሰኔ18 | Z30: =IF($K30="","",_xlfn.LET(_xlpm.gDate,K30,_xlpm.ethYear,IF(_xlpm.gDate>=DATE(YEAR(_xlpm.gDate),9,11),YEAR(_xlpm.gDate)-7,YEAR(_xlpm.gDate)-8),_xlpm.prevEthYear,_xlpm.ethYear-1,_xlpm.startDate,IF(_xlpm.gDate>=DATE(YEAR(_xlpm.gDate),9,11),DATE(YEAR(_xlpm.gDate),9,11)+IF(MOD(_xlpm.prevEthYear,4)=3,1,0),DATE(YEAR(_xlpm.gDate)-1,9,11)+IF(MOD(_xlpm.prevEthYear,4)=3,1,0)),_xlpm.dayOfYear,_xlpm.gDate-_xlpm.startDate+1,_xlpm.month,IF(_xlpm.dayOfYear<=360,CEILING(_xlpm.dayOfYear/30,1),13),_xlpm.day,IF(_xlpm.month=13,_xlpm.dayOfYear-360,_xlpm.dayOfYear-(_xlpm.month-1)*30),TEXT(_xlpm.ethYear,"0000")&"-"&TEXT(_xlpm.month,"00")&"-"&TEXT(_xlpm.day,"00"))) | AA30: =IF($Z30="","",TEXT($Z30,"mm")) | AB30: =IFERROR(CHOOSE(AA30,"መስከረም","ጥቅምት","ህዳር ","ታህሳስ ","ጥር ","የካቲት ","መጋቢት ","ሚይዚያ ","ግንቦት ","ሰኔ ","ሐምሌ ","ነሐሴ ","Pagume"),"") | AD30: =IF($D30="","",YEAR(D30)&"-W"&WEEKNUM(D30,2)) -> 2026-W26 | AE30: =IF($K30="","",YEAR(K30)&"-W"&WEEKNUM(K30,2))
A31: 30 | B31: Azi Ws | C31: 457200 | D31: 46210 | E31: =IF(D31="","",IF(F31="paid",0,I31-J31)) -> 52 | F31: Credit | G31: =IF(F31="Paid","Settled",IF(E31="","",IF(E31<0,"Over Due",IF(E31<=10,"Due soon",IF(E31<=20,"FP need",IF(E31<=30,"Pending","Pending")))))) -> Pending | H31: =IFERROR(CHOOSE($X31,"መስከረም","ጥቅምት","ህዳር ","ታህሳስ ","ጥር ","የካቲት ","መጋቢት ","ሚይዚያ ","ግንቦት ","ሰኔ ","ሐምሌ ","ነሐሴ ","Pagume"),"") -> ሰኔ | I31: 60 | J31: =IF(D31="","-",$Q$1-D31) -> 8 | L31: =IF(E31="","",$Q$1+E31) -> 46270 | M31: ሰኔ18 | O31: {=SUMPRODUCT(($F31:$F31="Parcial")*ABS($C31:$C31-$N31:$N31))} -> 0 | W31: =IF($D31="","",_xlfn.LET(_xlpm.gDate,D31,_xlpm.ethYear,IF(_xlpm.gDate>=DATE(YEAR(_xlpm.gDate),9,11),YEAR(_xlpm.gDate)-7,YEAR(_xlpm.gDate)-8),_xlpm.prevEthYear,_xlpm.ethYear-1,_xlpm.startDate,IF(_xlpm.gDate>=DATE(YEAR(_xlpm.gDate),9,11),DATE(YEAR(_xlpm.gDate),9,11)+IF(MOD(_xlpm.prevEthYear,4)=3,1,0),DATE(YEAR(_xlpm.gDate)-1,9,11)+IF(MOD(_xlpm.prevEthYear,4)=3,1,0)),_xlpm.dayOfYear,_xlpm.gDate-_xlpm.startDate+1,_xlpm.month,IF(_xlpm.dayOfYear<=360,CEILING(_xlpm.dayOfYear/30,1),13),_xlpm.day,IF(_xlpm.month=13,_xlpm.dayOfYear-360,_xlpm.dayOfYear-(_xlpm.month-1)*30),TEXT(_xlpm.ethYear,"0000")&"-"&TEXT(_xlpm.month,"00")&"-"&TEXT(_xlpm.day,"00"))) -> 2018-10-30 | X31: =IF($W31="","",TEXT($W31,"mm")) -> 10 | Y31: =IFERROR(CHOOSE(X31,"መስከረም","ጥቅምት","ህዳር ","ታህሳስ ","ጥር ","የካቲት ","መጋቢት18","ሚይዚያ ","ግንቦት18","ሰኔ18","ሐምሌ ","ነሐሴ ","Pagume"),"") -> ሰኔ18 | Z31: =IF($K31="","",_xlfn.LET(_xlpm.gDate,K31,_xlpm.ethYear,IF(_xlpm.gDate>=DATE(YEAR(_xlpm.gDate),9,11),YEAR(_xlpm.gDate)-7,YEAR(_xlpm.gDate)-8),_xlpm.prevEthYear,_xlpm.ethYear-1,_xlpm.startDate,IF(_xlpm.gDate>=DATE(YEAR(_xlpm.gDate),9,11),DATE(YEAR(_xlpm.gDate),9,11)+IF(MOD(_xlpm.prevEthYear,4)=3,1,0),DATE(YEAR(_xlpm.gDate)-1,9,11)+IF(MOD(_xlpm.prevEthYear,4)=3,1,0)),_xlpm.dayOfYear,_xlpm.gDate-_xlpm.startDate+1,_xlpm.month,IF(_xlpm.dayOfYear<=360,CEILING(_xlpm.dayOfYear/30,1),13),_xlpm.day,IF(_xlpm.month=13,_xlpm.dayOfYear-360,_xlpm.dayOfYear-(_xlpm.month-1)*30),TEXT(_xlpm.ethYear,"0000")&"-"&TEXT(_xlpm.month,"00")&"-"&TEXT(_xlpm.day,"00"))) | AA31: =IF($Z31="","",TEXT($Z31,"mm")) | AB31: =IFERROR(CHOOSE(AA31,"መስከረም","ጥቅምት","ህዳር ","ታህሳስ ","ጥር ","የካቲት ","መጋቢት ","ሚይዚያ ","ግንቦት ","ሰኔ ","ሐምሌ ","ነሐሴ ","Pagume"),"") | AD31: =IF($D31="","",YEAR(D31)&"-W"&WEEKNUM(D31,2)) -> 2026-W28 | AE31: =IF($K31="","",YEAR(K31)&"-W"&WEEKNUM(K31,2))
A32: 31 | B32: Filix pharma | C32: 11500 | D32: 46210 | E32: =IF(D32="","",IF(F32="paid",0,I32-J32)) -> 22 | F32: Credit | G32: =IF(F32="Paid","Settled",IF(E32="","",IF(E32<0,"Over Due",IF(E32<=10,"Due soon",IF(E32<=20,"FP need",IF(E32<=30,"Pending","Pending")))))) -> Pending | H32: =IFERROR(CHOOSE($X32,"መስከረም","ጥቅምት","ህዳር ","ታህሳስ ","ጥር ","የካቲት ","መጋቢት ","ሚይዚያ ","ግንቦት ","ሰኔ ","ሐምሌ ","ነሐሴ ","Pagume"),"") -> ሰኔ | I32: 30 | J32: =IF(D32="","-",$Q$1-D32) -> 8 | L32: =IF(E32="","",$Q$1+E32) -> 46240 | M32: ሰኔ18 | O32: {=SUMPRODUCT(($F32:$F32="Parcial")*ABS($C32:$C32-$N32:$N32))} -> 0 | W32: =IF($D32="","",_xlfn.LET(_xlpm.gDate,D32,_xlpm.ethYear,IF(_xlpm.gDate>=DATE(YEAR(_xlpm.gDate),9,11),YEAR(_xlpm.gDate)-7,YEAR(_xlpm.gDate)-8),_xlpm.prevEthYear,_xlpm.ethYear-1,_xlpm.startDate,IF(_xlpm.gDate>=DATE(YEAR(_xlpm.gDate),9,11),DATE(YEAR(_xlpm.gDate),9,11)+IF(MOD(_xlpm.prevEthYear,4)=3,1,0),DATE(YEAR(_xlpm.gDate)-1,9,11)+IF(MOD(_xlpm.prevEthYear,4)=3,1,0)),_xlpm.dayOfYear,_xlpm.gDate-_xlpm.startDate+1,_xlpm.month,IF(_xlpm.dayOfYear<=360,CEILING(_xlpm.dayOfYear/30,1),13),_xlpm.day,IF(_xlpm.month=13,_xlpm.dayOfYear-360,_xlpm.dayOfYear-(_xlpm.month-1)*30),TEXT(_xlpm.ethYear,"0000")&"-"&TEXT(_xlpm.month,"00")&"-"&TEXT(_xlpm.day,"00"))) -> 2018-10-30 | X32: =IF($W32="","",TEXT($W32,"mm")) -> 10 | Y32: =IFERROR(CHOOSE(X32,"መስከረም","ጥቅምት","ህዳር ","ታህሳስ ","ጥር ","የካቲት ","መጋቢት18","ሚይዚያ ","ግንቦት18","ሰኔ18","ሐምሌ ","ነሐሴ ","Pagume"),"") -> ሰኔ18 | Z32: =IF($K32="","",_xlfn.LET(_xlpm.gDate,K32,_xlpm.ethYear,IF(_xlpm.gDate>=DATE(YEAR(_xlpm.gDate),9,11),YEAR(_xlpm.gDate)-7,YEAR(_xlpm.gDate)-8),_xlpm.prevEthYear,_xlpm.ethYear-1,_xlpm.startDate,IF(_xlpm.gDate>=DATE(YEAR(_xlpm.gDate),9,11),DATE(YEAR(_xlpm.gDate),9,11)+IF(MOD(_xlpm.prevEthYear,4)=3,1,0),DATE(YEAR(_xlpm.gDate)-1,9,11)+IF(MOD(_xlpm.prevEthYear,4)=3,1,0)),_xlpm.dayOfYear,_xlpm.gDate-_xlpm.startDate+1,_xlpm.month,IF(_xlpm.dayOfYear<=360,CEILING(_xlpm.dayOfYear/30,1),13),_xlpm.day,IF(_xlpm.month=13,_xlpm.dayOfYear-360,_xlpm.dayOfYear-(_xlpm.month-1)*30),TEXT(_xlpm.ethYear,"0000")&"-"&TEXT(_xlpm.month,"00")&"-"&TEXT(_xlpm.day,"00"))) | AA32: =IF($Z32="","",TEXT($Z32,"mm")) | AB32: =IFERROR(CHOOSE(AA32,"መስከረም","ጥቅምት","ህዳር ","ታህሳስ ","ጥር ","የካቲት ","መጋቢት ","ሚይዚያ ","ግንቦት ","ሰኔ ","ሐምሌ ","ነሐሴ ","Pagume"),"") | AD32: =IF($D32="","",YEAR(D32)&"-W"&WEEKNUM(D32,2)) -> 2026-W28 | AE32: =IF($K32="","",YEAR(K32)&"-W"&WEEKNUM(K32,2))
A33: 32 | B33: Nolawi | C33: 30800 | D33: 46214 | E33: =IF(D33="","",IF(F33="paid",0,I33-J33)) -> 26 | F33: Credit | G33: =IF(F33="Paid","Settled",IF(E33="","",IF(E33<0,"Over Due",IF(E33<=10,"Due soon",IF(E33<=20,"FP need",IF(E33<=30,"Pending","Pending")))))) -> Pending | H33: =IFERROR(CHOOSE($X33,"መስከረም","ጥቅምት","ህዳር ","ታህሳስ ","ጥር ","የካቲት ","መጋቢት ","ሚይዚያ ","ግንቦት ","ሰኔ ","ሐምሌ ","ነሐሴ ","Pagume"),"") -> ሐምሌ | I33: 30 | J33: =IF(D33="","-",$Q$1-D33) -> 4 | L33: =IF(E33="","",$Q$1+E33) -> 46244 | M33: end of18 | O33: {=SUMPRODUCT(($F33:$F33="Parcial")*ABS($C33:$C33-$N33:$N33))} -> 0 | W33: =IF($D33="","",_xlfn.LET(_xlpm.gDate,D33,_xlpm.ethYear,IF(_xlpm.gDate>=DATE(YEAR(_xlpm.gDate),9,11),YEAR(_xlpm.gDate)-7,YEAR(_xlpm.gDate)-8),_xlpm.prevEthYear,_xlpm.ethYear-1,_xlpm.startDate,IF(_xlpm.gDate>=DATE(YEAR(_xlpm.gDate),9,11),DATE(YEAR(_xlpm.gDate),9,11)+IF(MOD(_xlpm.prevEthYear,4)=3,1,0),DATE(YEAR(_xlpm.gDate)-1,9,11)+IF(MOD(_xlpm.prevEthYear,4)=3,1,0)),_xlpm.dayOfYear,_xlpm.gDate-_xlpm.startDate+1,_xlpm.month,IF(_xlpm.dayOfYear<=360,CEILING(_xlpm.dayOfYear/30,1),13),_xlpm.day,IF(_xlpm.month=13,_xlpm.dayOfYear-360,_xlpm.dayOfYear-(_xlpm.month-1)*30),TEXT(_xlpm.ethYear,"0000")&"-"&TEXT(_xlpm.month,"00")&"-"&TEXT(_xlpm.day,"00"))) -> 2018-11-04 | X33: =IF($W33="","",TEXT($W33,"mm")) -> 11 | Y33: =IFERROR(CHOOSE(X33,"መስከረም","ጥቅምት","ህዳር ","ታህሳስ ","ጥር ","የካቲት ","መጋቢት ","ሚይዚያ ","ግንቦት ","ሰኔ ","ሐምሌ ","ነሐሴ ","Pagume"),"") -> ሐምሌ | Z33: =IF($K33="","",_xlfn.LET(_xlpm.gDate,K33,_xlpm.ethYear,IF(_xlpm.gDate>=DATE(YEAR(_xlpm.gDate),9,11),YEAR(_xlpm.gDate)-7,YEAR(_xlpm.gDate)-8),_xlpm.prevEthYear,_xlpm.ethYear-1,_xlpm.startDate,IF(_xlpm.gDate>=DATE(YEAR(_xlpm.gDate),9,11),DATE(YEAR(_xlpm.gDate),9,11)+IF(MOD(_xlpm.prevEthYear,4)=3,1,0),DATE(YEAR(_xlpm.gDate)-1,9,11)+IF(MOD(_xlpm.prevEthYear,4)=3,1,0)),_xlpm.dayOfYear,_xlpm.gDate-_xlpm.startDate+1,_xlpm.month,IF(_xlpm.dayOfYear<=360,CEILING(_xlpm.dayOfYear/30,1),13),_xlpm.day,IF(_xlpm.month=13,_xlpm.dayOfYear-360,_xlpm.dayOfYear-(_xlpm.month-1)*30),TEXT(_xlpm.ethYear,"0000")&"-"&TEXT(_xlpm.month,"00")&"-"&TEXT(_xlpm.day,"00"))) | AA33: =IF($Z33="","",TEXT($Z33,"mm")) | AB33: =IFERROR(CHOOSE(AA33,"መስከረም","ጥቅምት","ህዳር ","ታህሳስ ","ጥር ","የካቲት ","መጋቢት ","ሚይዚያ ","ግንቦት ","ሰኔ ","ሐምሌ ","ነሐሴ ","Pagume"),"") | AD33: =IF($D33="","",YEAR(D33)&"-W"&WEEKNUM(D33,2)) -> 2026-W28 | AE33: =IF($K33="","",YEAR(K33)&"-W"&WEEKNUM(K33,2))
A34: 33 | B34: Azi Ws | C34: 97200 | D34: 46214 | E34: =IF(D34="","",IF(F34="paid",0,I34-J34)) -> 56 | F34: Credit | G34: =IF(F34="Paid","Settled",IF(E34="","",IF(E34<0,"Over Due",IF(E34<=10,"Due soon",IF(E34<=20,"FP need",IF(E34<=30,"Pending","Pending")))))) -> Pending | H34: =IFERROR(CHOOSE($X34,"መስከረም","ጥቅምት","ህዳር ","ታህሳስ ","ጥር ","የካቲት ","መጋቢት ","ሚይዚያ ","ግንቦት ","ሰኔ ","ሐምሌ ","ነሐሴ ","Pagume"),"") -> ሐምሌ | I34: 60 | J34: =IF(D34="","-",$Q$1-D34) -> 4 | L34: =IF(E34="","",$Q$1+E34) -> 46274 | O34: {=SUMPRODUCT(($F34:$F34="Parcial")*ABS($C34:$C34-$N34:$N34))} -> 0 | W34: =IF($D34="","",_xlfn.LET(_xlpm.gDate,D34,_xlpm.ethYear,IF(_xlpm.gDate>=DATE(YEAR(_xlpm.gDate),9,11),YEAR(_xlpm.gDate)-7,YEAR(_xlpm.gDate)-8),_xlpm.prevEthYear,_xlpm.ethYear-1,_xlpm.startDate,IF(_xlpm.gDate>=DATE(YEAR(_xlpm.gDate),9,11),DATE(YEAR(_xlpm.gDate),9,11)+IF(MOD(_xlpm.prevEthYear,4)=3,1,0),DATE(YEAR(_xlpm.gDate)-1,9,11)+IF(MOD(_xlpm.prevEthYear,4)=3,1,0)),_xlpm.dayOfYear,_xlpm.gDate-_xlpm.startDate+1,_xlpm.month,IF(_xlpm.dayOfYear<=360,CEILING(_xlpm.dayOfYear/30,1),13),_xlpm.day,IF(_xlpm.month=13,_xlpm.dayOfYear-360,_xlpm.dayOfYear-(_xlpm.month-1)*30),TEXT(_xlpm.ethYear,"0000")&"-"&TEXT(_xlpm.month,"00")&"-"&TEXT(_xlpm.day,"00"))) -> 2018-11-04 | X34: =IF($W34="","",TEXT($W34,"mm")) -> 11 | Y34: =IFERROR(CHOOSE(X34,"መስከረም","ጥቅምት","ህዳር ","ታህሳስ ","ጥር ","የካቲት ","መጋቢት ","ሚይዚያ ","ግንቦት ","ሰኔ ","ሐምሌ ","ነሐሴ ","Pagume"),"") -> ሐምሌ | Z34: =IF($K34="","",_xlfn.LET(_xlpm.gDate,K34,_xlpm.ethYear,IF(_xlpm.gDate>=DATE(YEAR(_xlpm.gDate),9,11),YEAR(_xlpm.gDate)-7,YEAR(_xlpm.gDate)-8),_xlpm.prevEthYear,_xlpm.ethYear-1,_xlpm.startDate,IF(_xlpm.gDate>=DATE(YEAR(_xlpm.gDate),9,11),DATE(YEAR(_xlpm.gDate),9,11)+IF(MOD(_xlpm.prevEthYear,4)=3,1,0),DATE(YEAR(_xlpm.gDate)-1,9,11)+IF(MOD(_xlpm.prevEthYear,4)=3,1,0)),_xlpm.dayOfYear,_xlpm.gDate-_xlpm.startDate+1,_xlpm.month,IF(_xlpm.dayOfYear<=360,CEILING(_xlpm.dayOfYear/30,1),13),_xlpm.day,IF(_xlpm.month=13,_xlpm.dayOfYear-360,_xlpm.dayOfYear-(_xlpm.month-1)*30),TEXT(_xlpm.ethYear,"0000")&"-"&TEXT(_xlpm.month,"00")&"-"&TEXT(_xlpm.day,"00"))) | AA34: =IF($Z34="","",TEXT($Z34,"mm")) | AB34: =IFERROR(CHOOSE(AA34,"መስከረም","ጥቅምት","ህዳር ","ታህሳስ ","ጥር ","የካቲት ","መጋቢት ","ሚይዚያ ","ግንቦት ","ሰኔ ","ሐምሌ ","ነሐሴ ","Pagume"),"") | AD34: =IF($D34="","",YEAR(D34)&"-W"&WEEKNUM(D34,2)) -> 2026-W28 | AE34: =IF($K34="","",YEAR(K34)&"-W"&WEEKNUM(K34,2))
A35: 34 | E35: =IF(D35="","",IF(F35="paid",0,I35-J35)) | G35: =IF(F35="Paid","Settled",IF(E35="","",IF(E35<0,"Over Due",IF(E35<=10,"Due soon",IF(E35<=20,"FP need",IF(E35<=30,"Pending","Pending")))))) | H35: =IFERROR(CHOOSE($X35,"መስከረም","ጥቅምት","ህዳር ","ታህሳስ ","ጥር ","የካቲት ","መጋቢት ","ሚይዚያ ","ግንቦት ","ሰኔ ","ሐምሌ ","ነሐሴ ","Pagume"),"") | J35: =IF(D35="","-",$Q$1-D35) -> - | L35: =IF(E35="","",$Q$1+E35) | O35: {=SUMPRODUCT(($F35:$F35="Parcial")*ABS($C35:$C35-$N35:$N35))} -> 0 | W35: =IF($D35="","",_xlfn.LET(_xlpm.gDate,D35,_xlpm.ethYear,IF(_xlpm.gDate>=DATE(YEAR(_xlpm.gDate),9,11),YEAR(_xlpm.gDate)-7,YEAR(_xlpm.gDate)-8),_xlpm.prevEthYear,_xlpm.ethYear-1,_xlpm.startDate,IF(_xlpm.gDate>=DATE(YEAR(_xlpm.gDate),9,11),DATE(YEAR(_xlpm.gDate),9,11)+IF(MOD(_xlpm.prevEthYear,4)=3,1,0),DATE(YEAR(_xlpm.gDate)-1,9,11)+IF(MOD(_xlpm.prevEthYear,4)=3,1,0)),_xlpm.dayOfYear,_xlpm.gDate-_xlpm.startDate+1,_xlpm.month,IF(_xlpm.dayOfYear<=360,CEILING(_xlpm.dayOfYear/30,1),13),_xlpm.day,IF(_xlpm.month=13,_xlpm.dayOfYear-360,_xlpm.dayOfYear-(_xlpm.month-1)*30),TEXT(_xlpm.ethYear,"0000")&"-"&TEXT(_xlpm.month,"00")&"-"&TEXT(_xlpm.day,"00"))) | X35: =IF($W35="","",TEXT($W35,"mm")) | Y35: =IFERROR(CHOOSE(X35,"መስከረም","ጥቅምት","ህዳር ","ታህሳስ ","ጥር ","የካቲት ","መጋቢት ","ሚይዚያ ","ግንቦት ","ሰኔ ","ሐምሌ ","ነሐሴ ","Pagume"),"") | Z35: =IF($K35="","",_xlfn.LET(_xlpm.gDate,K35,_xlpm.ethYear,IF(_xlpm.gDate>=DATE(YEAR(_xlpm.gDate),9,11),YEAR(_xlpm.gDate)-7,YEAR(_xlpm.gDate)-8),_xlpm.prevEthYear,_xlpm.ethYear-1,_xlpm.startDate,IF(_xlpm.gDate>=DATE(YEAR(_xlpm.gDate),9,11),DATE(YEAR(_xlpm.gDate),9,11)+IF(MOD(_xlpm.prevEthYear,4)=3,1,0),DATE(YEAR(_xlpm.gDate)-1,9,11)+IF(MOD(_xlpm.prevEthYear,4)=3,1,0)),_xlpm.dayOfYear,_xlpm.gDate-_xlpm.startDate+1,_xlpm.month,IF(_xlpm.dayOfYear<=360,CEILING(_xlpm.dayOfYear/30,1),13),_xlpm.day,IF(_xlpm.month=13,_xlpm.dayOfYear-360,_xlpm.dayOfYear-(_xlpm.month-1)*30),TEXT(_xlpm.ethYear,"0000")&"-"&TEXT(_xlpm.month,"00")&"-"&TEXT(_xlpm.day,"00"))) | AA35: =IF($Z35="","",TEXT($Z35,"mm")) | AB35: =IFERROR(CHOOSE(AA35,"መስከረም","ጥቅምት","ህዳር ","ታህሳስ ","ጥር ","የካቲት ","መጋቢት ","ሚይዚያ ","ግንቦት ","ሰኔ ","ሐምሌ ","ነሐሴ ","Pagume"),"") | AD35: =IF($D35="","",YEAR(D35)&"-W"&WEEKNUM(D35,2)) | AE35: =IF($K35="","",YEAR(K35)&"-W"&WEEKNUM(K35,2))
A36: 35 | E36: =IF(D36="","",IF(F36="paid",0,I36-J36)) | G36: =IF(F36="Paid","Settled",IF(E36="","",IF(E36<0,"Over Due",IF(E36<=10,"Due soon",IF(E36<=20,"FP need",IF(E36<=30,"Pending","Pending")))))) | H36: =IFERROR(CHOOSE($X36,"መስከረም","ጥቅምት","ህዳር ","ታህሳስ ","ጥር ","የካቲት ","መጋቢት ","ሚይዚያ ","ግንቦት ","ሰኔ ","ሐምሌ ","ነሐሴ ","Pagume"),"") | J36: =IF(D36="","-",$Q$1-D36) -> - | L36: =IF(E36="","",$Q$1+E36) | O36: {=SUMPRODUCT(($F36:$F36="Parcial")*ABS($C36:$C36-$N36:$N36))} -> 0 | W36: =IF($D36="","",_xlfn.LET(_xlpm.gDate,D36,_xlpm.ethYear,IF(_xlpm.gDate>=DATE(YEAR(_xlpm.gDate),9,11),YEAR(_xlpm.gDate)-7,YEAR(_xlpm.gDate)-8),_xlpm.prevEthYear,_xlpm.ethYear-1,_xlpm.startDate,IF(_xlpm.gDate>=DATE(YEAR(_xlpm.gDate),9,11),DATE(YEAR(_xlpm.gDate),9,11)+IF(MOD(_xlpm.prevEthYear,4)=3,1,0),DATE(YEAR(_xlpm.gDate)-1,9,11)+IF(MOD(_xlpm.prevEthYear,4)=3,1,0)),_xlpm.dayOfYear,_xlpm.gDate-_xlpm.startDate+1,_xlpm.month,IF(_xlpm.dayOfYear<=360,CEILING(_xlpm.dayOfYear/30,1),13),_xlpm.day,IF(_xlpm.month=13,_xlpm.dayOfYear-360,_xlpm.dayOfYear-(_xlpm.month-1)*30),TEXT(_xlpm.ethYear,"0000")&"-"&TEXT(_xlpm.month,"00")&"-"&TEXT(_xlpm.day,"00"))) | X36: =IF($W36="","",TEXT($W36,"mm")) | Y36: =IFERROR(CHOOSE(X36,"መስከረም","ጥቅምት","ህዳር ","ታህሳስ ","ጥር ","የካቲት ","መጋቢት ","ሚይዚያ ","ግንቦት ","ሰኔ ","ሐምሌ ","ነሐሴ ","Pagume"),"") | Z36: =IF($K36="","",_xlfn.LET(_xlpm.gDate,K36,_xlpm.ethYear,IF(_xlpm.gDate>=DATE(YEAR(_xlpm.gDate),9,11),YEAR(_xlpm.gDate)-7,YEAR(_xlpm.gDate)-8),_xlpm.prevEthYear,_xlpm.ethYear-1,_xlpm.startDate,IF(_xlpm.gDate>=DATE(YEAR(_xlpm.gDate),9,11),DATE(YEAR(_xlpm.gDate),9,11)+IF(MOD(_xlpm.prevEthYear,4)=3,1,0),DATE(YEAR(_xlpm.gDate)-1,9,11)+IF(MOD(_xlpm.prevEthYear,4)=3,1,0)),_xlpm.dayOfYear,_xlpm.gDate-_xlpm.startDate+1,_xlpm.month,IF(_xlpm.dayOfYear<=360,CEILING(_xlpm.dayOfYear/30,1),13),_xlpm.day,IF(_xlpm.month=13,_xlpm.dayOfYear-360,_xlpm.dayOfYear-(_xlpm.month-1)*30),TEXT(_xlpm.ethYear,"0000")&"-"&TEXT(_xlpm.month,"00")&"-"&TEXT(_xlpm.day,"00"))) | AA36: =IF($Z36="","",TEXT($Z36,"mm")) | AB36: =IFERROR(CHOOSE(AA36,"መስከረም","ጥቅምት","ህዳር ","ታህሳስ ","ጥር ","የካቲት ","መጋቢት ","ሚይዚያ ","ግንቦት ","ሰኔ ","ሐምሌ ","ነሐሴ ","Pagume"),"") | AD36: =IF($D36="","",YEAR(D36)&"-W"&WEEKNUM(D36,2)) | AE36: =IF($K36="","",YEAR(K36)&"-W"&WEEKNUM(K36,2))
A37: 36 | E37: =IF(D37="","",IF(F37="paid",0,I37-J37)) | G37: =IF(F37="Paid","Settled",IF(E37="","",IF(E37<0,"Over Due",IF(E37<=10,"Due soon",IF(E37<=20,"FP need",IF(E37<=30,"Pending","Pending")))))) | H37: =IFERROR(CHOOSE($X37,"መስከረም","ጥቅምት","ህዳር ","ታህሳስ ","ጥር ","የካቲት ","መጋቢት ","ሚይዚያ ","ግንቦት ","ሰኔ ","ሐምሌ ","ነሐሴ ","Pagume"),"") | J37: =IF(D37="","-",$Q$1-D37) -> - | L37: =IF(E37="","",$Q$1+E37) | O37: {=SUMPRODUCT(($F37:$F37="Parcial")*ABS($C37:$C37-$N37:$N37))} -> 0 | W37: =IF($D37="","",_xlfn.LET(_xlpm.gDate,D37,_xlpm.ethYear,IF(_xlpm.gDate>=DATE(YEAR(_xlpm.gDate),9,11),YEAR(_xlpm.gDate)-7,YEAR(_xlpm.gDate)-8),_xlpm.prevEthYear,_xlpm.ethYear-1,_xlpm.startDate,IF(_xlpm.gDate>=DATE(YEAR(_xlpm.gDate),9,11),DATE(YEAR(_xlpm.gDate),9,11)+IF(MOD(_xlpm.prevEthYear,4)=3,1,0),DATE(YEAR(_xlpm.gDate)-1,9,11)+IF(MOD(_xlpm.prevEthYear,4)=3,1,0)),_xlpm.dayOfYear,_xlpm.gDate-_xlpm.startDate+1,_xlpm.month,IF(_xlpm.dayOfYear<=360,CEILING(_xlpm.dayOfYear/30,1),13),_xlpm.day,IF(_xlpm.month=13,_xlpm.dayOfYear-360,_xlpm.dayOfYear-(_xlpm.month-1)*30),TEXT(_xlpm.ethYear,"0000")&"-"&TEXT(_xlpm.month,"00")&"-"&TEXT(_xlpm.day,"00"))) | X37: =IF($W37="","",TEXT($W37,"mm")) | Y37: =IFERROR(CHOOSE(X37,"መስከረም","ጥቅምት","ህዳር ","ታህሳስ ","ጥር ","የካቲት ","መጋቢት ","ሚይዚያ ","ግንቦት ","ሰኔ ","ሐምሌ ","ነሐሴ ","Pagume"),"") | Z37: =IF($K37="","",_xlfn.LET(_xlpm.gDate,K37,_xlpm.ethYear,IF(_xlpm.gDate>=DATE(YEAR(_xlpm.gDate),9,11),YEAR(_xlpm.gDate)-7,YEAR(_xlpm.gDate)-8),_xlpm.prevEthYear,_xlpm.ethYear-1,_xlpm.startDate,IF(_xlpm.gDate>=DATE(YEAR(_xlpm.gDate),9,11),DATE(YEAR(_xlpm.gDate),9,11)+IF(MOD(_xlpm.prevEthYear,4)=3,1,0),DATE(YEAR(_xlpm.gDate)-1,9,11)+IF(MOD(_xlpm.prevEthYear,4)=3,1,0)),_xlpm.dayOfYear,_xlpm.gDate-_xlpm.startDate+1,_xlpm.month,IF(_xlpm.dayOfYear<=360,CEILING(_xlpm.dayOfYear/30,1),13),_xlpm.day,IF(_xlpm.month=13,_xlpm.dayOfYear-360,_xlpm.dayOfYear-(_xlpm.month-1)*30),TEXT(_xlpm.ethYear,"0000")&"-"&TEXT(_xlpm.month,"00")&"-"&TEXT(_xlpm.day,"00"))) | AA37: =IF($Z37="","",TEXT($Z37,"mm")) | AB37: =IFERROR(CHOOSE(AA37,"መስከረም","ጥቅምት","ህዳር ","ታህሳስ ","ጥር ","የካቲት ","መጋቢት ","ሚይዚያ ","ግንቦት ","ሰኔ ","ሐምሌ ","ነሐሴ ","Pagume"),"") | AD37: =IF($D37="","",YEAR(D37)&"-W"&WEEKNUM(D37,2)) | AE37: =IF($K37="","",YEAR(K37)&"-W"&WEEKNUM(K37,2))
A38: 37 | E38: =IF(D38="","",IF(F38="paid",0,I38-J38)) | G38: =IF(F38="Paid","Settled",IF(E38="","",IF(E38<0,"Over Due",IF(E38<=10,"Due soon",IF(E38<=20,"FP need",IF(E38<=30,"Pending","Pending")))))) | H38: =IFERROR(CHOOSE($X38,"መስከረም","ጥቅምት","ህዳር ","ታህሳስ ","ጥር ","የካቲት ","መጋቢት ","ሚይዚያ ","ግንቦት ","ሰኔ ","ሐምሌ ","ነሐሴ ","Pagume"),"") | J38: =IF(D38="","-",$Q$1-D38) -> - | L38: =IF(E38="","",$Q$1+E38) | O38: {=SUMPRODUCT(($F38:$F38="Parcial")*ABS($C38:$C38-$N38:$N38))} -> 0 | W38: =IF($D38="","",_xlfn.LET(_xlpm.gDate,D38,_xlpm.ethYear,IF(_xlpm.gDate>=DATE(YEAR(_xlpm.gDate),9,11),YEAR(_xlpm.gDate)-7,YEAR(_xlpm.gDate)-8),_xlpm.prevEthYear,_xlpm.ethYear-1,_xlpm.startDate,IF(_xlpm.gDate>=DATE(YEAR(_xlpm.gDate),9,11),DATE(YEAR(_xlpm.gDate),9,11)+IF(MOD(_xlpm.prevEthYear,4)=3,1,0),DATE(YEAR(_xlpm.gDate)-1,9,11)+IF(MOD(_xlpm.prevEthYear,4)=3,1,0)),_xlpm.dayOfYear,_xlpm.gDate-_xlpm.startDate+1,_xlpm.month,IF(_xlpm.dayOfYear<=360,CEILING(_xlpm.dayOfYear/30,1),13),_xlpm.day,IF(_xlpm.month=13,_xlpm.dayOfYear-360,_xlpm.dayOfYear-(_xlpm.month-1)*30),TEXT(_xlpm.ethYear,"0000")&"-"&TEXT(_xlpm.month,"00")&"-"&TEXT(_xlpm.day,"00"))) | X38: =IF($W38="","",TEXT($W38,"mm")) | Y38: =IFERROR(CHOOSE(X38,"መስከረም","ጥቅምት","ህዳር ","ታህሳስ ","ጥር ","የካቲት ","መጋቢት ","ሚይዚያ ","ግንቦት ","ሰኔ ","ሐምሌ ","ነሐሴ ","Pagume"),"") | Z38: =IF($K38="","",_xlfn.LET(_xlpm.gDate,K38,_xlpm.ethYear,IF(_xlpm.gDate>=DATE(YEAR(_xlpm.gDate),9,11),YEAR(_xlpm.gDate)-7,YEAR(_xlpm.gDate)-8),_xlpm.prevEthYear,_xlpm.ethYear-1,_xlpm.startDate,IF(_xlpm.gDate>=DATE(YEAR(_xlpm.gDate),9,11),DATE(YEAR(_xlpm.gDate),9,11)+IF(MOD(_xlpm.prevEthYear,4)=3,1,0),DATE(YEAR(_xlpm.gDate)-1,9,11)+IF(MOD(_xlpm.prevEthYear,4)=3,1,0)),_xlpm.dayOfYear,_xlpm.gDate-_xlpm.startDate+1,_xlpm.month,IF(_xlpm.dayOfYear<=360,CEILING(_xlpm.dayOfYear/30,1),13),_xlpm.day,IF(_xlpm.month=13,_xlpm.dayOfYear-360,_xlpm.dayOfYear-(_xlpm.month-1)*30),TEXT(_xlpm.ethYear,"0000")&"-"&TEXT(_xlpm.month,"00")&"-"&TEXT(_xlpm.day,"00"))) | AA38: =IF($Z38="","",TEXT($Z38,"mm")) | AB38: =IFERROR(CHOOSE(AA38,"መስከረም","ጥቅምት","ህዳር ","ታህሳስ ","ጥር ","የካቲት ","መጋቢት ","ሚይዚያ ","ግንቦት ","ሰኔ ","ሐምሌ ","ነሐሴ ","Pagume"),"") | AD38: =IF($D38="","",YEAR(D38)&"-W"&WEEKNUM(D38,2)) | AE38: =IF($K38="","",YEAR(K38)&"-W"&WEEKNUM(K38,2))
A39: 1 | E39: =IF(D39="","",IF(F39="paid",0,I39-J39)) | G39: =IF(F39="Paid","Settled",IF(E39="","",IF(E39<0,"Over Due",IF(E39<=10,"Due soon",IF(E39<=20,"FP need",IF(E39<=30,"Pending","Pending")))))) | H39: =IFERROR(CHOOSE($X39,"መስከረም","ጥቅምት","ህዳር ","ታህሳስ ","ጥር ","የካቲት ","መጋቢት ","ሚይዚያ ","ግንቦት ","ሰኔ ","ሐምሌ ","ነሐሴ ","Pagume"),"") | J39: =IF(D39="","-",$Q$1-D39) -> - | L39: =IF(E39="","",$Q$1+E39) | O39: {=SUMPRODUCT(($F39:$F39="Parcial")*ABS($C39:$C39-$N39:$N39))} -> 0 | W39: =IF($D39="","",_xlfn.LET(_xlpm.gDate,D39,_xlpm.ethYear,IF(_xlpm.gDate>=DATE(YEAR(_xlpm.gDate),9,11),YEAR(_xlpm.gDate)-7,YEAR(_xlpm.gDate)-8),_xlpm.prevEthYear,_xlpm.ethYear-1,_xlpm.startDate,IF(_xlpm.gDate>=DATE(YEAR(_xlpm.gDate),9,11),DATE(YEAR(_xlpm.gDate),9,11)+IF(MOD(_xlpm.prevEthYear,4)=3,1,0),DATE(YEAR(_xlpm.gDate)-1,9,11)+IF(MOD(_xlpm.prevEthYear,4)=3,1,0)),_xlpm.dayOfYear,_xlpm.gDate-_xlpm.startDate+1,_xlpm.month,IF(_xlpm.dayOfYear<=360,CEILING(_xlpm.dayOfYear/30,1),13),_xlpm.day,IF(_xlpm.month=13,_xlpm.dayOfYear-360,_xlpm.dayOfYear-(_xlpm.month-1)*30),TEXT(_xlpm.ethYear,"0000")&"-"&TEXT(_xlpm.month,"00")&"-"&TEXT(_xlpm.day,"00"))) | X39: =IF($W39="","",TEXT($W39,"mm")) | Y39: =IFERROR(CHOOSE(X39,"መስከረም","ጥቅምት","ህዳር ","ታህሳስ ","ጥር ","የካቲት ","መጋቢት ","ሚይዚያ ","ግንቦት ","ሰኔ ","ሐምሌ ","ነሐሴ ","Pagume"),"") | Z39: =IF($K39="","",_xlfn.LET(_xlpm.gDate,K39,_xlpm.ethYear,IF(_xlpm.gDate>=DATE(YEAR(_xlpm.gDate),9,11),YEAR(_xlpm.gDate)-7,YEAR(_xlpm.gDate)-8),_xlpm.prevEthYear,_xlpm.ethYear-1,_xlpm.startDate,IF(_xlpm.gDate>=DATE(YEAR(_xlpm.gDate),9,11),DATE(YEAR(_xlpm.gDate),9,11)+IF(MOD(_xlpm.prevEthYear,4)=3,1,0),DATE(YEAR(_xlpm.gDate)-1,9,11)+IF(MOD(_xlpm.prevEthYear,4)=3,1,0)),_xlpm.dayOfYear,_xlpm.gDate-_xlpm.startDate+1,_xlpm.month,IF(_xlpm.dayOfYear<=360,CEILING(_xlpm.dayOfYear/30,1),13),_xlpm.day,IF(_xlpm.month=13,_xlpm.dayOfYear-360,_xlpm.dayOfYear-(_xlpm.month-1)*30),TEXT(_xlpm.ethYear,"0000")&"-"&TEXT(_xlpm.month,"00")&"-"&TEXT(_xlpm.day,"00"))) | AA39: =IF($Z39="","",TEXT($Z39,"mm")) | AB39: =IFERROR(CHOOSE(AA39,"መስከረም","ጥቅምት","ህዳር ","ታህሳስ ","ጥር ","የካቲት ","መጋቢት ","ሚይዚያ ","ግንቦት ","ሰኔ ","ሐምሌ ","ነሐሴ ","Pagume"),"") | AD39: =IF($D39="","",YEAR(D39)&"-W"&WEEKNUM(D39,2)) | AE39: =IF($K39="","",YEAR(K39)&"-W"&WEEKNUM(K39,2))
A40: 1 | E40: =IF(D40="","",IF(F40="paid",0,I40-J40)) | G40: =IF(F40="Paid","Settled",IF(E40="","",IF(E40<0,"Over Due",IF(E40<=10,"Due soon",IF(E40<=20,"FP need",IF(E40<=30,"Pending","Pending")))))) | H40: =IFERROR(CHOOSE($X40,"መስከረም","ጥቅምት","ህዳር ","ታህሳስ ","ጥር ","የካቲት ","መጋቢት ","ሚይዚያ ","ግንቦት ","ሰኔ ","ሐምሌ ","ነሐሴ ","Pagume"),"") | J40: =IF(D40="","-",$Q$1-D40) -> - | L40: =IF(E40="","",$Q$1+E40) | O40: {=SUMPRODUCT(($F40:$F40="Parcial")*ABS($C40:$C40-$N40:$N40))} -> 0 | W40: =IF($D40="","",_xlfn.LET(_xlpm.gDate,D40,_xlpm.ethYear,IF(_xlpm.gDate>=DATE(YEAR(_xlpm.gDate),9,11),YEAR(_xlpm.gDate)-7,YEAR(_xlpm.gDate)-8),_xlpm.prevEthYear,_xlpm.ethYear-1,_xlpm.startDate,IF(_xlpm.gDate>=DATE(YEAR(_xlpm.gDate),9,11),DATE(YEAR(_xlpm.gDate),9,11)+IF(MOD(_xlpm.prevEthYear,4)=3,1,0),DATE(YEAR(_xlpm.gDate)-1,9,11)+IF(MOD(_xlpm.prevEthYear,4)=3,1,0)),_xlpm.dayOfYear,_xlpm.gDate-_xlpm.startDate+1,_xlpm.month,IF(_xlpm.dayOfYear<=360,CEILING(_xlpm.dayOfYear/30,1),13),_xlpm.day,IF(_xlpm.month=13,_xlpm.dayOfYear-360,_xlpm.dayOfYear-(_xlpm.month-1)*30),TEXT(_xlpm.ethYear,"0000")&"-"&TEXT(_xlpm.month,"00")&"-"&TEXT(_xlpm.day,"00"))) | X40: =IF($W40="","",TEXT($W40,"mm")) | Y40: =IFERROR(CHOOSE(X40,"መስከረም","ጥቅምት","ህዳር ","ታህሳስ ","ጥር ","የካቲት ","መጋቢት ","ሚይዚያ ","ግንቦት ","ሰኔ ","ሐምሌ ","ነሐሴ ","Pagume"),"") | Z40: =IF($K40="","",_xlfn.LET(_xlpm.gDate,K40,_xlpm.ethYear,IF(_xlpm.gDate>=DATE(YEAR(_xlpm.gDate),9,11),YEAR(_xlpm.gDate)-7,YEAR(_xlpm.gDate)-8),_xlpm.prevEthYear,_xlpm.ethYear-1,_xlpm.startDate,IF(_xlpm.gDate>=DATE(YEAR(_xlpm.gDate),9,11),DATE(YEAR(_xlpm.gDate),9,11)+IF(MOD(_xlpm.prevEthYear,4)=3,1,0),DATE(YEAR(_xlpm.gDate)-1,9,11)+IF(MOD(_xlpm.prevEthYear,4)=3,1,0)),_xlpm.dayOfYear,_xlpm.gDate-_xlpm.startDate+1,_xlpm.month,IF(_xlpm.dayOfYear<=360,CEILING(_xlpm.dayOfYear/30,1),13),_xlpm.day,IF(_xlpm.month=13,_xlpm.dayOfYear-360,_xlpm.dayOfYear-(_xlpm.month-1)*30),TEXT(_xlpm.ethYear,"0000")&"-"&TEXT(_xlpm.month,"00")&"-"&TEXT(_xlpm.day,"00"))) | AA40: =IF($Z40="","",TEXT($Z40,"mm")) | AB40: =IFERROR(CHOOSE(AA40,"መስከረም","ጥቅምት","ህዳር ","ታህሳስ ","ጥር ","የካቲት ","መጋቢት ","ሚይዚያ ","ግንቦት ","ሰኔ ","ሐምሌ ","ነሐሴ ","Pagume"),"") | AD40: =IF($D40="","",YEAR(D40)&"-W"&WEEKNUM(D40,2)) | AE40: =IF($K40="","",YEAR(K40)&"-W"&WEEKNUM(K40,2))
A41: 1 | E41: =IF(D41="","",IF(F41="paid",0,I41-J41)) | G41: =IF(F41="Paid","Settled",IF(E41="","",IF(E41<0,"Over Due",IF(E41<=10,"Due soon",IF(E41<=20,"FP need",IF(E41<=30,"Pending","Pending")))))) | H41: =IFERROR(CHOOSE($X41,"መስከረም","ጥቅምት","ህዳር ","ታህሳስ ","ጥር ","የካቲት ","መጋቢት ","ሚይዚያ ","ግንቦት ","ሰኔ ","ሐምሌ ","ነሐሴ ","Pagume"),"") | J41: =IF(D41="","-",$Q$1-D41) -> - | L41: =IF(E41="","",$Q$1+E41) | O41: {=SUMPRODUCT(($F41:$F41="Parcial")*ABS($C41:$C41-$N41:$N41))} -> 0 | W41: =IF($D41="","",_xlfn.LET(_xlpm.gDate,D41,_xlpm.ethYear,IF(_xlpm.gDate>=DATE(YEAR(_xlpm.gDate),9,11),YEAR(_xlpm.gDate)-7,YEAR(_xlpm.gDate)-8),_xlpm.prevEthYear,_xlpm.ethYear-1,_xlpm.startDate,IF(_xlpm.gDate>=DATE(YEAR(_xlpm.gDate),9,11),DATE(YEAR(_xlpm.gDate),9,11)+IF(MOD(_xlpm.prevEthYear,4)=3,1,0),DATE(YEAR(_xlpm.gDate)-1,9,11)+IF(MOD(_xlpm.prevEthYear,4)=3,1,0)),_xlpm.dayOfYear,_xlpm.gDate-_xlpm.startDate+1,_xlpm.month,IF(_xlpm.dayOfYear<=360,CEILING(_xlpm.dayOfYear/30,1),13),_xlpm.day,IF(_xlpm.month=13,_xlpm.dayOfYear-360,_xlpm.dayOfYear-(_xlpm.month-1)*30),TEXT(_xlpm.ethYear,"0000")&"-"&TEXT(_xlpm.month,"00")&"-"&TEXT(_xlpm.day,"00"))) | X41: =IF($W41="","",TEXT($W41,"mm")) | Y41: =IFERROR(CHOOSE(X41,"መስከረም","ጥቅምት","ህዳር ","ታህሳስ ","ጥር ","የካቲት ","መጋቢት ","ሚይዚያ ","ግንቦት ","ሰኔ ","ሐምሌ ","ነሐሴ ","Pagume"),"") | Z41: =IF($K41="","",_xlfn.LET(_xlpm.gDate,K41,_xlpm.ethYear,IF(_xlpm.gDate>=DATE(YEAR(_xlpm.gDate),9,11),YEAR(_xlpm.gDate)-7,YEAR(_xlpm.gDate)-8),_xlpm.prevEthYear,_xlpm.ethYear-1,_xlpm.startDate,IF(_xlpm.gDate>=DATE(YEAR(_xlpm.gDate),9,11),DATE(YEAR(_xlpm.gDate),9,11)+IF(MOD(_xlpm.prevEthYear,4)=3,1,0),DATE(YEAR(_xlpm.gDate)-1,9,11)+IF(MOD(_xlpm.prevEthYear,4)=3,1,0)),_xlpm.dayOfYear,_xlpm.gDate-_xlpm.startDate+1,_xlpm.month,IF(_xlpm.dayOfYear<=360,CEILING(_xlpm.dayOfYear/30,1),13),_xlpm.day,IF(_xlpm.month=13,_xlpm.dayOfYear-360,_xlpm.dayOfYear-(_xlpm.month-1)*30),TEXT(_xlpm.ethYear,"0000")&"-"&TEXT(_xlpm.month,"00")&"-"&TEXT(_xlpm.day,"00"))) | AA41: =IF($Z41="","",TEXT($Z41,"mm")) | AB41: =IFERROR(CHOOSE(AA41,"መስከረም","ጥቅምት","ህዳር ","ታህሳስ ","ጥር ","የካቲት ","መጋቢት ","ሚይዚያ ","ግንቦት ","ሰኔ ","ሐምሌ ","ነሐሴ ","Pagume"),"") | AD41: =IF($D41="","",YEAR(D41)&"-W"&WEEKNUM(D41,2)) | AE41: =IF($K41="","",YEAR(K41)&"-W"&WEEKNUM(K41,2))
A42: 1 | E42: =IF(D42="","",IF(F42="paid",0,I42-J42)) | G42: =IF(F42="Paid","Settled",IF(E42="","",IF(E42<0,"Over Due",IF(E42<=10,"Due soon",IF(E42<=20,"FP need",IF(E42<=30,"Pending","Pending")))))) | H42: =IFERROR(CHOOSE($X42,"መስከረም","ጥቅምት","ህዳር ","ታህሳስ ","ጥር ","የካቲት ","መጋቢት ","ሚይዚያ ","ግንቦት ","ሰኔ ","ሐምሌ ","ነሐሴ ","Pagume"),"") | J42: =IF(D42="","-",$Q$1-D42) -> - | L42: =IF(E42="","",$Q$1+E42) | O42: {=SUMPRODUCT(($F42:$F42="Parcial")*ABS($C42:$C42-$N42:$N42))} -> 0 | W42: =IF($D42="","",_xlfn.LET(_xlpm.gDate,D42,_xlpm.ethYear,IF(_xlpm.gDate>=DATE(YEAR(_xlpm.gDate),9,11),YEAR(_xlpm.gDate)-7,YEAR(_xlpm.gDate)-8),_xlpm.prevEthYear,_xlpm.ethYear-1,_xlpm.startDate,IF(_xlpm.gDate>=DATE(YEAR(_xlpm.gDate),9,11),DATE(YEAR(_xlpm.gDate),9,11)+IF(MOD(_xlpm.prevEthYear,4)=3,1,0),DATE(YEAR(_xlpm.gDate)-1,9,11)+IF(MOD(_xlpm.prevEthYear,4)=3,1,0)),_xlpm.dayOfYear,_xlpm.gDate-_xlpm.startDate+1,_xlpm.month,IF(_xlpm.dayOfYear<=360,CEILING(_xlpm.dayOfYear/30,1),13),_xlpm.day,IF(_xlpm.month=13,_xlpm.dayOfYear-360,_xlpm.dayOfYear-(_xlpm.month-1)*30),TEXT(_xlpm.ethYear,"0000")&"-"&TEXT(_xlpm.month,"00")&"-"&TEXT(_xlpm.day,"00"))) | X42: =IF($W42="","",TEXT($W42,"mm")) | Y42: =IFERROR(CHOOSE(X42,"መስከረም","ጥቅምት","ህዳር ","ታህሳስ ","ጥር ","የካቲት ","መጋቢት ","ሚይዚያ ","ግንቦት ","ሰኔ ","ሐምሌ ","ነሐሴ ","Pagume"),"") | Z42: =IF($K42="","",_xlfn.LET(_xlpm.gDate,K42,_xlpm.ethYear,IF(_xlpm.gDate>=DATE(YEAR(_xlpm.gDate),9,11),YEAR(_xlpm.gDate)-7,YEAR(_xlpm.gDate)-8),_xlpm.prevEthYear,_xlpm.ethYear-1,_xlpm.startDate,IF(_xlpm.gDate>=DATE(YEAR(_xlpm.gDate),9,11),DATE(YEAR(_xlpm.gDate),9,11)+IF(MOD(_xlpm.prevEthYear,4)=3,1,0),DATE(YEAR(_xlpm.gDate)-1,9,11)+IF(MOD(_xlpm.prevEthYear,4)=3,1,0)),_xlpm.dayOfYear,_xlpm.gDate-_xlpm.startDate+1,_xlpm.month,IF(_xlpm.dayOfYear<=360,CEILING(_xlpm.dayOfYear/30,1),13),_xlpm.day,IF(_xlpm.month=13,_xlpm.dayOfYear-360,_xlpm.dayOfYear-(_xlpm.month-1)*30),TEXT(_xlpm.ethYear,"0000")&"-"&TEXT(_xlpm.month,"00")&"-"&TEXT(_xlpm.day,"00"))) | AA42: =IF($Z42="","",TEXT($Z42,"mm")) | AB42: =IFERROR(CHOOSE(AA42,"መስከረም","ጥቅምት","ህዳር ","ታህሳስ ","ጥር ","የካቲት ","መጋቢት ","ሚይዚያ ","ግንቦት ","ሰኔ ","ሐምሌ ","ነሐሴ ","Pagume"),"") | AD42: =IF($D42="","",YEAR(D42)&"-W"&WEEKNUM(D42,2)) | AE42: =IF($K42="","",YEAR(K42)&"-W"&WEEKNUM(K42,2))
A43: 1 | E43: =IF(D43="","",IF(F43="paid",0,I43-J43)) | G43: =IF(F43="Paid","Settled",IF(E43="","",IF(E43<0,"Over Due",IF(E43<=10,"Due soon",IF(E43<=20,"FP need",IF(E43<=30,"Pending","Pending")))))) | H43: =IFERROR(CHOOSE($X43,"መስከረም","ጥቅምት","ህዳር ","ታህሳስ ","ጥር ","የካቲት ","መጋቢት ","ሚይዚያ ","ግንቦት ","ሰኔ ","ሐምሌ ","ነሐሴ ","Pagume"),"") | J43: =IF(D43="","-",$Q$1-D43) -> - | L43: =IF(E43="","",$Q$1+E43) | O43: {=SUMPRODUCT(($F43:$F43="Parcial")*ABS($C43:$C43-$N43:$N43))} -> 0 | W43: =IF($D43="","",_xlfn.LET(_xlpm.gDate,D43,_xlpm.ethYear,IF(_xlpm.gDate>=DATE(YEAR(_xlpm.gDate),9,11),YEAR(_xlpm.gDate)-7,YEAR(_xlpm.gDate)-8),_xlpm.prevEthYear,_xlpm.ethYear-1,_xlpm.startDate,IF(_xlpm.gDate>=DATE(YEAR(_xlpm.gDate),9,11),DATE(YEAR(_xlpm.gDate),9,11)+IF(MOD(_xlpm.prevEthYear,4)=3,1,0),DATE(YEAR(_xlpm.gDate)-1,9,11)+IF(MOD(_xlpm.prevEthYear,4)=3,1,0)),_xlpm.dayOfYear,_xlpm.gDate-_xlpm.startDate+1,_xlpm.month,IF(_xlpm.dayOfYear<=360,CEILING(_xlpm.dayOfYear/30,1),13),_xlpm.day,IF(_xlpm.month=13,_xlpm.dayOfYear-360,_xlpm.dayOfYear-(_xlpm.month-1)*30),TEXT(_xlpm.ethYear,"0000")&"-"&TEXT(_xlpm.month,"00")&"-"&TEXT(_xlpm.day,"00"))) | X43: =IF($W43="","",TEXT($W43,"mm")) | Y43: =IFERROR(CHOOSE(X43,"መስከረም","ጥቅምት","ህዳር ","ታህሳስ ","ጥር ","የካቲት ","መጋቢት ","ሚይዚያ ","ግንቦት ","ሰኔ ","ሐምሌ ","ነሐሴ ","Pagume"),"") | Z43: =IF($K43="","",_xlfn.LET(_xlpm.gDate,K43,_xlpm.ethYear,IF(_xlpm.gDate>=DATE(YEAR(_xlpm.gDate),9,11),YEAR(_xlpm.gDate)-7,YEAR(_xlpm.gDate)-8),_xlpm.prevEthYear,_xlpm.ethYear-1,_xlpm.startDate,IF(_xlpm.gDate>=DATE(YEAR(_xlpm.gDate),9,11),DATE(YEAR(_xlpm.gDate),9,11)+IF(MOD(_xlpm.prevEthYear,4)=3,1,0),DATE(YEAR(_xlpm.gDate)-1,9,11)+IF(MOD(_xlpm.prevEthYear,4)=3,1,0)),_xlpm.dayOfYear,_xlpm.gDate-_xlpm.startDate+1,_xlpm.month,IF(_xlpm.dayOfYear<=360,CEILING(_xlpm.dayOfYear/30,1),13),_xlpm.day,IF(_xlpm.month=13,_xlpm.dayOfYear-360,_xlpm.dayOfYear-(_xlpm.month-1)*30),TEXT(_xlpm.ethYear,"0000")&"-"&TEXT(_xlpm.month,"00")&"-"&TEXT(_xlpm.day,"00"))) | AA43: =IF($Z43="","",TEXT($Z43,"mm")) | AB43: =IFERROR(CHOOSE(AA43,"መስከረም","ጥቅምት","ህዳር ","ታህሳስ ","ጥር ","የካቲት ","መጋቢት ","ሚይዚያ ","ግንቦት ","ሰኔ ","ሐምሌ ","ነሐሴ ","Pagume"),"") | AD43: =IF($D43="","",YEAR(D43)&"-W"&WEEKNUM(D43,2)) | AE43: =IF($K43="","",YEAR(K43)&"-W"&WEEKNUM(K43,2))
A44: 1 | E44: =IF(D44="","",IF(F44="paid",0,I44-J44)) | G44: =IF(F44="Paid","Settled",IF(E44="","",IF(E44<0,"Over Due",IF(E44<=10,"Due soon",IF(E44<=20,"FP need",IF(E44<=30,"Pending","Pending")))))) | H44: =IFERROR(CHOOSE($X44,"መስከረም","ጥቅምት","ህዳር ","ታህሳስ ","ጥር ","የካቲት ","መጋቢት ","ሚይዚያ ","ግንቦት ","ሰኔ ","ሐምሌ ","ነሐሴ ","Pagume"),"") | J44: =IF(D44="","-",$Q$1-D44) -> - | L44: =IF(E44="","",$Q$1+E44) | O44: {=SUMPRODUCT(($F44:$F44="Parcial")*ABS($C44:$C44-$N44:$N44))} -> 0 | W44: =IF($D44="","",_xlfn.LET(_xlpm.gDate,D44,_xlpm.ethYear,IF(_xlpm.gDate>=DATE(YEAR(_xlpm.gDate),9,11),YEAR(_xlpm.gDate)-7,YEAR(_xlpm.gDate)-8),_xlpm.prevEthYear,_xlpm.ethYear-1,_xlpm.startDate,IF(_xlpm.gDate>=DATE(YEAR(_xlpm.gDate),9,11),DATE(YEAR(_xlpm.gDate),9,11)+IF(MOD(_xlpm.prevEthYear,4)=3,1,0),DATE(YEAR(_xlpm.gDate)-1,9,11)+IF(MOD(_xlpm.prevEthYear,4)=3,1,0)),_xlpm.dayOfYear,_xlpm.gDate-_xlpm.startDate+1,_xlpm.month,IF(_xlpm.dayOfYear<=360,CEILING(_xlpm.dayOfYear/30,1),13),_xlpm.day,IF(_xlpm.month=13,_xlpm.dayOfYear-360,_xlpm.dayOfYear-(_xlpm.month-1)*30),TEXT(_xlpm.ethYear,"0000")&"-"&TEXT(_xlpm.month,"00")&"-"&TEXT(_xlpm.day,"00"))) | X44: =IF($W44="","",TEXT($W44,"mm")) | Y44: =IFERROR(CHOOSE(X44,"መስከረም","ጥቅምት","ህዳር ","ታህሳስ ","ጥር ","የካቲት ","መጋቢት ","ሚይዚያ ","ግንቦት ","ሰኔ ","ሐምሌ ","ነሐሴ ","Pagume"),"") | Z44: =IF($K44="","",_xlfn.LET(_xlpm.gDate,K44,_xlpm.ethYear,IF(_xlpm.gDate>=DATE(YEAR(_xlpm.gDate),9,11),YEAR(_xlpm.gDate)-7,YEAR(_xlpm.gDate)-8),_xlpm.prevEthYear,_xlpm.ethYear-1,_xlpm.startDate,IF(_xlpm.gDate>=DATE(YEAR(_xlpm.gDate),9,11),DATE(YEAR(_xlpm.gDate),9,11)+IF(MOD(_xlpm.prevEthYear,4)=3,1,0),DATE(YEAR(_xlpm.gDate)-1,9,11)+IF(MOD(_xlpm.prevEthYear,4)=3,1,0)),_xlpm.dayOfYear,_xlpm.gDate-_xlpm.startDate+1,_xlpm.month,IF(_xlpm.dayOfYear<=360,CEILING(_xlpm.dayOfYear/30,1),13),_xlpm.day,IF(_xlpm.month=13,_xlpm.dayOfYear-360,_xlpm.dayOfYear-(_xlpm.month-1)*30),TEXT(_xlpm.ethYear,"0000")&"-"&TEXT(_xlpm.month,"00")&"-"&TEXT(_xlpm.day,"00"))) | AA44: =IF($Z44="","",TEXT($Z44,"mm")) | AB44: =IFERROR(CHOOSE(AA44,"መስከረም","ጥቅምት","ህዳር ","ታህሳስ ","ጥር ","የካቲት ","መጋቢት ","ሚይዚያ ","ግንቦት ","ሰኔ ","ሐምሌ ","ነሐሴ ","Pagume"),"") | AD44: =IF($D44="","",YEAR(D44)&"-W"&WEEKNUM(D44,2)) | AE44: =IF($K44="","",YEAR(K44)&"-W"&WEEKNUM(K44,2))
A45: 1 | E45: =IF(D45="","",IF(F45="paid",0,I45-J45)) | G45: =IF(F45="Paid","Settled",IF(E45="","",IF(E45<0,"Over Due",IF(E45<=10,"Due soon",IF(E45<=20,"FP need",IF(E45<=30,"Pending","Pending")))))) | H45: =IFERROR(CHOOSE($X45,"መስከረም","ጥቅምት","ህዳር ","ታህሳስ ","ጥር ","የካቲት ","መጋቢት ","ሚይዚያ ","ግንቦት ","ሰኔ ","ሐምሌ ","ነሐሴ ","Pagume"),"") | J45: =IF(D45="","-",$Q$1-D45) -> - | L45: =IF(E45="","",$Q$1+E45) | O45: {=SUMPRODUCT(($F45:$F45="Parcial")*ABS($C45:$C45-$N45:$N45))} -> 0 | W45: =IF($D45="","",_xlfn.LET(_xlpm.gDate,D45,_xlpm.ethYear,IF(_xlpm.gDate>=DATE(YEAR(_xlpm.gDate),9,11),YEAR(_xlpm.gDate)-7,YEAR(_xlpm.gDate)-8),_xlpm.prevEthYear,_xlpm.ethYear-1,_xlpm.startDate,IF(_xlpm.gDate>=DATE(YEAR(_xlpm.gDate),9,11),DATE(YEAR(_xlpm.gDate),9,11)+IF(MOD(_xlpm.prevEthYear,4)=3,1,0),DATE(YEAR(_xlpm.gDate)-1,9,11)+IF(MOD(_xlpm.prevEthYear,4)=3,1,0)),_xlpm.dayOfYear,_xlpm.gDate-_xlpm.startDate+1,_xlpm.month,IF(_xlpm.dayOfYear<=360,CEILING(_xlpm.dayOfYear/30,1),13),_xlpm.day,IF(_xlpm.month=13,_xlpm.dayOfYear-360,_xlpm.dayOfYear-(_xlpm.month-1)*30),TEXT(_xlpm.ethYear,"0000")&"-"&TEXT(_xlpm.month,"00")&"-"&TEXT(_xlpm.day,"00"))) | X45: =IF($W45="","",TEXT($W45,"mm")) | Y45: =IFERROR(CHOOSE(X45,"መስከረም","ጥቅምት","ህዳር ","ታህሳስ ","ጥር ","የካቲት ","መጋቢት ","ሚይዚያ ","ግንቦት ","ሰኔ ","ሐምሌ ","ነሐሴ ","Pagume"),"") | Z45: =IF($K45="","",_xlfn.LET(_xlpm.gDate,K45,_xlpm.ethYear,IF(_xlpm.gDate>=DATE(YEAR(_xlpm.gDate),9,11),YEAR(_xlpm.gDate)-7,YEAR(_xlpm.gDate)-8),_xlpm.prevEthYear,_xlpm.ethYear-1,_xlpm.startDate,IF(_xlpm.gDate>=DATE(YEAR(_xlpm.gDate),9,11),DATE(YEAR(_xlpm.gDate),9,11)+IF(MOD(_xlpm.prevEthYear,4)=3,1,0),DATE(YEAR(_xlpm.gDate)-1,9,11)+IF(MOD(_xlpm.prevEthYear,4)=3,1,0)),_xlpm.dayOfYear,_xlpm.gDate-_xlpm.startDate+1,_xlpm.month,IF(_xlpm.dayOfYear<=360,CEILING(_xlpm.dayOfYear/30,1),13),_xlpm.day,IF(_xlpm.month=13,_xlpm.dayOfYear-360,_xlpm.dayOfYear-(_xlpm.month-1)*30),TEXT(_xlpm.ethYear,"0000")&"-"&TEXT(_xlpm.month,"00")&"-"&TEXT(_xlpm.day,"00"))) | AA45: =IF($Z45="","",TEXT($Z45,"mm")) | AB45: =IFERROR(CHOOSE(AA45,"መስከረም","ጥቅምት","ህዳር ","ታህሳስ ","ጥር ","የካቲት ","መጋቢት ","ሚይዚያ ","ግንቦት ","ሰኔ ","ሐምሌ ","ነሐሴ ","Pagume"),"") | AD45: =IF($D45="","",YEAR(D45)&"-W"&WEEKNUM(D45,2)) | AE45: =IF($K45="","",YEAR(K45)&"-W"&WEEKNUM(K45,2))
A46: 1 | E46: =IF(D46="","",IF(F46="paid",0,I46-J46)) | G46: =IF(F46="Paid","Settled",IF(E46="","",IF(E46<0,"Over Due",IF(E46<=10,"Due soon",IF(E46<=20,"FP need",IF(E46<=30,"Pending","Pending")))))) | H46: =IFERROR(CHOOSE($X46,"መስከረም","ጥቅምት","ህዳር ","ታህሳስ ","ጥር ","የካቲት ","መጋቢት ","ሚይዚያ ","ግንቦት ","ሰኔ ","ሐምሌ ","ነሐሴ ","Pagume"),"") | J46: =IF(D46="","-",$Q$1-D46) -> - | L46: =IF(E46="","",$Q$1+E46) | O46: {=SUMPRODUCT(($F46:$F46="Parcial")*ABS($C46:$C46-$N46:$N46))} -> 0 | W46: =IF($D46="","",_xlfn.LET(_xlpm.gDate,D46,_xlpm.ethYear,IF(_xlpm.gDate>=DATE(YEAR(_xlpm.gDate),9,11),YEAR(_xlpm.gDate)-7,YEAR(_xlpm.gDate)-8),_xlpm.prevEthYear,_xlpm.ethYear-1,_xlpm.startDate,IF(_xlpm.gDate>=DATE(YEAR(_xlpm.gDate),9,11),DATE(YEAR(_xlpm.gDate),9,11)+IF(MOD(_xlpm.prevEthYear,4)=3,1,0),DATE(YEAR(_xlpm.gDate)-1,9,11)+IF(MOD(_xlpm.prevEthYear,4)=3,1,0)),_xlpm.dayOfYear,_xlpm.gDate-_xlpm.startDate+1,_xlpm.month,IF(_xlpm.dayOfYear<=360,CEILING(_xlpm.dayOfYear/30,1),13),_xlpm.day,IF(_xlpm.month=13,_xlpm.dayOfYear-360,_xlpm.dayOfYear-(_xlpm.month-1)*30),TEXT(_xlpm.ethYear,"0000")&"-"&TEXT(_xlpm.month,"00")&"-"&TEXT(_xlpm.day,"00"))) | X46: =IF($W46="","",TEXT($W46,"mm")) | Y46: =IFERROR(CHOOSE(X46,"መስከረም","ጥቅምት","ህዳር ","ታህሳስ ","ጥር ","የካቲት ","መጋቢት ","ሚይዚያ ","ግንቦት ","ሰኔ ","ሐምሌ ","ነሐሴ ","Pagume"),"") | Z46: =IF($K46="","",_xlfn.LET(_xlpm.gDate,K46,_xlpm.ethYear,IF(_xlpm.gDate>=DATE(YEAR(_xlpm.gDate),9,11),YEAR(_xlpm.gDate)-7,YEAR(_xlpm.gDate)-8),_xlpm.prevEthYear,_xlpm.ethYear-1,_xlpm.startDate,IF(_xlpm.gDate>=DATE(YEAR(_xlpm.gDate),9,11),DATE(YEAR(_xlpm.gDate),9,11)+IF(MOD(_xlpm.prevEthYear,4)=3,1,0),DATE(YEAR(_xlpm.gDate)-1,9,11)+IF(MOD(_xlpm.prevEthYear,4)=3,1,0)),_xlpm.dayOfYear,_xlpm.gDate-_xlpm.startDate+1,_xlpm.month,IF(_xlpm.dayOfYear<=360,CEILING(_xlpm.dayOfYear/30,1),13),_xlpm.day,IF(_xlpm.month=13,_xlpm.dayOfYear-360,_xlpm.dayOfYear-(_xlpm.month-1)*30),TEXT(_xlpm.ethYear,"0000")&"-"&TEXT(_xlpm.month,"00")&"-"&TEXT(_xlpm.day,"00"))) | AA46: =IF($Z46="","",TEXT($Z46,"mm")) | AB46: =IFERROR(CHOOSE(AA46,"መስከረም","ጥቅምት","ህዳር ","ታህሳስ ","ጥር ","የካቲት ","መጋቢት ","ሚይዚያ ","ግንቦት ","ሰኔ ","ሐምሌ ","ነሐሴ ","Pagume"),"") | AD46: =IF($D46="","",YEAR(D46)&"-W"&WEEKNUM(D46,2)) | AE46: =IF($K46="","",YEAR(K46)&"-W"&WEEKNUM(K46,2))
... A96: 1 | E96: =IF(D96="","",IF(F96="paid",0,I96-J96)) | G96: =IF(F96="Paid","Settled",IF(E96="","",IF(E96<0,"Over Due",IF(E96<=10,"Due soon",IF(E96<=20,"FP need",IF(E96<=30,"Pending","Pending")))))) | H96: =IFERROR(CHOOSE($X96,"መስከረም","ጥቅምት","ህዳር ","ታህሳስ ","ጥር ","የካቲት ","መጋቢት ","ሚይዚያ ","ግንቦት ","ሰኔ ","ሐምሌ ","ነሐሴ ","Pagume"),"") | J96: =IF(D96="","-",$Q$1-D96) -> - | L96: =IF(E96="","",$Q$1+E96) | O96: {=SUMPRODUCT(($F96:$F96="Parcial")*ABS($C96:$C96-$N96:$N96))} -> 0 | W96: =IF($D96="","",_xlfn.LET(_xlpm.gDate,D96,_xlpm.ethYear,IF(_xlpm.gDate>=DATE(YEAR(_xlpm.gDate),9,11),YEAR(_xlpm.gDate)-7,YEAR(_xlpm.gDate)-8),_xlpm.prevEthYear,_xlpm.ethYear-1,_xlpm.startDate,IF(_xlpm.gDate>=DATE(YEAR(_xlpm.gDate),9,11),DATE(YEAR(_xlpm.gDate),9,11)+IF(MOD(_xlpm.prevEthYear,4)=3,1,0),DATE(YEAR(_xlpm.gDate)-1,9,11)+IF(MOD(_xlpm.prevEthYear,4)=3,1,0)),_xlpm.dayOfYear,_xlpm.gDate-_xlpm.startDate+1,_xlpm.month,IF(_xlpm.dayOfYear<=360,CEILING(_xlpm.dayOfYear/30,1),13),_xlpm.day,IF(_xlpm.month=13,_xlpm.dayOfYear-360,_xlpm.dayOfYear-(_xlpm.month-1)*30),TEXT(_xlpm.ethYear,"0000")&"-"&TEXT(_xlpm.month,"00")&"-"&TEXT(_xlpm.day,"00"))) | X96: =IF($W96="","",TEXT($W96,"mm")) | Y96: =IFERROR(CHOOSE(X96,"መስከረም","ጥቅምት","ህዳር ","ታህሳስ ","ጥር ","የካቲት ","መጋቢት ","ሚይዚያ ","ግንቦት ","ሰኔ ","ሐምሌ ","ነሐሴ ","Pagume"),"") | Z96: =IF($K96="","",_xlfn.LET(_xlpm.gDate,K96,_xlpm.ethYear,IF(_xlpm.gDate>=DATE(YEAR(_xlpm.gDate),9,11),YEAR(_xlpm.gDate)-7,YEAR(_xlpm.gDate)-8),_xlpm.prevEthYear,_xlpm.ethYear-1,_xlpm.startDate,IF(_xlpm.gDate>=DATE(YEAR(_xlpm.gDate),9,11),DATE(YEAR(_xlpm.gDate),9,11)+IF(MOD(_xlpm.prevEthYear,4)=3,1,0),DATE(YEAR(_xlpm.gDate)-1,9,11)+IF(MOD(_xlpm.prevEthYear,4)=3,1,0)),_xlpm.dayOfYear,_xlpm.gDate-_xlpm.startDate+1,_xlpm.month,IF(_xlpm.dayOfYear<=360,CEILING(_xlpm.dayOfYear/30,1),13),_xlpm.day,IF(_xlpm.month=13,_xlpm.dayOfYear-360,_xlpm.dayOfYear-(_xlpm.month-1)*30),TEXT(_xlpm.ethYear,"0000")&"-"&TEXT(_xlpm.month,"00")&"-"&TEXT(_xlpm.day,"00"))) | AA96: =IF($Z96="","",TEXT($Z96,"mm")) | AB96: =IFERROR(CHOOSE(AA96,"መስከረም","ጥቅምት","ህዳር ","ታህሳስ ","ጥር ","የካቲት ","መጋቢት ","ሚይዚያ ","ግንቦት ","ሰኔ ","ሐምሌ ","ነሐሴ ","Pagume"),"") | AD96: =IF($D96="","",YEAR(D96)&"-W"&WEEKNUM(D96,2)) | AE96: =IF($K96="","",YEAR(K96)&"-W"&WEEKNUM(K96,2))
A97: 2 | E97: =IF(D97="","",IF(F97="paid",0,I97-J97)) | G97: =IF(F97="Paid","Settled",IF(E97="","",IF(E97<0,"Over Due",IF(E97<=10,"Due soon",IF(E97<=20,"FP need",IF(E97<=30,"Pending","Pending")))))) | H97: =IFERROR(CHOOSE($X97,"መስከረም","ጥቅምት","ህዳር ","ታህሳስ ","ጥር ","የካቲት ","መጋቢት ","ሚይዚያ ","ግንቦት ","ሰኔ ","ሐምሌ ","ነሐሴ ","Pagume"),"") | J97: =IF(D97="","-",$Q$1-D97) -> - | L97: =IF(E97="","",$Q$1+E97) | O97: {=SUMPRODUCT(($F97:$F97="Parcial")*ABS($C97:$C97-$N97:$N97))} -> 0 | W97: =IF($D97="","",_xlfn.LET(_xlpm.gDate,D97,_xlpm.ethYear,IF(_xlpm.gDate>=DATE(YEAR(_xlpm.gDate),9,11),YEAR(_xlpm.gDate)-7,YEAR(_xlpm.gDate)-8),_xlpm.prevEthYear,_xlpm.ethYear-1,_xlpm.startDate,IF(_xlpm.gDate>=DATE(YEAR(_xlpm.gDate),9,11),DATE(YEAR(_xlpm.gDate),9,11)+IF(MOD(_xlpm.prevEthYear,4)=3,1,0),DATE(YEAR(_xlpm.gDate)-1,9,11)+IF(MOD(_xlpm.prevEthYear,4)=3,1,0)),_xlpm.dayOfYear,_xlpm.gDate-_xlpm.startDate+1,_xlpm.month,IF(_xlpm.dayOfYear<=360,CEILING(_xlpm.dayOfYear/30,1),13),_xlpm.day,IF(_xlpm.month=13,_xlpm.dayOfYear-360,_xlpm.dayOfYear-(_xlpm.month-1)*30),TEXT(_xlpm.ethYear,"0000")&"-"&TEXT(_xlpm.month,"00")&"-"&TEXT(_xlpm.day,"00"))) | X97: =IF($W97="","",TEXT($W97,"mm")) | Y97: =IFERROR(CHOOSE(X97,"መስከረም","ጥቅምት","ህዳር ","ታህሳስ ","ጥር ","የካቲት ","መጋቢት ","ሚይዚያ ","ግንቦት ","ሰኔ ","ሐምሌ ","ነሐሴ ","Pagume"),"") | Z97: =IF($K97="","",_xlfn.LET(_xlpm.gDate,K97,_xlpm.ethYear,IF(_xlpm.gDate>=DATE(YEAR(_xlpm.gDate),9,11),YEAR(_xlpm.gDate)-7,YEAR(_xlpm.gDate)-8),_xlpm.prevEthYear,_xlpm.ethYear-1,_xlpm.startDate,IF(_xlpm.gDate>=DATE(YEAR(_xlpm.gDate),9,11),DATE(YEAR(_xlpm.gDate),9,11)+IF(MOD(_xlpm.prevEthYear,4)=3,1,0),DATE(YEAR(_xlpm.gDate)-1,9,11)+IF(MOD(_xlpm.prevEthYear,4)=3,1,0)),_xlpm.dayOfYear,_xlpm.gDate-_xlpm.startDate+1,_xlpm.month,IF(_xlpm.dayOfYear<=360,CEILING(_xlpm.dayOfYear/30,1),13),_xlpm.day,IF(_xlpm.month=13,_xlpm.dayOfYear-360,_xlpm.dayOfYear-(_xlpm.month-1)*30),TEXT(_xlpm.ethYear,"0000")&"-"&TEXT(_xlpm.month,"00")&"-"&TEXT(_xlpm.day,"00"))) | AA97: =IF($Z97="","",TEXT($Z97,"mm")) | AB97: =IFERROR(CHOOSE(AA97,"መስከረም","ጥቅምት","ህዳር ","ታህሳስ ","ጥር ","የካቲት ","መጋቢት ","ሚይዚያ ","ግንቦት ","ሰኔ ","ሐምሌ ","ነሐሴ ","Pagume"),"") | AD97: =IF($D97="","",YEAR(D97)&"-W"&WEEKNUM(D97,2)) | AE97: =IF($K97="","",YEAR(K97)&"-W"&WEEKNUM(K97,2)) | AY97: {=_xlfn.UNIQUE(_xlfn._xlws.FILTER(B2:B1005,(COUNTIF(B2:B1005,B2:B1005)>1)*(F2:F1005="Credit ")))} -> Eman
A98: 3 | E98: =IF(D98="","",IF(F98="paid",0,I98-J98)) | G98: =IF(F98="Paid","Settled",IF(E98="","",IF(E98<0,"Over Due",IF(E98<=10,"Due soon",IF(E98<=20,"FP need",IF(E98<=30,"Pending","Pending")))))) | H98: =IFERROR(CHOOSE($X98,"መስከረም","ጥቅምት","ህዳር ","ታህሳስ ","ጥር ","የካቲት ","መጋቢት ","ሚይዚያ ","ግንቦት ","ሰኔ ","ሐምሌ ","ነሐሴ ","Pagume"),"") | J98: =IF(D98="","-",$Q$1-D98) -> - | L98: =IF(E98="","",$Q$1+E98) | O98: {=SUMPRODUCT(($F98:$F98="Parcial")*ABS($C98:$C98-$N98:$N98))} -> 0 | W98: =IF($D98="","",_xlfn.LET(_xlpm.gDate,D98,_xlpm.ethYear,IF(_xlpm.gDate>=DATE(YEAR(_xlpm.gDate),9,11),YEAR(_xlpm.gDate)-7,YEAR(_xlpm.gDate)-8),_xlpm.prevEthYear,_xlpm.ethYear-1,_xlpm.startDate,IF(_xlpm.gDate>=DATE(YEAR(_xlpm.gDate),9,11),DATE(YEAR(_xlpm.gDate),9,11)+IF(MOD(_xlpm.prevEthYear,4)=3,1,0),DATE(YEAR(_xlpm.gDate)-1,9,11)+IF(MOD(_xlpm.prevEthYear,4)=3,1,0)),_xlpm.dayOfYear,_xlpm.gDate-_xlpm.startDate+1,_xlpm.month,IF(_xlpm.dayOfYear<=360,CEILING(_xlpm.dayOfYear/30,1),13),_xlpm.day,IF(_xlpm.month=13,_xlpm.dayOfYear-360,_xlpm.dayOfYear-(_xlpm.month-1)*30),TEXT(_xlpm.ethYear,"0000")&"-"&TEXT(_xlpm.month,"00")&"-"&TEXT(_xlpm.day,"00"))) | X98: =IF($W98="","",TEXT($W98,"mm")) | Y98: =IFERROR(CHOOSE(X98,"መስከረም","ጥቅምት","ህዳር ","ታህሳስ ","ጥር ","የካቲት ","መጋቢት ","ሚይዚያ ","ግንቦት ","ሰኔ ","ሐምሌ ","ነሐሴ ","Pagume"),"") | Z98: =IF($K98="","",_xlfn.LET(_xlpm.gDate,K98,_xlpm.ethYear,IF(_xlpm.gDate>=DATE(YEAR(_xlpm.gDate),9,11),YEAR(_xlpm.gDate)-7,YEAR(_xlpm.gDate)-8),_xlpm.prevEthYear,_xlpm.ethYear-1,_xlpm.startDate,IF(_xlpm.gDate>=DATE(YEAR(_xlpm.gDate),9,11),DATE(YEAR(_xlpm.gDate),9,11)+IF(MOD(_xlpm.prevEthYear,4)=3,1,0),DATE(YEAR(_xlpm.gDate)-1,9,11)+IF(MOD(_xlpm.prevEthYear,4)=3,1,0)),_xlpm.dayOfYear,_xlpm.gDate-_xlpm.startDate+1,_xlpm.month,IF(_xlpm.dayOfYear<=360,CEILING(_xlpm.dayOfYear/30,1),13),_xlpm.day,IF(_xlpm.month=13,_xlpm.dayOfYear-360,_xlpm.dayOfYear-(_xlpm.month-1)*30),TEXT(_xlpm.ethYear,"0000")&"-"&TEXT(_xlpm.month,"00")&"-"&TEXT(_xlpm.day,"00"))) | AA98: =IF($Z98="","",TEXT($Z98,"mm")) | AB98: =IFERROR(CHOOSE(AA98,"መስከረም","ጥቅምት","ህዳር ","ታህሳስ ","ጥር ","የካቲት ","መጋቢት ","ሚይዚያ ","ግንቦት ","ሰኔ ","ሐምሌ ","ነሐሴ ","Pagume"),"") | AD98: =IF($D98="","",YEAR(D98)&"-W"&WEEKNUM(D98,2)) | AE98: =IF($K98="","",YEAR(K98)&"-W"&WEEKNUM(K98,2)) | AR98: {=_xlfn._xlws.FILTER(A2:E1005,(COUNTIF(B2:B1005,B2:B1005)>1)*(F2:F1005="Credit "))} -> 1 | AS98: Eman | AT98: 62000 | AU98: 46104 | AV98: -54 | AY98: wilget
A99: 4 | E99: =IF(D99="","",IF(F99="paid",0,I99-J99)) | G99: =IF(F99="Paid","Settled",IF(E99="","",IF(E99<0,"Over Due",IF(E99<=10,"Due soon",IF(E99<=20,"FP need",IF(E99<=30,"Pending","Pending")))))) | H99: =IFERROR(CHOOSE($X99,"መስከረም","ጥቅምት","ህዳር ","ታህሳስ ","ጥር ","የካቲት ","መጋቢት ","ሚይዚያ ","ግንቦት ","ሰኔ ","ሐምሌ ","ነሐሴ ","Pagume"),"") | J99: =IF(D99="","-",$Q$1-D99) -> - | L99: =IF(E99="","",$Q$1+E99) | O99: {=SUMPRODUCT(($F99:$F99="Parcial")*ABS($C99:$C99-$N99:$N99))} -> 0 | W99: =IF($D99="","",_xlfn.LET(_xlpm.gDate,D99,_xlpm.ethYear,IF(_xlpm.gDate>=DATE(YEAR(_xlpm.gDate),9,11),YEAR(_xlpm.gDate)-7,YEAR(_xlpm.gDate)-8),_xlpm.prevEthYear,_xlpm.ethYear-1,_xlpm.startDate,IF(_xlpm.gDate>=DATE(YEAR(_xlpm.gDate),9,11),DATE(YEAR(_xlpm.gDate),9,11)+IF(MOD(_xlpm.prevEthYear,4)=3,1,0),DATE(YEAR(_xlpm.gDate)-1,9,11)+IF(MOD(_xlpm.prevEthYear,4)=3,1,0)),_xlpm.dayOfYear,_xlpm.gDate-_xlpm.startDate+1,_xlpm.month,IF(_xlpm.dayOfYear<=360,CEILING(_xlpm.dayOfYear/30,1),13),_xlpm.day,IF(_xlpm.month=13,_xlpm.dayOfYear-360,_xlpm.dayOfYear-(_xlpm.month-1)*30),TEXT(_xlpm.ethYear,"0000")&"-"&TEXT(_xlpm.month,"00")&"-"&TEXT(_xlpm.day,"00"))) | X99: =IF($W99="","",TEXT($W99,"mm")) | Y99: =IFERROR(CHOOSE(X99,"መስከረም","ጥቅምት","ህዳር ","ታህሳስ ","ጥር ","የካቲት ","መጋቢት ","ሚይዚያ ","ግንቦት ","ሰኔ ","ሐምሌ ","ነሐሴ ","Pagume"),"") | Z99: =IF($K99="","",_xlfn.LET(_xlpm.gDate,K99,_xlpm.ethYear,IF(_xlpm.gDate>=DATE(YEAR(_xlpm.gDate),9,11),YEAR(_xlpm.gDate)-7,YEAR(_xlpm.gDate)-8),_xlpm.prevEthYear,_xlpm.ethYear-1,_xlpm.startDate,IF(_xlpm.gDate>=DATE(YEAR(_xlpm.gDate),9,11),DATE(YEAR(_xlpm.gDate),9,11)+IF(MOD(_xlpm.prevEthYear,4)=3,1,0),DATE(YEAR(_xlpm.gDate)-1,9,11)+IF(MOD(_xlpm.prevEthYear,4)=3,1,0)),_xlpm.dayOfYear,_xlpm.gDate-_xlpm.startDate+1,_xlpm.month,IF(_xlpm.dayOfYear<=360,CEILING(_xlpm.dayOfYear/30,1),13),_xlpm.day,IF(_xlpm.month=13,_xlpm.dayOfYear-360,_xlpm.dayOfYear-(_xlpm.month-1)*30),TEXT(_xlpm.ethYear,"0000")&"-"&TEXT(_xlpm.month,"00")&"-"&TEXT(_xlpm.day,"00"))) | AA99: =IF($Z99="","",TEXT($Z99,"mm")) | AB99: =IFERROR(CHOOSE(AA99,"መስከረም","ጥቅምት","ህዳር ","ታህሳስ ","ጥር ","የካቲት ","መጋቢት ","ሚይዚያ ","ግንቦት ","ሰኔ ","ሐምሌ ","ነሐሴ ","Pagume"),"") | AD99: =IF($D99="","",YEAR(D99)&"-W"&WEEKNUM(D99,2)) | AE99: =IF($K99="","",YEAR(K99)&"-W"&WEEKNUM(K99,2)) | AR99: 2 | AS99: Eman | AT99: 353600 | AU99: 46155 | AV99: -3 | AY99: Abune/A
A100: 5 | E100: =IF(D100="","",IF(F100="paid",0,I100-J100)) | G100: =IF(F100="Paid","Settled",IF(E100="","",IF(E100<0,"Over Due",IF(E100<=10,"Due soon",IF(E100<=20,"FP need",IF(E100<=30,"Pending","Pending")))))) | H100: =IFERROR(CHOOSE($X100,"መስከረም","ጥቅምት","ህዳር ","ታህሳስ ","ጥር ","የካቲት ","መጋቢት ","ሚይዚያ ","ግንቦት ","ሰኔ ","ሐምሌ ","ነሐሴ ","Pagume"),"") | J100: =IF(D100="","-",$Q$1-D100) -> - | L100: =IF(E100="","",$Q$1+E100) | O100: {=SUMPRODUCT(($F100:$F100="Parcial")*ABS($C100:$C100-$N100:$N100))} -> 0 | W100: =IF($D100="","",_xlfn.LET(_xlpm.gDate,D100,_xlpm.ethYear,IF(_xlpm.gDate>=DATE(YEAR(_xlpm.gDate),9,11),YEAR(_xlpm.gDate)-7,YEAR(_xlpm.gDate)-8),_xlpm.prevEthYear,_xlpm.ethYear-1,_xlpm.startDate,IF(_xlpm.gDate>=DATE(YEAR(_xlpm.gDate),9,11),DATE(YEAR(_xlpm.gDate),9,11)+IF(MOD(_xlpm.prevEthYear,4)=3,1,0),DATE(YEAR(_xlpm.gDate)-1,9,11)+IF(MOD(_xlpm.prevEthYear,4)=3,1,0)),_xlpm.dayOfYear,_xlpm.gDate-_xlpm.startDate+1,_xlpm.month,IF(_xlpm.dayOfYear<=360,CEILING(_xlpm.dayOfYear/30,1),13),_xlpm.day,IF(_xlpm.month=13,_xlpm.dayOfYear-360,_xlpm.dayOfYear-(_xlpm.month-1)*30),TEXT(_xlpm.ethYear,"0000")&"-"&TEXT(_xlpm.month,"00")&"-"&TEXT(_xlpm.day,"00"))) | X100: =IF($W100="","",TEXT($W100,"mm")) | Y100: =IFERROR(CHOOSE(X100,"መስከረም","ጥቅምት","ህዳር ","ታህሳስ ","ጥር ","የካቲት ","መጋቢት ","ሚይዚያ ","ግንቦት ","ሰኔ ","ሐምሌ ","ነሐሴ ","Pagume"),"") | Z100: =IF($K100="","",_xlfn.LET(_xlpm.gDate,K100,_xlpm.ethYear,IF(_xlpm.gDate>=DATE(YEAR(_xlpm.gDate),9,11),YEAR(_xlpm.gDate)-7,YEAR(_xlpm.gDate)-8),_xlpm.prevEthYear,_xlpm.ethYear-1,_xlpm.startDate,IF(_xlpm.gDate>=DATE(YEAR(_xlpm.gDate),9,11),DATE(YEAR(_xlpm.gDate),9,11)+IF(MOD(_xlpm.prevEthYear,4)=3,1,0),DATE(YEAR(_xlpm.gDate)-1,9,11)+IF(MOD(_xlpm.prevEthYear,4)=3,1,0)),_xlpm.dayOfYear,_xlpm.gDate-_xlpm.startDate+1,_xlpm.month,IF(_xlpm.dayOfYear<=360,CEILING(_xlpm.dayOfYear/30,1),13),_xlpm.day,IF(_xlpm.month=13,_xlpm.dayOfYear-360,_xlpm.dayOfYear-(_xlpm.month-1)*30),TEXT(_xlpm.ethYear,"0000")&"-"&TEXT(_xlpm.month,"00")&"-"&TEXT(_xlpm.day,"00"))) | AA100: =IF($Z100="","",TEXT($Z100,"mm")) | AB100: =IFERROR(CHOOSE(AA100,"መስከረም","ጥቅምት","ህዳር ","ታህሳስ ","ጥር ","የካቲት ","መጋቢት ","ሚይዚያ ","ግንቦት ","ሰኔ ","ሐምሌ ","ነሐሴ ","Pagume"),"") | AD100: =IF($D100="","",YEAR(D100)&"-W"&WEEKNUM(D100,2)) | AE100: =IF($K100="","",YEAR(K100)&"-W"&WEEKNUM(K100,2)) | AR100: 3 | AS100: wilget | AT100: 59900 | AU100: 46155 | AV100: -33 | AY100: Kidus/M
A101: 6 | E101: =IF(D101="","",IF(F101="paid",0,I101-J101)) | G101: =IF(F101="Paid","Settled",IF(E101="","",IF(E101<0,"Over Due",IF(E101<=10,"Due soon",IF(E101<=20,"FP need",IF(E101<=30,"Pending","Pending")))))) | H101: =IFERROR(CHOOSE($X101,"መስከረም","ጥቅምት","ህዳር ","ታህሳስ ","ጥር ","የካቲት ","መጋቢት ","ሚይዚያ ","ግንቦት ","ሰኔ ","ሐምሌ ","ነሐሴ ","Pagume"),"") | J101: =IF(D101="","-",$Q$1-D101) -> - | L101: =IF(E101="","",$Q$1+E101) | O101: {=SUMPRODUCT(($F101:$F101="Parcial")*ABS($C101:$C101-$N101:$N101))} -> 0 | W101: =IF($D101="","",_xlfn.LET(_xlpm.gDate,D101,_xlpm.ethYear,IF(_xlpm.gDate>=DATE(YEAR(_xlpm.gDate),9,11),YEAR(_xlpm.gDate)-7,YEAR(_xlpm.gDate)-8),_xlpm.prevEthYear,_xlpm.ethYear-1,_xlpm.startDate,IF(_xlpm.gDate>=DATE(YEAR(_xlpm.gDate),9,11),DATE(YEAR(_xlpm.gDate),9,11)+IF(MOD(_xlpm.prevEthYear,4)=3,1,0),DATE(YEAR(_xlpm.gDate)-1,9,11)+IF(MOD(_xlpm.prevEthYear,4)=3,1,0)),_xlpm.dayOfYear,_xlpm.gDate-_xlpm.startDate+1,_xlpm.month,IF(_xlpm.dayOfYear<=360,CEILING(_xlpm.dayOfYear/30,1),13),_xlpm.day,IF(_xlpm.month=13,_xlpm.dayOfYear-360,_xlpm.dayOfYear-(_xlpm.month-1)*30),TEXT(_xlpm.ethYear,"0000")&"-"&TEXT(_xlpm.month,"00")&"-"&TEXT(_xlpm.day,"00"))) | X101: =IF($W101="","",TEXT($W101,"mm")) | Y101: =IFERROR(CHOOSE(X101,"መስከረም","ጥቅምት","ህዳር ","ታህሳስ ","ጥር ","የካቲት ","መጋቢት ","ሚይዚያ ","ግንቦት ","ሰኔ ","ሐምሌ ","ነሐሴ ","Pagume"),"") | Z101: =IF($K101="","",_xlfn.LET(_xlpm.gDate,K101,_xlpm.ethYear,IF(_xlpm.gDate>=DATE(YEAR(_xlpm.gDate),9,11),YEAR(_xlpm.gDate)-7,YEAR(_xlpm.gDate)-8),_xlpm.prevEthYear,_xlpm.ethYear-1,_xlpm.startDate,IF(_xlpm.gDate>=DATE(YEAR(_xlpm.gDate),9,11),DATE(YEAR(_xlpm.gDate),9,11)+IF(MOD(_xlpm.prevEthYear,4)=3,1,0),DATE(YEAR(_xlpm.gDate)-1,9,11)+IF(MOD(_xlpm.prevEthYear,4)=3,1,0)),_xlpm.dayOfYear,_xlpm.gDate-_xlpm.startDate+1,_xlpm.month,IF(_xlpm.dayOfYear<=360,CEILING(_xlpm.dayOfYear/30,1),13),_xlpm.day,IF(_xlpm.month=13,_xlpm.dayOfYear-360,_xlpm.dayOfYear-(_xlpm.month-1)*30),TEXT(_xlpm.ethYear,"0000")&"-"&TEXT(_xlpm.month,"00")&"-"&TEXT(_xlpm.day,"00"))) | AA101: =IF($Z101="","",TEXT($Z101,"mm")) | AB101: =IFERROR(CHOOSE(AA101,"መስከረም","ጥቅምት","ህዳር ","ታህሳስ ","ጥር ","የካቲት ","መጋቢት ","ሚይዚያ ","ግንቦት ","ሰኔ ","ሐምሌ ","ነሐሴ ","Pagume"),"") | AD101: =IF($D101="","",YEAR(D101)&"-W"&WEEKNUM(D101,2)) | AE101: =IF($K101="","",YEAR(K101)&"-W"&WEEKNUM(K101,2)) | AR101: 4 | AS101: Abune/A | AT101: 43800 | AU101: 46157 | AV101: -31 | AY101: Jacaranda
A102: 7 | E102: =IF(D102="","",IF(F102="paid",0,I102-J102)) | G102: =IF(F102="Paid","Settled",IF(E102="","",IF(E102<0,"Over Due",IF(E102<=10,"Due soon",IF(E102<=20,"FP need",IF(E102<=30,"Pending","Pending")))))) | H102: =IFERROR(CHOOSE($X102,"መስከረም","ጥቅምት","ህዳር ","ታህሳስ ","ጥር ","የካቲት ","መጋቢት ","ሚይዚያ ","ግንቦት ","ሰኔ ","ሐምሌ ","ነሐሴ ","Pagume"),"") | J102: =IF(D102="","-",$Q$1-D102) -> - | L102: =IF(E102="","",$Q$1+E102) | O102: {=SUMPRODUCT(($F102:$F102="Parcial")*ABS($C102:$C102-$N102:$N102))} -> 0 | W102: =IF($D102="","",_xlfn.LET(_xlpm.gDate,D102,_xlpm.ethYear,IF(_xlpm.gDate>=DATE(YEAR(_xlpm.gDate),9,11),YEAR(_xlpm.gDate)-7,YEAR(_xlpm.gDate)-8),_xlpm.prevEthYear,_xlpm.ethYear-1,_xlpm.startDate,IF(_xlpm.gDate>=DATE(YEAR(_xlpm.gDate),9,11),DATE(YEAR(_xlpm.gDate),9,11)+IF(MOD(_xlpm.prevEthYear,4)=3,1,0),DATE(YEAR(_xlpm.gDate)-1,9,11)+IF(MOD(_xlpm.prevEthYear,4)=3,1,0)),_xlpm.dayOfYear,_xlpm.gDate-_xlpm.startDate+1,_xlpm.month,IF(_xlpm.dayOfYear<=360,CEILING(_xlpm.dayOfYear/30,1),13),_xlpm.day,IF(_xlpm.month=13,_xlpm.dayOfYear-360,_xlpm.dayOfYear-(_xlpm.month-1)*30),TEXT(_xlpm.ethYear,"0000")&"-"&TEXT(_xlpm.month,"00")&"-"&TEXT(_xlpm.day,"00"))) | X102: =IF($W102="","",TEXT($W102,"mm")) | Y102: =IFERROR(CHOOSE(X102,"መስከረም","ጥቅምት","ህዳር ","ታህሳስ ","ጥር ","የካቲት ","መጋቢት ","ሚይዚያ ","ግንቦት ","ሰኔ ","ሐምሌ ","ነሐሴ ","Pagume"),"") | Z102: =IF($K102="","",_xlfn.LET(_xlpm.gDate,K102,_xlpm.ethYear,IF(_xlpm.gDate>=DATE(YEAR(_xlpm.gDate),9,11),YEAR(_xlpm.gDate)-7,YEAR(_xlpm.gDate)-8),_xlpm.prevEthYear,_xlpm.ethYear-1,_xlpm.startDate,IF(_xlpm.gDate>=DATE(YEAR(_xlpm.gDate),9,11),DATE(YEAR(_xlpm.gDate),9,11)+IF(MOD(_xlpm.prevEthYear,4)=3,1,0),DATE(YEAR(_xlpm.gDate)-1,9,11)+IF(MOD(_xlpm.prevEthYear,4)=3,1,0)),_xlpm.dayOfYear,_xlpm.gDate-_xlpm.startDate+1,_xlpm.month,IF(_xlpm.dayOfYear<=360,CEILING(_xlpm.dayOfYear/30,1),13),_xlpm.day,IF(_xlpm.month=13,_xlpm.dayOfYear-360,_xlpm.dayOfYear-(_xlpm.month-1)*30),TEXT(_xlpm.ethYear,"0000")&"-"&TEXT(_xlpm.month,"00")&"-"&TEXT(_xlpm.day,"00"))) | AA102: =IF($Z102="","",TEXT($Z102,"mm")) | AB102: =IFERROR(CHOOSE(AA102,"መስከረም","ጥቅምት","ህዳር ","ታህሳስ ","ጥር ","የካቲት ","መጋቢት ","ሚይዚያ ","ግንቦት ","ሰኔ ","ሐምሌ ","ነሐሴ ","Pagume"),"") | AD102: =IF($D102="","",YEAR(D102)&"-W"&WEEKNUM(D102,2)) | AE102: =IF($K102="","",YEAR(K102)&"-W"&WEEKNUM(K102,2)) | AR102: 9 | AS102: Kidus/M | AT102: 21950 | AU102: 46165 | AV102: -23 | AY102: wajin
A103: 8 | E103: =IF(D103="","",IF(F103="paid",0,I103-J103)) | G103: =IF(F103="Paid","Settled",IF(E103="","",IF(E103<0,"Over Due",IF(E103<=10,"Due soon",IF(E103<=20,"FP need",IF(E103<=30,"Pending","Pending")))))) | H103: =IFERROR(CHOOSE($X103,"መስከረም","ጥቅምት","ህዳር ","ታህሳስ ","ጥር ","የካቲት ","መጋቢት ","ሚይዚያ ","ግንቦት ","ሰኔ ","ሐምሌ ","ነሐሴ ","Pagume"),"") | J103: =IF(D103="","-",$Q$1-D103) -> - | L103: =IF(E103="","",$Q$1+E103) | O103: {=SUMPRODUCT(($F103:$F103="Parcial")*ABS($C103:$C103-$N103:$N103))} -> 0 | W103: =IF($D103="","",_xlfn.LET(_xlpm.gDate,D103,_xlpm.ethYear,IF(_xlpm.gDate>=DATE(YEAR(_xlpm.gDate),9,11),YEAR(_xlpm.gDate)-7,YEAR(_xlpm.gDate)-8),_xlpm.prevEthYear,_xlpm.ethYear-1,_xlpm.startDate,IF(_xlpm.gDate>=DATE(YEAR(_xlpm.gDate),9,11),DATE(YEAR(_xlpm.gDate),9,11)+IF(MOD(_xlpm.prevEthYear,4)=3,1,0),DATE(YEAR(_xlpm.gDate)-1,9,11)+IF(MOD(_xlpm.prevEthYear,4)=3,1,0)),_xlpm.dayOfYear,_xlpm.gDate-_xlpm.startDate+1,_xlpm.month,IF(_xlpm.dayOfYear<=360,CEILING(_xlpm.dayOfYear/30,1),13),_xlpm.day,IF(_xlpm.month=13,_xlpm.dayOfYear-360,_xlpm.dayOfYear-(_xlpm.month-1)*30),TEXT(_xlpm.ethYear,"0000")&"-"&TEXT(_xlpm.month,"00")&"-"&TEXT(_xlpm.day,"00"))) | X103: =IF($W103="","",TEXT($W103,"mm")) | Y103: =IFERROR(CHOOSE(X103,"መስከረም","ጥቅምት","ህዳር ","ታህሳስ ","ጥር ","የካቲት ","መጋቢት ","ሚይዚያ ","ግንቦት ","ሰኔ ","ሐምሌ ","ነሐሴ ","Pagume"),"") | Z103: =IF($K103="","",_xlfn.LET(_xlpm.gDate,K103,_xlpm.ethYear,IF(_xlpm.gDate>=DATE(YEAR(_xlpm.gDate),9,11),YEAR(_xlpm.gDate)-7,YEAR(_xlpm.gDate)-8),_xlpm.prevEthYear,_xlpm.ethYear-1,_xlpm.startDate,IF(_xlpm.gDate>=DATE(YEAR(_xlpm.gDate),9,11),DATE(YEAR(_xlpm.gDate),9,11)+IF(MOD(_xlpm.prevEthYear,4)=3,1,0),DATE(YEAR(_xlpm.gDate)-1,9,11)+IF(MOD(_xlpm.prevEthYear,4)=3,1,0)),_xlpm.dayOfYear,_xlpm.gDate-_xlpm.startDate+1,_xlpm.month,IF(_xlpm.dayOfYear<=360,CEILING(_xlpm.dayOfYear/30,1),13),_xlpm.day,IF(_xlpm.month=13,_xlpm.dayOfYear-360,_xlpm.dayOfYear-(_xlpm.month-1)*30),TEXT(_xlpm.ethYear,"0000")&"-"&TEXT(_xlpm.month,"00")&"-"&TEXT(_xlpm.day,"00"))) | AA103: =IF($Z103="","",TEXT($Z103,"mm")) | AB103: =IFERROR(CHOOSE(AA103,"መስከረም","ጥቅምት","ህዳር ","ታህሳስ ","ጥር ","የካቲት ","መጋቢት ","ሚይዚያ ","ግንቦት ","ሰኔ ","ሐምሌ ","ነሐሴ ","Pagume"),"") | AD103: =IF($D103="","",YEAR(D103)&"-W"&WEEKNUM(D103,2)) | AE103: =IF($K103="","",YEAR(K103)&"-W"&WEEKNUM(K103,2)) | AR103: 10 | AS103: wilget | AT103: 85750 | AU103: 46165 | AV103: 7 | AY103: Yeorit pharm
A104: 9 | E104: =IF(D104="","",IF(F104="paid",0,I104-J104)) | G104: =IF(F104="Paid","Settled",IF(E104="","",IF(E104<0,"Over Due",IF(E104<=10,"Due soon",IF(E104<=20,"FP need",IF(E104<=30,"Pending","Pending")))))) | H104: =IFERROR(CHOOSE($X104,"መስከረም","ጥቅምት","ህዳር ","ታህሳስ ","ጥር ","የካቲት ","መጋቢት ","ሚይዚያ ","ግንቦት ","ሰኔ ","ሐምሌ ","ነሐሴ ","Pagume"),"") | J104: =IF(D104="","-",$Q$1-D104) -> - | L104: =IF(E104="","",$Q$1+E104) | O104: {=SUMPRODUCT(($F104:$F104="Parcial")*ABS($C104:$C104-$N104:$N104))} -> 0 | W104: =IF($D104="","",_xlfn.LET(_xlpm.gDate,D104,_xlpm.ethYear,IF(_xlpm.gDate>=DATE(YEAR(_xlpm.gDate),9,11),YEAR(_xlpm.gDate)-7,YEAR(_xlpm.gDate)-8),_xlpm.prevEthYear,_xlpm.ethYear-1,_xlpm.startDate,IF(_xlpm.gDate>=DATE(YEAR(_xlpm.gDate),9,11),DATE(YEAR(_xlpm.gDate),9,11)+IF(MOD(_xlpm.prevEthYear,4)=3,1,0),DATE(YEAR(_xlpm.gDate)-1,9,11)+IF(MOD(_xlpm.prevEthYear,4)=3,1,0)),_xlpm.dayOfYear,_xlpm.gDate-_xlpm.startDate+1,_xlpm.month,IF(_xlpm.dayOfYear<=360,CEILING(_xlpm.dayOfYear/30,1),13),_xlpm.day,IF(_xlpm.month=13,_xlpm.dayOfYear-360,_xlpm.dayOfYear-(_xlpm.month-1)*30),TEXT(_xlpm.ethYear,"0000")&"-"&TEXT(_xlpm.month,"00")&"-"&TEXT(_xlpm.day,"00"))) | X104: =IF($W104="","",TEXT($W104,"mm")) | Y104: =IFERROR(CHOOSE(X104,"መስከረም","ጥቅምት","ህዳር ","ታህሳስ ","ጥር ","የካቲት ","መጋቢት ","ሚይዚያ ","ግንቦት ","ሰኔ ","ሐምሌ ","ነሐሴ ","Pagume"),"") | Z104: =IF($K104="","",_xlfn.LET(_xlpm.gDate,K104,_xlpm.ethYear,IF(_xlpm.gDate>=DATE(YEAR(_xlpm.gDate),9,11),YEAR(_xlpm.gDate)-7,YEAR(_xlpm.gDate)-8),_xlpm.prevEthYear,_xlpm.ethYear-1,_xlpm.startDate,IF(_xlpm.gDate>=DATE(YEAR(_xlpm.gDate),9,11),DATE(YEAR(_xlpm.gDate),9,11)+IF(MOD(_xlpm.prevEthYear,4)=3,1,0),DATE(YEAR(_xlpm.gDate)-1,9,11)+IF(MOD(_xlpm.prevEthYear,4)=3,1,0)),_xlpm.dayOfYear,_xlpm.gDate-_xlpm.startDate+1,_xlpm.month,IF(_xlpm.dayOfYear<=360,CEILING(_xlpm.dayOfYear/30,1),13),_xlpm.day,IF(_xlpm.month=13,_xlpm.dayOfYear-360,_xlpm.dayOfYear-(_xlpm.month-1)*30),TEXT(_xlpm.ethYear,"0000")&"-"&TEXT(_xlpm.month,"00")&"-"&TEXT(_xlpm.day,"00"))) | AA104: =IF($Z104="","",TEXT($Z104,"mm")) | AB104: =IFERROR(CHOOSE(AA104,"መስከረም","ጥቅምት","ህዳር ","ታህሳስ ","ጥር ","የካቲት ","መጋቢት ","ሚይዚያ ","ግንቦት ","ሰኔ ","ሐምሌ ","ነሐሴ ","Pagume"),"") | AD104: =IF($D104="","",YEAR(D104)&"-W"&WEEKNUM(D104,2)) | AE104: =IF($K104="","",YEAR(K104)&"-W"&WEEKNUM(K104,2)) | AR104: 11 | AS104: Jacaranda | AT104: 60000 | AU104: 46168 | AV104: 10 | AY104: Azi Ws
A105: 10 | E105: =IF(D105="","",IF(F105="paid",0,I105-J105)) | G105: =IF(F105="Paid","Settled",IF(E105="","",IF(E105<0,"Over Due",IF(E105<=10,"Due soon",IF(E105<=20,"FP need",IF(E105<=30,"Pending","Pending")))))) | H105: =IFERROR(CHOOSE($X105,"መስከረም","ጥቅምት","ህዳር ","ታህሳስ ","ጥር ","የካቲት ","መጋቢት ","ሚይዚያ ","ግንቦት ","ሰኔ ","ሐምሌ ","ነሐሴ ","Pagume"),"") | J105: =IF(D105="","-",$Q$1-D105) -> - | L105: =IF(E105="","",$Q$1+E105) | O105: {=SUMPRODUCT(($F105:$F105="Parcial")*ABS($C105:$C105-$N105:$N105))} -> 0 | W105: =IF($D105="","",_xlfn.LET(_xlpm.gDate,D105,_xlpm.ethYear,IF(_xlpm.gDate>=DATE(YEAR(_xlpm.gDate),9,11),YEAR(_xlpm.gDate)-7,YEAR(_xlpm.gDate)-8),_xlpm.prevEthYear,_xlpm.ethYear-1,_xlpm.startDate,IF(_xlpm.gDate>=DATE(YEAR(_xlpm.gDate),9,11),DATE(YEAR(_xlpm.gDate),9,11)+IF(MOD(_xlpm.prevEthYear,4)=3,1,0),DATE(YEAR(_xlpm.gDate)-1,9,11)+IF(MOD(_xlpm.prevEthYear,4)=3,1,0)),_xlpm.dayOfYear,_xlpm.gDate-_xlpm.startDate+1,_xlpm.month,IF(_xlpm.dayOfYear<=360,CEILING(_xlpm.dayOfYear/30,1),13),_xlpm.day,IF(_xlpm.month=13,_xlpm.dayOfYear-360,_xlpm.dayOfYear-(_xlpm.month-1)*30),TEXT(_xlpm.ethYear,"0000")&"-"&TEXT(_xlpm.month,"00")&"-"&TEXT(_xlpm.day,"00"))) | X105: =IF($W105="","",TEXT($W105,"mm")) | Y105: =IFERROR(CHOOSE(X105,"መስከረም","ጥቅምት","ህዳር ","ታህሳስ ","ጥር ","የካቲት ","መጋቢት ","ሚይዚያ ","ግንቦት ","ሰኔ ","ሐምሌ ","ነሐሴ ","Pagume"),"") | Z105: =IF($K105="","",_xlfn.LET(_xlpm.gDate,K105,_xlpm.ethYear,IF(_xlpm.gDate>=DATE(YEAR(_xlpm.gDate),9,11),YEAR(_xlpm.gDate)-7,YEAR(_xlpm.gDate)-8),_xlpm.prevEthYear,_xlpm.ethYear-1,_xlpm.startDate,IF(_xlpm.gDate>=DATE(YEAR(_xlpm.gDate),9,11),DATE(YEAR(_xlpm.gDate),9,11)+IF(MOD(_xlpm.prevEthYear,4)=3,1,0),DATE(YEAR(_xlpm.gDate)-1,9,11)+IF(MOD(_xlpm.prevEthYear,4)=3,1,0)),_xlpm.dayOfYear,_xlpm.gDate-_xlpm.startDate+1,_xlpm.month,IF(_xlpm.dayOfYear<=360,CEILING(_xlpm.dayOfYear/30,1),13),_xlpm.day,IF(_xlpm.month=13,_xlpm.dayOfYear-360,_xlpm.dayOfYear-(_xlpm.month-1)*30),TEXT(_xlpm.ethYear,"0000")&"-"&TEXT(_xlpm.month,"00")&"-"&TEXT(_xlpm.day,"00"))) | AA105: =IF($Z105="","",TEXT($Z105,"mm")) | AB105: =IFERROR(CHOOSE(AA105,"መስከረም","ጥቅምት","ህዳር ","ታህሳስ ","ጥር ","የካቲት ","መጋቢት ","ሚይዚያ ","ግንቦት ","ሰኔ ","ሐምሌ ","ነሐሴ ","Pagume"),"") | AD105: =IF($D105="","",YEAR(D105)&"-W"&WEEKNUM(D105,2)) | AE105: =IF($K105="","",YEAR(K105)&"-W"&WEEKNUM(K105,2)) | AR105: 12 | AS105: Jacaranda | AT105: 89400 | AU105: 46176 | AV105: 18
A106: 11 | E106: =IF(D106="","",IF(F106="paid",0,I106-J106)) | G106: =IF(F106="Paid","Settled",IF(E106="","",IF(E106<0,"Over Due",IF(E106<=10,"Due soon",IF(E106<=20,"FP need",IF(E106<=30,"Pending","Pending")))))) | H106: =IFERROR(CHOOSE($X106,"መስከረም","ጥቅምት","ህዳር ","ታህሳስ ","ጥር ","የካቲት ","መጋቢት ","ሚይዚያ ","ግንቦት ","ሰኔ ","ሐምሌ ","ነሐሴ ","Pagume"),"") | J106: =IF(D106="","-",$Q$1-D106) -> - | L106: =IF(E106="","",$Q$1+E106) | O106: {=SUMPRODUCT(($F106:$F106="Parcial")*ABS($C106:$C106-$N106:$N106))} -> 0 | W106: =IF($D106="","",_xlfn.LET(_xlpm.gDate,D106,_xlpm.ethYear,IF(_xlpm.gDate>=DATE(YEAR(_xlpm.gDate),9,11),YEAR(_xlpm.gDate)-7,YEAR(_xlpm.gDate)-8),_xlpm.prevEthYear,_xlpm.ethYear-1,_xlpm.startDate,IF(_xlpm.gDate>=DATE(YEAR(_xlpm.gDate),9,11),DATE(YEAR(_xlpm.gDate),9,11)+IF(MOD(_xlpm.prevEthYear,4)=3,1,0),DATE(YEAR(_xlpm.gDate)-1,9,11)+IF(MOD(_xlpm.prevEthYear,4)=3,1,0)),_xlpm.dayOfYear,_xlpm.gDate-_xlpm.startDate+1,_xlpm.month,IF(_xlpm.dayOfYear<=360,CEILING(_xlpm.dayOfYear/30,1),13),_xlpm.day,IF(_xlpm.month=13,_xlpm.dayOfYear-360,_xlpm.dayOfYear-(_xlpm.month-1)*30),TEXT(_xlpm.ethYear,"0000")&"-"&TEXT(_xlpm.month,"00")&"-"&TEXT(_xlpm.day,"00"))) | X106: =IF($W106="","",TEXT($W106,"mm")) | Y106: =IFERROR(CHOOSE(X106,"መስከረም","ጥቅምት","ህዳር ","ታህሳስ ","ጥር ","የካቲት ","መጋቢት ","ሚይዚያ ","ግንቦት ","ሰኔ ","ሐምሌ ","ነሐሴ ","Pagume"),"") | Z106: =IF($K106="","",_xlfn.LET(_xlpm.gDate,K106,_xlpm.ethYear,IF(_xlpm.gDate>=DATE(YEAR(_xlpm.gDate),9,11),YEAR(_xlpm.gDate)-7,YEAR(_xlpm.gDate)-8),_xlpm.prevEthYear,_xlpm.ethYear-1,_xlpm.startDate,IF(_xlpm.gDate>=DATE(YEAR(_xlpm.gDate),9,11),DATE(YEAR(_xlpm.gDate),9,11)+IF(MOD(_xlpm.prevEthYear,4)=3,1,0),DATE(YEAR(_xlpm.gDate)-1,9,11)+IF(MOD(_xlpm.prevEthYear,4)=3,1,0)),_xlpm.dayOfYear,_xlpm.gDate-_xlpm.startDate+1,_xlpm.month,IF(_xlpm.dayOfYear<=360,CEILING(_xlpm.dayOfYear/30,1),13),_xlpm.day,IF(_xlpm.month=13,_xlpm.dayOfYear-360,_xlpm.dayOfYear-(_xlpm.month-1)*30),TEXT(_xlpm.ethYear,"0000")&"-"&TEXT(_xlpm.month,"00")&"-"&TEXT(_xlpm.day,"00"))) | AA106: =IF($Z106="","",TEXT($Z106,"mm")) | AB106: =IFERROR(CHOOSE(AA106,"መስከረም","ጥቅምት","ህዳር ","ታህሳስ ","ጥር ","የካቲት ","መጋቢት ","ሚይዚያ ","ግንቦት ","ሰኔ ","ሐምሌ ","ነሐሴ ","Pagume"),"") | AD106: =IF($D106="","",YEAR(D106)&"-W"&WEEKNUM(D106,2)) | AE106: =IF($K106="","",YEAR(K106)&"-W"&WEEKNUM(K106,2)) | AR106: 14 | AS106: wajin | AT106: 102000 | AU106: 46177 | AV106: 19
A107: 12 | E107: =IF(D107="","",IF(F107="paid",0,I107-J107)) | G107: =IF(F107="Paid","Settled",IF(E107="","",IF(E107<0,"Over Due",IF(E107<=10,"Due soon",IF(E107<=20,"FP need",IF(E107<=30,"Pending","Pending")))))) | H107: =IFERROR(CHOOSE($X107,"መስከረም","ጥቅምት","ህዳር ","ታህሳስ ","ጥር ","የካቲት ","መጋቢት ","ሚይዚያ ","ግንቦት ","ሰኔ ","ሐምሌ ","ነሐሴ ","Pagume"),"") | J107: =IF(D107="","-",$Q$1-D107) -> - | L107: =IF(E107="","",$Q$1+E107) | O107: {=SUMPRODUCT(($F107:$F107="Parcial")*ABS($C107:$C107-$N107:$N107))} -> 0 | W107: =IF($D107="","",_xlfn.LET(_xlpm.gDate,D107,_xlpm.ethYear,IF(_xlpm.gDate>=DATE(YEAR(_xlpm.gDate),9,11),YEAR(_xlpm.gDate)-7,YEAR(_xlpm.gDate)-8),_xlpm.prevEthYear,_xlpm.ethYear-1,_xlpm.startDate,IF(_xlpm.gDate>=DATE(YEAR(_xlpm.gDate),9,11),DATE(YEAR(_xlpm.gDate),9,11)+IF(MOD(_xlpm.prevEthYear,4)=3,1,0),DATE(YEAR(_xlpm.gDate)-1,9,11)+IF(MOD(_xlpm.prevEthYear,4)=3,1,0)),_xlpm.dayOfYear,_xlpm.gDate-_xlpm.startDate+1,_xlpm.month,IF(_xlpm.dayOfYear<=360,CEILING(_xlpm.dayOfYear/30,1),13),_xlpm.day,IF(_xlpm.month=13,_xlpm.dayOfYear-360,_xlpm.dayOfYear-(_xlpm.month-1)*30),TEXT(_xlpm.ethYear,"0000")&"-"&TEXT(_xlpm.month,"00")&"-"&TEXT(_xlpm.day,"00"))) | X107: =IF($W107="","",TEXT($W107,"mm")) | Y107: =IFERROR(CHOOSE(X107,"መስከረም","ጥቅምት","ህዳር ","ታህሳስ ","ጥር ","የካቲት ","መጋቢት ","ሚይዚያ ","ግንቦት ","ሰኔ ","ሐምሌ ","ነሐሴ ","Pagume"),"") | Z107: =IF($K107="","",_xlfn.LET(_xlpm.gDate,K107,_xlpm.ethYear,IF(_xlpm.gDate>=DATE(YEAR(_xlpm.gDate),9,11),YEAR(_xlpm.gDate)-7,YEAR(_xlpm.gDate)-8),_xlpm.prevEthYear,_xlpm.ethYear-1,_xlpm.startDate,IF(_xlpm.gDate>=DATE(YEAR(_xlpm.gDate),9,11),DATE(YEAR(_xlpm.gDate),9,11)+IF(MOD(_xlpm.prevEthYear,4)=3,1,0),DATE(YEAR(_xlpm.gDate)-1,9,11)+IF(MOD(_xlpm.prevEthYear,4)=3,1,0)),_xlpm.dayOfYear,_xlpm.gDate-_xlpm.startDate+1,_xlpm.month,IF(_xlpm.dayOfYear<=360,CEILING(_xlpm.dayOfYear/30,1),13),_xlpm.day,IF(_xlpm.month=13,_xlpm.dayOfYear-360,_xlpm.dayOfYear-(_xlpm.month-1)*30),TEXT(_xlpm.ethYear,"0000")&"-"&TEXT(_xlpm.month,"00")&"-"&TEXT(_xlpm.day,"00"))) | AA107: =IF($Z107="","",TEXT($Z107,"mm")) | AB107: =IFERROR(CHOOSE(AA107,"መስከረም","ጥቅምት","ህዳር ","ታህሳስ ","ጥር ","የካቲት ","መጋቢት ","ሚይዚያ ","ግንቦት ","ሰኔ ","ሐምሌ ","ነሐሴ ","Pagume"),"") | AD107: =IF($D107="","",YEAR(D107)&"-W"&WEEKNUM(D107,2)) | AE107: =IF($K107="","",YEAR(K107)&"-W"&WEEKNUM(K107,2)) | AR107: 15 | AS107: Kidus/M | AT107: 6000 | AU107: 46178 | AV107: -10
A108: 13 | E108: =IF(D108="","",IF(F108="paid",0,I108-J108)) | G108: =IF(F108="Paid","Settled",IF(E108="","",IF(E108<0,"Over Due",IF(E108<=10,"Due soon",IF(E108<=20,"FP need",IF(E108<=30,"Pending","Pending")))))) | H108: =IFERROR(CHOOSE($X108,"መስከረም","ጥቅምት","ህዳር ","ታህሳስ ","ጥር ","የካቲት ","መጋቢት ","ሚይዚያ ","ግንቦት ","ሰኔ ","ሐምሌ ","ነሐሴ ","Pagume"),"") | J108: =IF(D108="","-",$Q$1-D108) -> - | L108: =IF(E108="","",$Q$1+E108) | O108: {=SUMPRODUCT(($F108:$F108="Parcial")*ABS($C108:$C108-$N108:$N108))} -> 0 | W108: =IF($D108="","",_xlfn.LET(_xlpm.gDate,D108,_xlpm.ethYear,IF(_xlpm.gDate>=DATE(YEAR(_xlpm.gDate),9,11),YEAR(_xlpm.gDate)-7,YEAR(_xlpm.gDate)-8),_xlpm.prevEthYear,_xlpm.ethYear-1,_xlpm.startDate,IF(_xlpm.gDate>=DATE(YEAR(_xlpm.gDate),9,11),DATE(YEAR(_xlpm.gDate),9,11)+IF(MOD(_xlpm.prevEthYear,4)=3,1,0),DATE(YEAR(_xlpm.gDate)-1,9,11)+IF(MOD(_xlpm.prevEthYear,4)=3,1,0)),_xlpm.dayOfYear,_xlpm.gDate-_xlpm.startDate+1,_xlpm.month,IF(_xlpm.dayOfYear<=360,CEILING(_xlpm.dayOfYear/30,1),13),_xlpm.day,IF(_xlpm.month=13,_xlpm.dayOfYear-360,_xlpm.dayOfYear-(_xlpm.month-1)*30),TEXT(_xlpm.ethYear,"0000")&"-"&TEXT(_xlpm.month,"00")&"-"&TEXT(_xlpm.day,"00"))) | X108: =IF($W108="","",TEXT($W108,"mm")) | Y108: =IFERROR(CHOOSE(X108,"መስከረም","ጥቅምት","ህዳር ","ታህሳስ ","ጥር ","የካቲት ","መጋቢት ","ሚይዚያ ","ግንቦት ","ሰኔ ","ሐምሌ ","ነሐሴ ","Pagume"),"") | Z108: =IF($K108="","",_xlfn.LET(_xlpm.gDate,K108,_xlpm.ethYear,IF(_xlpm.gDate>=DATE(YEAR(_xlpm.gDate),9,11),YEAR(_xlpm.gDate)-7,YEAR(_xlpm.gDate)-8),_xlpm.prevEthYear,_xlpm.ethYear-1,_xlpm.startDate,IF(_xlpm.gDate>=DATE(YEAR(_xlpm.gDate),9,11),DATE(YEAR(_xlpm.gDate),9,11)+IF(MOD(_xlpm.prevEthYear,4)=3,1,0),DATE(YEAR(_xlpm.gDate)-1,9,11)+IF(MOD(_xlpm.prevEthYear,4)=3,1,0)),_xlpm.dayOfYear,_xlpm.gDate-_xlpm.startDate+1,_xlpm.month,IF(_xlpm.dayOfYear<=360,CEILING(_xlpm.dayOfYear/30,1),13),_xlpm.day,IF(_xlpm.month=13,_xlpm.dayOfYear-360,_xlpm.dayOfYear-(_xlpm.month-1)*30),TEXT(_xlpm.ethYear,"0000")&"-"&TEXT(_xlpm.month,"00")&"-"&TEXT(_xlpm.day,"00"))) | AA108: =IF($Z108="","",TEXT($Z108,"mm")) | AB108: =IFERROR(CHOOSE(AA108,"መስከረም","ጥቅምት","ህዳር ","ታህሳስ ","ጥር ","የካቲት ","መጋቢት ","ሚይዚያ ","ግንቦት ","ሰኔ ","ሐምሌ ","ነሐሴ ","Pagume"),"") | AD108: =IF($D108="","",YEAR(D108)&"-W"&WEEKNUM(D108,2)) | AE108: =IF($K108="","",YEAR(K108)&"-W"&WEEKNUM(K108,2)) | AR108: 16 | AS108: Wajin | AT108: 110000 | AU108: 46182 | AV108: 24
